Workbook

Sheet LEEME
A1: PLAN FINANCIERO PERSONAL · cómo se usa
A2: Viene con datos ficticios de ejemplo. Para usarlo con los tuyos, sigue docs/GUIA_DESPLIEGUE.md del repositorio.
A4: Cada mes
A5: 1. Descarga | B5: Los movimientos de tus bancos, en el formato que te da cada uno. Ya se reconocen Openbank (cuenta y tarjeta), CaixaBank e ING; otro banco se añade en BANCOS, en el importador.
A6: 2. Déjalos | B6: En la carpeta «Movimientos», junto a este sheet (se crea sola la primera vez que importas).
A7: 3. Importa | B7: Menú Plan financiero → Importar movimientos. No duplica lo que ya estaba, aunque las descargas se solapen.
A8: 4. Revisa | B8: En MOVIMIENTOS, lo amarillo (Bizum, ingresos en efectivo…): elige categoría y explica en Nota.
A10: Qué tocas
A11: MOVIMIENTOS | B11: Solo las columnas Categoría y Nota.
A12: REGLAS | B12: Para que un concepto se categorice solo la próxima vez.
A13: CATEGORÍAS | B13: Qué cuenta como ingreso, gasto o traspaso, y qué es de la casa.
A14: PARÁMETROS | B14: Edad, jubilación, rentabilidades, pensión. Gastos y ahorro salen de tus datos, pero puedes escribir encima.
A15: FLEXIBLE | B15: Si tienes retribución flexible: lo que se descuenta de tu nómina cada mes.
A16: DECISIONES | B16: ¿Y si invierto parte del efectivo, recorto gastos, compro vivienda ahora o dentro de unos años…?
A17: HISTORIAL | B17: Cada vez que cambias una cifra del plan, apunta aquí qué, de qué a qué y por qué.
A18: VIVIENDA · INMUEBLES | B18: Precio, hipoteca y alquiler; y lo que tengas en ladrillo.
A19: VIAJES | B19: Tu cuenta de viajes: lo que aportas al mes, tu parte de cada viaje, si llega, y qué pasa si aportas otra cantidad.
A21: Qué miras
A22: MI FUTURO | B22: El panel: nivel, patrimonio, jubilación, hitos, medallas de ahorro, decisiones y gráficos.
A23: CASA | B23: Gastos de la vivienda por concepto y mes.
A24: MIS DATOS | B24: Saldos de fin de mes e ingresos y gastos, solos.
A25: PANEL_DATOS | B25: Lo que lee el dashboard. No se toca.
A27: Colores | B27: Amarillo con texto azul = lo cambias tú · Verde = viene de otra pestaña o de tus datos · Negro = fórmula.
A28: Ojo | B28: Es una herramienta de planificación, no asesoramiento financiero ni fiscal. Las rentabilidades son supuestos.

Sheet MI FUTURO
A1: MI FUTURO FINANCIERO
A2: ="Datos ficticios de ejemplo a "&TEXT(PROYECCIÓN!$B$4,"mmmm yyyy")&" · estimados: precio de la vivienda y pensión" -> Datos ficticios de ejemplo a September 2026 · estimados: precio de la vivienda y pensión
A4: TU NIVEL | C4: PATRIMONIO LÍQUIDO HOY | E4: LIBERTAD FINANCIERA HOY | H4: ="CUENTA DE VIAJES · FIN DE "&VIAJES!$B$7 -> CUENTA DE VIAJES · FIN DE 2026
A5: =INDEX(PARÁMETROS!$B$25:$B$31,MATCH(PROYECCIÓN!$M$15,PARÁMETROS!$A$25:$A$31,1)) -> 🛡️ Escudo | C5: =PROYECCIÓN!$B$8 -> 67957.06 | E5: =PROYECCIÓN!$M$15 -> 0.13724131 | H5: =VIAJES!$B$10 -> 1900
A6: =IFERROR(REPT("█",ROUND((PROYECCIÓN!$M$15-INDEX(PARÁMETROS!$A$25:$A$31,MATCH(PROYECCIÓN!$M$15,PARÁMETROS!$A$25:$A$31,1)))/(INDEX(PARÁMETROS!$A$25:$A$31,MATCH(PROYECCIÓN!$M$15,PARÁMETROS!$A$25:$A$31,1)+1)-INDEX(PARÁMETROS!$A$25:$A$31,MATCH(PROYECCIÓN!$M$15,PARÁMETROS!$A$25:$A$31,1)))*10,0))&REPT("░",10-ROUND((PROYECCIÓN!$M$15-INDEX(PARÁMETROS!$A$25:$A$31,MATCH(PROYECCIÓN!$M$15,PARÁMETROS!$A$25:$A$31,1)))/(INDEX(PARÁMETROS!$A$25:$A$31,MATCH(PROYECCIÓN!$M$15,PARÁMETROS!$A$25:$A$31,1)+1)-INDEX(PARÁMETROS!$A$25:$A$31,MATCH(PROYECCIÓN!$M$15,PARÁMETROS!$A$25:$A$31,1)))*10,0)),"██████████") -> █████████░ | C6: ="Con tus inmuebles: "&TEXT(PROYECCIÓN!$B$10,"#,##0")&" €" -> Con tus inmuebles: 67,957 € | E6: =REPT("█",ROUND(MIN(1,PROYECCIÓN!$M$15)*20,0))&REPT("░",20-ROUND(MIN(1,PROYECCIÓN!$M$15)*20,0)) -> ███░░░░░░░░░░░░░░░░░ | H6: ="Aportas "&TEXT(VIAJES!$B$4,"#,##0")&" €/mes · "&VIAJES!$B$11&" viajes en "&VIAJES!$B$7 -> Aportas 150 €/mes · 2 viajes en 2026
A7: =IFERROR("Siguiente: "&INDEX(PARÁMETROS!$B$25:$B$31,MATCH(PROYECCIÓN!$M$15,PARÁMETROS!$A$25:$A$31,1)+1)&" al "&TEXT(INDEX(PARÁMETROS!$A$25:$A$31,MATCH(PROYECCIÓN!$M$15,PARÁMETROS!$A$25:$A$31,1)+1),"0%"),"Nivel máximo") -> Siguiente: 🧭 Brújula al 15% | C7: ="CaixaBank "&TEXT(INDEX('MIS DATOS'!$B$6:$B$245,COUNT('MIS DATOS'!$A$6:$A$245)),"#,##0")&" · Openbank "&TEXT(INDEX('MIS DATOS'!$C$6:$C$245,COUNT('MIS DATOS'!$A$6:$A$245)),"#,##0")&" · ING "&TEXT(INDEX('MIS DATOS'!$D$6:$D$245,COUNT('MIS DATOS'!$A$6:$A$245)),"#,##0") -> CaixaBank 10,501 · Openbank 1,450 · ING 56,006 | E7: ="Tu dinero cubre el "&TEXT(PROYECCIÓN!$M$15,"0%")&" de tus gastos (regla del "&TEXT(PARÁMETROS!$B$16,"0%")&")" -> Tu dinero cubre el 14% de tus gastos (regla del 4%) | H7: =VIAJES!$B$12 -> ✅ Llega para todos los viajes apuntados
A8: ="🏠 Casa: "&TEXT(CASA!$O$13,"#,##0")&" €/mes de media · 🧾 Por revisar: "&COUNTIFS(MOVIMIENTOS!$H$4:$H$20000,"Por revisar",MOVIMIENTOS!$B$4:$B$20000,">="&'MIS DATOS'!$A$6)&" movimientos desde "&TEXT('MIS DATOS'!$A$6,"mmmm yyyy")&" (cuentan cuando les pongas categoría)" -> 🏠 Casa: 969 €/mes de media · 🧾 Por revisar: 2 movimientos desde October 2025 (cuentan cuando les pongas categoría)
A9: ="¿CUÁNTO TENDRÁS A LOS "&PARÁMETROS!$B$5&"?" -> ¿CUÁNTO TENDRÁS A LOS 67?
A10: PATRIMONIO LÍQUIDO | C10: LO QUE PONES DE TU BOLSILLO | E10: LO QUE GENERAN TUS INVERSIONES | G10: EN € DE HOY | I10: INGRESO MENSUAL (€ DE HOY)
A11: =INDEX(PROYECCIÓN!$G$15:$G$45,PROYECCIÓN!$B$11+1) -> 502169.25 | C11: =INDEX(PROYECCIÓN!$I$15:$I$45,PROYECCIÓN!$B$11+1)+INDEX(PROYECCIÓN!$J$15:$J$45,PROYECCIÓN!$B$11+1) -> 462658.19 | E11: =INDEX(PROYECCIÓN!$K$15:$K$45,PROYECCIÓN!$B$11+1) -> 39511.054 | G11: =INDEX(PROYECCIÓN!$H$15:$H$45,PROYECCIÓN!$B$11+1) -> 264258.89 | I11: =INDEX(PROYECCIÓN!$H$15:$H$45,PROYECCIÓN!$B$11+1)*PARÁMETROS!$B$16/12+PARÁMETROS!$B$17*14/12 -> 2339.1963
A12: ="Por cada euro que pones, tus inversiones añaden "&TEXT(E11/C11,"0.00")&" €. El ingreso mensual suma la regla del "&TEXT(PARÁMETROS!$B$16,"0%")&" y una pensión pública de "&TEXT(PARÁMETROS!$B$17,"#,##0")&" € × 14 pagas (de hoy), repartida en 12 meses." -> Por cada euro que pones, tus inversiones añaden 0.09 €. El ingreso mensual suma la regla del 4% y una pensión pública de 1,250 € × 14 pagas (de hoy), repartida en 12 meses.
A14: 🏖️ TU JUBILACIÓN · ¿hasta cuándo te dura el dinero?
A15: SIN DECISIONES | C15: CON TUS DECISIONES | E15: LO QUE SACAS EL 1.er AÑO | G15: PENSIÓN + RENTAS EL 1.er AÑO
A16: =IF(PROYECCIÓN!$B$92>=PARÁMETROS!$B$5+40,"Más allá de los "&(PARÁMETROS!$B$5+40),"Hasta los "&PROYECCIÓN!$B$92) -> Más allá de los 107 | C16: =IF(PROYECCIÓN!$B$93>=PARÁMETROS!$B$5+40,"Más allá de los "&(PARÁMETROS!$B$5+40),"Hasta los "&PROYECCIÓN!$B$93) -> Más allá de los 107 | E16: =PROYECCIÓN!$H$50 -> 4383.1961 | G16: =PROYECCIÓN!$F$50+PROYECCIÓN!$G$50 -> 33255.122
A17: ="Cada año sacas lo que no cubren la pensión y las rentas; el capital renta un "&TEXT(PARÁMETROS!$B$20,"0%")&" y la pensión sube con la inflación. Con decisiones incluye la cuota si la hipoteca sigue viva." -> Cada año sacas lo que no cubren la pensión y las rentas; el capital renta un 3% y la pensión sube con la inflación. Con decisiones incluye la cuota si la hipoteca sigue viva.
A19: 🏆 TUS HITOS · se desbloquean solos según tu plan
A20: Hito | B20: Meta | C20: Hoy | D20: % | E20: Año | F20: Edad | G20: Faltan (años) | H20: Estado | I20: Progreso
A21: 🛟 Colchón de emergencia | B21: =PARÁMETROS!$B$15*PARÁMETROS!$B$18 -> 9903.295 | C21: =PROYECCIÓN!$B$5 -> 67957.06 | D21: =MIN(1,IFERROR(C21/B21,0)) -> 1 | E21: =IF(C21>=B21,"Hoy",IF(COUNTIF(PROYECCIÓN!$D$15:$D$45,"<"&B21)>PROYECCIÓN!$B$11,"—",INDEX(PROYECCIÓN!$C$15:$C$45,COUNTIF(PROYECCIÓN!$D$15:$D$45,"<"&B21)+1))) -> Hoy | F21: =IF(OR(C21>=B21,COUNTIF(PROYECCIÓN!$D$15:$D$45,"<"&B21)>PROYECCIÓN!$B$11),"",INDEX(PROYECCIÓN!$B$15:$B$45,COUNTIF(PROYECCIÓN!$D$15:$D$45,"<"&B21)+1)) | G21: =IF(OR(C21>=B21,COUNTIF(PROYECCIÓN!$D$15:$D$45,"<"&B21)>PROYECCIÓN!$B$11),"",COUNTIF(PROYECCIÓN!$D$15:$D$45,"<"&B21)) | H21: =IF(C21>=B21,"✅ Conseguido",IF(COUNTIF(PROYECCIÓN!$D$15:$D$45,"<"&B21)>PROYECCIÓN!$B$11,"⛔ Antes de jubilarte no","🔄 En camino")) -> ✅ Conseguido | I21: =REPT("█",ROUND(D21*10,0))&REPT("░",10-ROUND(D21*10,0))&" "&TEXT(D21,"0%") -> ██████████ 100%
A22: 💶 100.000 € de patrimonio líquido | B22: 100000 | C22: =PROYECCIÓN!$B$8 -> 67957.06 | D22: =MIN(1,IFERROR(C22/B22,0)) -> 0.6795706 | E22: =IF(C22>=B22,"Hoy",IF(COUNTIF(PROYECCIÓN!$G$15:$G$45,"<"&B22)>PROYECCIÓN!$B$11,"—",INDEX(PROYECCIÓN!$C$15:$C$45,COUNTIF(PROYECCIÓN!$G$15:$G$45,"<"&B22)+1))) -> 2029 | F22: =IF(OR(C22>=B22,COUNTIF(PROYECCIÓN!$G$15:$G$45,"<"&B22)>PROYECCIÓN!$B$11),"",INDEX(PROYECCIÓN!$B$15:$B$45,COUNTIF(PROYECCIÓN!$G$15:$G$45,"<"&B22)+1)) -> 44 | G22: =IF(OR(C22>=B22,COUNTIF(PROYECCIÓN!$G$15:$G$45,"<"&B22)>PROYECCIÓN!$B$11),"",COUNTIF(PROYECCIÓN!$G$15:$G$45,"<"&B22)) -> 3 | H22: =IF(C22>=B22,"✅ Conseguido",IF(COUNTIF(PROYECCIÓN!$G$15:$G$45,"<"&B22)>PROYECCIÓN!$B$11,"⛔ Antes de jubilarte no","🔄 En camino")) -> 🔄 En camino | I22: =REPT("█",ROUND(D22*10,0))&REPT("░",10-ROUND(D22*10,0))&" "&TEXT(D22,"0%") -> ███████░░░ 68%
A23: 💰 150.000 € de patrimonio líquido | B23: 150000 | C23: =PROYECCIÓN!$B$8 -> 67957.06 | D23: =MIN(1,IFERROR(C23/B23,0)) -> 0.45304707 | E23: =IF(C23>=B23,"Hoy",IF(COUNTIF(PROYECCIÓN!$G$15:$G$45,"<"&B23)>PROYECCIÓN!$B$11,"—",INDEX(PROYECCIÓN!$C$15:$C$45,COUNTIF(PROYECCIÓN!$G$15:$G$45,"<"&B23)+1))) -> 2033 | F23: =IF(OR(C23>=B23,COUNTIF(PROYECCIÓN!$G$15:$G$45,"<"&B23)>PROYECCIÓN!$B$11),"",INDEX(PROYECCIÓN!$B$15:$B$45,COUNTIF(PROYECCIÓN!$G$15:$G$45,"<"&B23)+1)) -> 48 | G23: =IF(OR(C23>=B23,COUNTIF(PROYECCIÓN!$G$15:$G$45,"<"&B23)>PROYECCIÓN!$B$11),"",COUNTIF(PROYECCIÓN!$G$15:$G$45,"<"&B23)) -> 7 | H23: =IF(C23>=B23,"✅ Conseguido",IF(COUNTIF(PROYECCIÓN!$G$15:$G$45,"<"&B23)>PROYECCIÓN!$B$11,"⛔ Antes de jubilarte no","🔄 En camino")) -> 🔄 En camino | I23: =REPT("█",ROUND(D23*10,0))&REPT("░",10-ROUND(D23*10,0))&" "&TEXT(D23,"0%") -> █████░░░░░ 45%
A24: 🏠 Vivienda comprada | B24: 1 | C24: =VIVIENDA!$B$6 -> 0 | D24: =MIN(1,IFERROR(C24/B24,0)) -> 0 | E24: =IF(C24>=B24,"Hoy",IF(DECISIONES!$B$10="Sí",PARÁMETROS!$B$6+DECISIONES!$B$14,"—")) -> 2026 | F24: =IF(C24>=B24,"",IF(DECISIONES!$B$10="Sí",PARÁMETROS!$B$4+DECISIONES!$B$14,"")) -> 41 | G24: =IF(C24>=B24,"",IF(DECISIONES!$B$10="Sí",DECISIONES!$B$14,"")) -> 0 | H24: =IF(C24>=B24,"✅ Conseguido",IF(DECISIONES!$B$10="Sí","📅 En DECISIONES","🤔 Por decidir")) -> 📅 En DECISIONES | I24: =REPT("█",ROUND(D24*10,0))&REPT("░",10-ROUND(D24*10,0))&" "&TEXT(D24,"0%") -> ░░░░░░░░░░ 0%
A25: 🔓 Libertad financiera 25 % | B25: 0.25 | C25: =PROYECCIÓN!$M$15 -> 0.13724131 | D25: =MIN(1,IFERROR(C25/B25,0)) -> 0.54896525 | E25: =IF(C25>=B25,"Hoy",IF(COUNTIF(PROYECCIÓN!$M$15:$M$45,"<"&B25)>PROYECCIÓN!$B$11,"—",INDEX(PROYECCIÓN!$C$15:$C$45,COUNTIF(PROYECCIÓN!$M$15:$M$45,"<"&B25)+1))) -> 2032 | F25: =IF(OR(C25>=B25,COUNTIF(PROYECCIÓN!$M$15:$M$45,"<"&B25)>PROYECCIÓN!$B$11),"",INDEX(PROYECCIÓN!$B$15:$B$45,COUNTIF(PROYECCIÓN!$M$15:$M$45,"<"&B25)+1)) -> 47 | G25: =IF(OR(C25>=B25,COUNTIF(PROYECCIÓN!$M$15:$M$45,"<"&B25)>PROYECCIÓN!$B$11),"",COUNTIF(PROYECCIÓN!$M$15:$M$45,"<"&B25)) -> 6 | H25: =IF(C25>=B25,"✅ Conseguido",IF(COUNTIF(PROYECCIÓN!$M$15:$M$45,"<"&B25)>PROYECCIÓN!$B$11,"⛔ Antes de jubilarte no","🔄 En camino")) -> 🔄 En camino | I25: =REPT("█",ROUND(D25*10,0))&REPT("░",10-ROUND(D25*10,0))&" "&TEXT(D25,"0%") -> █████░░░░░ 55%
A26: 💎 200.000 € de patrimonio líquido | B26: 200000 | C26: =PROYECCIÓN!$B$8 -> 67957.06 | D26: =MIN(1,IFERROR(C26/B26,0)) -> 0.3397853 | E26: =IF(C26>=B26,"Hoy",IF(COUNTIF(PROYECCIÓN!$G$15:$G$45,"<"&B26)>PROYECCIÓN!$B$11,"—",INDEX(PROYECCIÓN!$C$15:$C$45,COUNTIF(PROYECCIÓN!$G$15:$G$45,"<"&B26)+1))) -> 2036 | F26: =IF(OR(C26>=B26,COUNTIF(PROYECCIÓN!$G$15:$G$45,"<"&B26)>PROYECCIÓN!$B$11),"",INDEX(PROYECCIÓN!$B$15:$B$45,COUNTIF(PROYECCIÓN!$G$15:$G$45,"<"&B26)+1)) -> 51 | G26: =IF(OR(C26>=B26,COUNTIF(PROYECCIÓN!$G$15:$G$45,"<"&B26)>PROYECCIÓN!$B$11),"",COUNTIF(PROYECCIÓN!$G$15:$G$45,"<"&B26)) -> 10 | H26: =IF(C26>=B26,"✅ Conseguido",IF(COUNTIF(PROYECCIÓN!$G$15:$G$45,"<"&B26)>PROYECCIÓN!$B$11,"⛔ Antes de jubilarte no","🔄 En camino")) -> 🔄 En camino | I26: =REPT("█",ROUND(D26*10,0))&REPT("░",10-ROUND(D26*10,0))&" "&TEXT(D26,"0%") -> ███░░░░░░░ 34%
A27: 🔓 Libertad financiera 50 % | B27: 0.5 | C27: =PROYECCIÓN!$M$15 -> 0.13724131 | D27: =MIN(1,IFERROR(C27/B27,0)) -> 0.27448262 | E27: =IF(C27>=B27,"Hoy",IF(COUNTIF(PROYECCIÓN!$M$15:$M$45,"<"&B27)>PROYECCIÓN!$B$11,"—",INDEX(PROYECCIÓN!$C$15:$C$45,COUNTIF(PROYECCIÓN!$M$15:$M$45,"<"&B27)+1))) -> 2049 | F27: =IF(OR(C27>=B27,COUNTIF(PROYECCIÓN!$M$15:$M$45,"<"&B27)>PROYECCIÓN!$B$11),"",INDEX(PROYECCIÓN!$B$15:$B$45,COUNTIF(PROYECCIÓN!$M$15:$M$45,"<"&B27)+1)) -> 64 | G27: =IF(OR(C27>=B27,COUNTIF(PROYECCIÓN!$M$15:$M$45,"<"&B27)>PROYECCIÓN!$B$11),"",COUNTIF(PROYECCIÓN!$M$15:$M$45,"<"&B27)) -> 23 | H27: =IF(C27>=B27,"✅ Conseguido",IF(COUNTIF(PROYECCIÓN!$M$15:$M$45,"<"&B27)>PROYECCIÓN!$B$11,"⛔ Antes de jubilarte no","🔄 En camino")) -> 🔄 En camino | I27: =REPT("█",ROUND(D27*10,0))&REPT("░",10-ROUND(D27*10,0))&" "&TEXT(D27,"0%") -> ███░░░░░░░ 27%
A28: 🏖️ Que el dinero te dure hasta los 90 | B28: 90 | C28: =PROYECCIÓN!$B$92 -> 108 | D28: =MIN(1,IFERROR(C28/B28,0)) -> 1 | E28: ="" | F28: ="" | G28: ="" | H28: =IF(C28>=B28,"✅ Cubierto","⚠️ Ajusta el plan") -> ✅ Cubierto | I28: =REPT("█",ROUND(D28*10,0))&REPT("░",10-ROUND(D28*10,0))&" "&TEXT(D28,"0%") -> ██████████ 100%
A30: 🏅 TUS LOGROS DE AHORRO · medalla por % de ingresos ahorrado
A31: Año | B31: Ingresos | C31: Gastos | D31: Ahorro | E31: % ahorrado | F31: Medalla | G31: Meses con datos
A32: =PARÁMETROS!$B$6-1+0 -> 2025 | B32: =SUMIFS('MIS DATOS'!$G$6:$G$245,'MIS DATOS'!$L$6:$L$245,A32) -> 8698.69 | C32: =SUMIFS('MIS DATOS'!$H$6:$H$245,'MIS DATOS'!$L$6:$L$245,A32) -> 4904.55 | D32: =B32-C32 -> 3794.14 | E32: =IF(G32=0,"",D32/B32) -> 0.43617372 | F32: =IF(G32=0,"",IF(E32>=0.4,"🥇 Oro",IF(E32>=0.25,"🥈 Plata",IF(E32>=0.1,"🥉 Bronce","—")))&IF(G32<12," (parcial)","")) -> 🥇 Oro (parcial) | G32: =COUNTIF('MIS DATOS'!$L$6:$L$245,A32) -> 3
A33: =PARÁMETROS!$B$6-1+1 -> 2026 | B33: =SUMIFS('MIS DATOS'!$G$6:$G$245,'MIS DATOS'!$L$6:$L$245,A33) -> 22830.22 | C33: =SUMIFS('MIS DATOS'!$H$6:$H$245,'MIS DATOS'!$L$6:$L$245,A33) -> 14902.04 | D33: =B33-C33 -> 7928.18 | E33: =IF(G33=0,"",D33/B33) -> 0.34726691 | F33: =IF(G33=0,"",IF(E33>=0.4,"🥇 Oro",IF(E33>=0.25,"🥈 Plata",IF(E33>=0.1,"🥉 Bronce","—")))&IF(G33<12," (parcial)","")) -> 🥈 Plata (parcial) | G33: =COUNTIF('MIS DATOS'!$L$6:$L$245,A33) -> 9
A34: =PARÁMETROS!$B$6-1+2 -> 2027 | B34: =SUMIFS('MIS DATOS'!$G$6:$G$245,'MIS DATOS'!$L$6:$L$245,A34) -> 0 | C34: =SUMIFS('MIS DATOS'!$H$6:$H$245,'MIS DATOS'!$L$6:$L$245,A34) -> 0 | D34: =B34-C34 -> 0 | E34: =IF(G34=0,"",D34/B34) | F34: =IF(G34=0,"",IF(E34>=0.4,"🥇 Oro",IF(E34>=0.25,"🥈 Plata",IF(E34>=0.1,"🥉 Bronce","—")))&IF(G34<12," (parcial)","")) | G34: =COUNTIF('MIS DATOS'!$L$6:$L$245,A34) -> 0
A35: =PARÁMETROS!$B$6-1+3 -> 2028 | B35: =SUMIFS('MIS DATOS'!$G$6:$G$245,'MIS DATOS'!$L$6:$L$245,A35) -> 0 | C35: =SUMIFS('MIS DATOS'!$H$6:$H$245,'MIS DATOS'!$L$6:$L$245,A35) -> 0 | D35: =B35-C35 -> 0 | E35: =IF(G35=0,"",D35/B35) | F35: =IF(G35=0,"",IF(E35>=0.4,"🥇 Oro",IF(E35>=0.25,"🥈 Plata",IF(E35>=0.1,"🥉 Bronce","—")))&IF(G35<12," (parcial)","")) | G35: =COUNTIF('MIS DATOS'!$L$6:$L$245,A35) -> 0
A36: Oro ≥ 40 % · Plata ≥ 25 % · Bronce ≥ 10 %
A38: 🧭 TUS DECISIONES · ¿qué pasa si…?
B39: SIN DECISIONES | D39: CON TUS DECISIONES | G39: DIFERENCIA
A40: ="Patrimonio líquido a los "&PARÁMETROS!$B$5 -> Patrimonio líquido a los 67 | B40: =INDEX(PROYECCIÓN!$G$15:$G$45,PROYECCIÓN!$B$11+1) -> 502169.25 | D40: =INDEX(PROYECCIÓN!$O$15:$O$45,PROYECCIÓN!$B$11+1) -> 488086.56 | G40: =D40-B40 -> -14082.689
A41: Con tus inmuebles (netos de hipoteca) | B41: =INDEX(PROYECCIÓN!$T$15:$T$45,PROYECCIÓN!$B$11+1) -> 502169.25 | D41: =INDEX(PROYECCIÓN!$U$15:$U$45,PROYECCIÓN!$B$11+1) -> 962536.63 | G41: =D41-B41 -> 460367.39
A42: Libertad financiera | B42: =INDEX(PROYECCIÓN!$M$15:$M$45,PROYECCIÓN!$B$11+1) -> 0.53367873 | D42: =INDEX(PROYECCIÓN!$Q$15:$Q$45,PROYECCIÓN!$B$11+1) -> 1.0694662
A43: ="Decisiones: "&TEXT(DECISIONES!$B$5,"#,##0")&" € del efectivo a inversión, +"&TEXT(DECISIONES!$B$6,"#,##0")&" €/mes a inversión, −"&TEXT(DECISIONES!$B$7,"#,##0")&" €/mes de gastos"&IF(DECISIONES!$B$10="Sí",", compra de la vivienda ("&DECISIONES!$B$11&")","")&". Comprar pasa dinero líquido a ladrillo: mira las dos filas." -> Decisiones: 0 € del efectivo a inversión, +0 €/mes a inversión, −0 €/mes de gastos, compra de la vivienda (Comprar ya). Comprar pasa dinero líquido a ladrillo: mira las dos filas.
A45: 📊 TU FUTURO EN GRÁFICOS

Sheet MIS DATOS
A1: MIS DATOS
A2: Se rellena sola: saldos a fin de mes que trae el importador (B–D) e ingresos y gastos de MOVIMIENTOS. Inversión y plan de pensiones (E–F), a mano si algún día los tienes.
A3: La primera fila es el primer mes del que hay datos de las tres cuentas. Si descargas más histórico de todas, empieza antes.
A5: Mes | B5: CaixaBank | C5: Openbank | D5: ING | E5: Inversión | F5: Plan de pensiones | G5: Ingresos del mes | H5: Gastos del mes | I5: Ahorro del mes | J5: % de ahorro | K5: Patrimonio líquido | L5: Año | M5: Por revisar | N5: Mes completo
A6: 45931 | B6: 3446.26 | C6: 1080 | D6: 52332.69 | E6: 0 | F6: 0 | G6: =IF(A6="","",SUMIFS(MOVIMIENTOS!$E$4:$E$20000,MOVIMIENTOS!$B$4:$B$20000,A6,MOVIMIENTOS!$H$4:$H$20000,"Ingreso")+SUMIFS(FLEXIBLE!$D$4:$D$200,FLEXIBLE!$F$4:$F$200,A6)) -> 2182.69 | H6: =IF(A6="","",-SUMIFS(MOVIMIENTOS!$E$4:$E$20000,MOVIMIENTOS!$B$4:$B$20000,A6,MOVIMIENTOS!$H$4:$H$20000,"Gasto")+SUMIFS(FLEXIBLE!$D$4:$D$200,FLEXIBLE!$F$4:$F$200,A6)) -> 1569.48 | I6: =IF(A6="","",G6-H6) -> 613.21 | J6: =IF(A6="","",IF(N6=0,"en curso",IF(N(G6)=0,"",I6/G6))) -> 0.28094232 | K6: =IF(A6="","",SUM(B6:F6)) -> 56858.95 | L6: =IF(A6="","",YEAR(A6)) -> 2025 | M6: =IF(A6="","",COUNTIFS(MOVIMIENTOS!$B$4:$B$20000,A6,MOVIMIENTOS!$H$4:$H$20000,"Por revisar")) -> 0 | N6: =IF(A6="","",IF(A6<DATE(YEAR(TODAY()),MONTH(TODAY()),1),1,0)) -> 1
A7: 45962 | B7: 3570.92 | C7: 1114.26 | D7: 52665.59 | E7: 0 | F7: 0 | G7: =IF(A7="","",SUMIFS(MOVIMIENTOS!$E$4:$E$20000,MOVIMIENTOS!$B$4:$B$20000,A7,MOVIMIENTOS!$H$4:$H$20000,"Ingreso")+SUMIFS(FLEXIBLE!$D$4:$D$200,FLEXIBLE!$F$4:$F$200,A7)) -> 2182.9 | H7: =IF(A7="","",-SUMIFS(MOVIMIENTOS!$E$4:$E$20000,MOVIMIENTOS!$B$4:$B$20000,A7,MOVIMIENTOS!$H$4:$H$20000,"Gasto")+SUMIFS(FLEXIBLE!$D$4:$D$200,FLEXIBLE!$F$4:$F$200,A7)) -> 1735.4 | I7: =IF(A7="","",G7-H7) -> 447.5 | J7: =IF(A7="","",IF(N7=0,"en curso",IF(N(G7)=0,"",I7/G7))) -> 0.20500252 | K7: =IF(A7="","",SUM(B7:F7)) -> 57350.77 | L7: =IF(A7="","",YEAR(A7)) -> 2025 | M7: =IF(A7="","",COUNTIFS(MOVIMIENTOS!$B$4:$B$20000,A7,MOVIMIENTOS!$H$4:$H$20000,"Por revisar")) -> 0 | N7: =IF(A7="","",IF(A7<DATE(YEAR(TODAY()),MONTH(TODAY()),1),1,0)) -> 1
A8: 45992 | B8: 5931.77 | C8: 1104.2 | D8: 52998.69 | E8: 0 | F8: 0 | G8: =IF(A8="","",SUMIFS(MOVIMIENTOS!$E$4:$E$20000,MOVIMIENTOS!$B$4:$B$20000,A8,MOVIMIENTOS!$H$4:$H$20000,"Ingreso")+SUMIFS(FLEXIBLE!$D$4:$D$200,FLEXIBLE!$F$4:$F$200,A8)) -> 4333.1 | H8: =IF(A8="","",-SUMIFS(MOVIMIENTOS!$E$4:$E$20000,MOVIMIENTOS!$B$4:$B$20000,A8,MOVIMIENTOS!$H$4:$H$20000,"Gasto")+SUMIFS(FLEXIBLE!$D$4:$D$200,FLEXIBLE!$F$4:$F$200,A8)) -> 1599.67 | I8: =IF(A8="","",G8-H8) -> 2733.43 | J8: =IF(A8="","",IF(N8=0,"en curso",IF(N(G8)=0,"",I8/G8))) -> 0.63082551 | K8: =IF(A8="","",SUM(B8:F8)) -> 60034.66 | L8: =IF(A8="","",YEAR(A8)) -> 2025 | M8: =IF(A8="","",COUNTIFS(MOVIMIENTOS!$B$4:$B$20000,A8,MOVIMIENTOS!$H$4:$H$20000,"Por revisar")) -> 0 | N8: =IF(A8="","",IF(A8<DATE(YEAR(TODAY()),MONTH(TODAY()),1),1,0)) -> 1
A9: 46023 | B9: 6101.39 | C9: 1143.68 | D9: 53332 | E9: 0 | F9: 0 | G9: =IF(A9="","",SUMIFS(MOVIMIENTOS!$E$4:$E$20000,MOVIMIENTOS!$B$4:$B$20000,A9,MOVIMIENTOS!$H$4:$H$20000,"Ingreso")+SUMIFS(FLEXIBLE!$D$4:$D$200,FLEXIBLE!$F$4:$F$200,A9)) -> 2183.31 | H9: =IF(A9="","",-SUMIFS(MOVIMIENTOS!$E$4:$E$20000,MOVIMIENTOS!$B$4:$B$20000,A9,MOVIMIENTOS!$H$4:$H$20000,"Gasto")+SUMIFS(FLEXIBLE!$D$4:$D$200,FLEXIBLE!$F$4:$F$200,A9)) -> 1714.98 | I9: =IF(A9="","",G9-H9) -> 468.33 | J9: =IF(A9="","",IF(N9=0,"en curso",IF(N(G9)=0,"",I9/G9))) -> 0.21450458 | K9: =IF(A9="","",SUM(B9:F9)) -> 60577.07 | L9: =IF(A9="","",YEAR(A9)) -> 2026 | M9: =IF(A9="","",COUNTIFS(MOVIMIENTOS!$B$4:$B$20000,A9,MOVIMIENTOS!$H$4:$H$20000,"Por revisar")) -> 0 | N9: =IF(A9="","",IF(A9<DATE(YEAR(TODAY()),MONTH(TODAY()),1),1,0)) -> 1
A10: 46054 | B10: 6319.16 | C10: 1109.08 | D10: 53665.52 | E10: 0 | F10: 0 | G10: =IF(A10="","",SUMIFS(MOVIMIENTOS!$E$4:$E$20000,MOVIMIENTOS!$B$4:$B$20000,A10,MOVIMIENTOS!$H$4:$H$20000,"Ingreso")+SUMIFS(FLEXIBLE!$D$4:$D$200,FLEXIBLE!$F$4:$F$200,A10)) -> 2183.52 | H10: =IF(A10="","",-SUMIFS(MOVIMIENTOS!$E$4:$E$20000,MOVIMIENTOS!$B$4:$B$20000,A10,MOVIMIENTOS!$H$4:$H$20000,"Gasto")+SUMIFS(FLEXIBLE!$D$4:$D$200,FLEXIBLE!$F$4:$F$200,A10)) -> 1587.05 | I10: =IF(A10="","",G10-H10) -> 596.47 | J10: =IF(A10="","",IF(N10=0,"en curso",IF(N(G10)=0,"",I10/G10))) -> 0.27316901 | K10: =IF(A10="","",SUM(B10:F10)) -> 61093.76 | L10: =IF(A10="","",YEAR(A10)) -> 2026 | M10: =IF(A10="","",COUNTIFS(MOVIMIENTOS!$B$4:$B$20000,A10,MOVIMIENTOS!$H$4:$H$20000,"Por revisar")) -> 0 | N10: =IF(A10="","",IF(A10<DATE(YEAR(TODAY()),MONTH(TODAY()),1),1,0)) -> 1
A11: 46082 | B11: 6481.69 | C11: 1154.26 | D11: 53999.25 | E11: 0 | F11: 0 | G11: =IF(A11="","",SUMIFS(MOVIMIENTOS!$E$4:$E$20000,MOVIMIENTOS!$B$4:$B$20000,A11,MOVIMIENTOS!$H$4:$H$20000,"Ingreso")+SUMIFS(FLEXIBLE!$D$4:$D$200,FLEXIBLE!$F$4:$F$200,A11)) -> 2183.73 | H11: =IF(A11="","",-SUMIFS(MOVIMIENTOS!$E$4:$E$20000,MOVIMIENTOS!$B$4:$B$20000,A11,MOVIMIENTOS!$H$4:$H$20000,"Gasto")+SUMIFS(FLEXIBLE!$D$4:$D$200,FLEXIBLE!$F$4:$F$200,A11)) -> 1605.51 | I11: =IF(A11="","",G11-H11) -> 578.22 | J11: =IF(A11="","",IF(N11=0,"en curso",IF(N(G11)=0,"",I11/G11))) -> 0.26478548 | K11: =IF(A11="","",SUM(B11:F11)) -> 61635.2 | L11: =IF(A11="","",YEAR(A11)) -> 2026 | M11: =IF(A11="","",COUNTIFS(MOVIMIENTOS!$B$4:$B$20000,A11,MOVIMIENTOS!$H$4:$H$20000,"Por revisar")) -> 0 | N11: =IF(A11="","",IF(A11<DATE(YEAR(TODAY()),MONTH(TODAY()),1),1,0)) -> 1
A12: 46113 | B12: 6640.62 | C12: 1236.22 | D12: 54333.19 | E12: 0 | F12: 0 | G12: =IF(A12="","",SUMIFS(MOVIMIENTOS!$E$4:$E$20000,MOVIMIENTOS!$B$4:$B$20000,A12,MOVIMIENTOS!$H$4:$H$20000,"Ingreso")+SUMIFS(FLEXIBLE!$D$4:$D$200,FLEXIBLE!$F$4:$F$200,A12)) -> 2183.94 | H12: =IF(A12="","",-SUMIFS(MOVIMIENTOS!$E$4:$E$20000,MOVIMIENTOS!$B$4:$B$20000,A12,MOVIMIENTOS!$H$4:$H$20000,"Gasto")+SUMIFS(FLEXIBLE!$D$4:$D$200,FLEXIBLE!$F$4:$F$200,A12)) -> 1640.04 | I12: =IF(A12="","",G12-H12) -> 543.9 | J12: =IF(A12="","",IF(N12=0,"en curso",IF(N(G12)=0,"",I12/G12))) -> 0.2490453 | K12: =IF(A12="","",SUM(B12:F12)) -> 62210.03 | L12: =IF(A12="","",YEAR(A12)) -> 2026 | M12: =IF(A12="","",COUNTIFS(MOVIMIENTOS!$B$4:$B$20000,A12,MOVIMIENTOS!$H$4:$H$20000,"Por revisar")) -> 0 | N12: =IF(A12="","",IF(A12<DATE(YEAR(TODAY()),MONTH(TODAY()),1),1,0)) -> 1
A13: 46143 | B13: 6863.18 | C13: 1287.25 | D13: 54667.34 | E13: 0 | F13: 0 | G13: =IF(A13="","",SUMIFS(MOVIMIENTOS!$E$4:$E$20000,MOVIMIENTOS!$B$4:$B$20000,A13,MOVIMIENTOS!$H$4:$H$20000,"Ingreso")+SUMIFS(FLEXIBLE!$D$4:$D$200,FLEXIBLE!$F$4:$F$200,A13)) -> 2184.15 | H13: =IF(A13="","",-SUMIFS(MOVIMIENTOS!$E$4:$E$20000,MOVIMIENTOS!$B$4:$B$20000,A13,MOVIMIENTOS!$H$4:$H$20000,"Gasto")+SUMIFS(FLEXIBLE!$D$4:$D$200,FLEXIBLE!$F$4:$F$200,A13)) -> 1553.78 | I13: =IF(A13="","",G13-H13) -> 630.37 | J13: =IF(A13="","",IF(N13=0,"en curso",IF(N(G13)=0,"",I13/G13))) -> 0.28861113 | K13: =IF(A13="","",SUM(B13:F13)) -> 62817.77 | L13: =IF(A13="","",YEAR(A13)) -> 2026 | M13: =IF(A13="","",COUNTIFS(MOVIMIENTOS!$B$4:$B$20000,A13,MOVIMIENTOS!$H$4:$H$20000,"Por revisar")) -> 0 | N13: =IF(A13="","",IF(A13<DATE(YEAR(TODAY()),MONTH(TODAY()),1),1,0)) -> 1
A14: 46174 | B14: 9281.91 | C14: 1360.91 | D14: 55001.69 | E14: 0 | F14: 0 | G14: =IF(A14="","",SUMIFS(MOVIMIENTOS!$E$4:$E$20000,MOVIMIENTOS!$B$4:$B$20000,A14,MOVIMIENTOS!$H$4:$H$20000,"Ingreso")+SUMIFS(FLEXIBLE!$D$4:$D$200,FLEXIBLE!$F$4:$F$200,A14)) -> 4492.75 | H14: =IF(A14="","",-SUMIFS(MOVIMIENTOS!$E$4:$E$20000,MOVIMIENTOS!$B$4:$B$20000,A14,MOVIMIENTOS!$H$4:$H$20000,"Gasto")+SUMIFS(FLEXIBLE!$D$4:$D$200,FLEXIBLE!$F$4:$F$200,A14)) -> 1703.73 | I14: =IF(A14="","",G14-H14) -> 2789.02 | J14: =IF(A14="","",IF(N14=0,"en curso",IF(N(G14)=0,"",I14/G14))) -> 0.62078237 | K14: =IF(A14="","",SUM(B14:F14)) -> 65644.51 | L14: =IF(A14="","",YEAR(A14)) -> 2026 | M14: =IF(A14="","",COUNTIFS(MOVIMIENTOS!$B$4:$B$20000,A14,MOVIMIENTOS!$H$4:$H$20000,"Por revisar")) -> 0 | N14: =IF(A14="","",IF(A14<DATE(YEAR(TODAY()),MONTH(TODAY()),1),1,0)) -> 1
A15: 46204 | B15: 9973.79 | C15: 1396.85 | D15: 55336.25 | E15: 0 | F15: 0 | G15: =IF(A15="","",SUMIFS(MOVIMIENTOS!$E$4:$E$20000,MOVIMIENTOS!$B$4:$B$20000,A15,MOVIMIENTOS!$H$4:$H$20000,"Ingreso")+SUMIFS(FLEXIBLE!$D$4:$D$200,FLEXIBLE!$F$4:$F$200,A15)) -> 2768.17 | H15: =IF(A15="","",-SUMIFS(MOVIMIENTOS!$E$4:$E$20000,MOVIMIENTOS!$B$4:$B$20000,A15,MOVIMIENTOS!$H$4:$H$20000,"Gasto")+SUMIFS(FLEXIBLE!$D$4:$D$200,FLEXIBLE!$F$4:$F$200,A15)) -> 1750.81 | I15: =IF(A15="","",G15-H15) -> 1017.36 | J15: =IF(A15="","",IF(N15=0,"en curso",IF(N(G15)=0,"",I15/G15))) -> 0.36752078 | K15: =IF(A15="","",SUM(B15:F15)) -> 66706.89 | L15: =IF(A15="","",YEAR(A15)) -> 2026 | M15: =IF(A15="","",COUNTIFS(MOVIMIENTOS!$B$4:$B$20000,A15,MOVIMIENTOS!$H$4:$H$20000,"Por revisar")) -> 0 | N15: =IF(A15="","",IF(A15<DATE(YEAR(TODAY()),MONTH(TODAY()),1),1,0)) -> 1
A16: 46235 | B16: 10211.08 | C16: 1387.77 | D16: 55671.02 | E16: 0 | F16: 0 | G16: =IF(A16="","",SUMIFS(MOVIMIENTOS!$E$4:$E$20000,MOVIMIENTOS!$B$4:$B$20000,A16,MOVIMIENTOS!$H$4:$H$20000,"Ingreso")+SUMIFS(FLEXIBLE!$D$4:$D$200,FLEXIBLE!$F$4:$F$200,A16)) -> 2300.87 | H16: =IF(A16="","",-SUMIFS(MOVIMIENTOS!$E$4:$E$20000,MOVIMIENTOS!$B$4:$B$20000,A16,MOVIMIENTOS!$H$4:$H$20000,"Gasto")+SUMIFS(FLEXIBLE!$D$4:$D$200,FLEXIBLE!$F$4:$F$200,A16)) -> 1666.68 | I16: =IF(A16="","",G16-H16) -> 634.19 | J16: =IF(A16="","",IF(N16=0,"en curso",IF(N(G16)=0,"",I16/G16))) -> 0.27563052 | K16: =IF(A16="","",SUM(B16:F16)) -> 67269.87 | L16: =IF(A16="","",YEAR(A16)) -> 2026 | M16: =IF(A16="","",COUNTIFS(MOVIMIENTOS!$B$4:$B$20000,A16,MOVIMIENTOS!$H$4:$H$20000,"Por revisar")) -> 0 | N16: =IF(A16="","",IF(A16<DATE(YEAR(TODAY()),MONTH(TODAY()),1),1,0)) -> 1
A17: 46266 | B17: 10501.16 | C17: 1449.9 | D17: 56006 | E17: 0 | F17: 0 | G17: =IF(A17="","",SUMIFS(MOVIMIENTOS!$E$4:$E$20000,MOVIMIENTOS!$B$4:$B$20000,A17,MOVIMIENTOS!$H$4:$H$20000,"Ingreso")+SUMIFS(FLEXIBLE!$D$4:$D$200,FLEXIBLE!$F$4:$F$200,A17)) -> 2349.78 | H17: =IF(A17="","",-SUMIFS(MOVIMIENTOS!$E$4:$E$20000,MOVIMIENTOS!$B$4:$B$20000,A17,MOVIMIENTOS!$H$4:$H$20000,"Gasto")+SUMIFS(FLEXIBLE!$D$4:$D$200,FLEXIBLE!$F$4:$F$200,A17)) -> 1679.46 | I17: =IF(A17="","",G17-H17) -> 670.32 | J17: =IF(A17="","",IF(N17=0,"en curso",IF(N(G17)=0,"",I17/G17))) -> 0.28526926 | K17: =IF(A17="","",SUM(B17:F17)) -> 67957.06 | L17: =IF(A17="","",YEAR(A17)) -> 2026 | M17: =IF(A17="","",COUNTIFS(MOVIMIENTOS!$B$4:$B$20000,A17,MOVIMIENTOS!$H$4:$H$20000,"Por revisar")) -> 2 | N17: =IF(A17="","",IF(A17<DATE(YEAR(TODAY()),MONTH(TODAY()),1),1,0)) -> 1
G18: =IF(A18="","",SUMIFS(MOVIMIENTOS!$E$4:$E$20000,MOVIMIENTOS!$B$4:$B$20000,A18,MOVIMIENTOS!$H$4:$H$20000,"Ingreso")+SUMIFS(FLEXIBLE!$D$4:$D$200,FLEXIBLE!$F$4:$F$200,A18)) | H18: =IF(A18="","",-SUMIFS(MOVIMIENTOS!$E$4:$E$20000,MOVIMIENTOS!$B$4:$B$20000,A18,MOVIMIENTOS!$H$4:$H$20000,"Gasto")+SUMIFS(FLEXIBLE!$D$4:$D$200,FLEXIBLE!$F$4:$F$200,A18)) | I18: =IF(A18="","",G18-H18) | J18: =IF(A18="","",IF(N18=0,"en curso",IF(N(G18)=0,"",I18/G18))) | K18: =IF(A18="","",SUM(B18:F18)) | L18: =IF(A18="","",YEAR(A18)) | M18: =IF(A18="","",COUNTIFS(MOVIMIENTOS!$B$4:$B$20000,A18,MOVIMIENTOS!$H$4:$H$20000,"Por revisar")) | N18: =IF(A18="","",IF(A18<DATE(YEAR(TODAY()),MONTH(TODAY()),1),1,0))
G19: =IF(A19="","",SUMIFS(MOVIMIENTOS!$E$4:$E$20000,MOVIMIENTOS!$B$4:$B$20000,A19,MOVIMIENTOS!$H$4:$H$20000,"Ingreso")+SUMIFS(FLEXIBLE!$D$4:$D$200,FLEXIBLE!$F$4:$F$200,A19)) | H19: =IF(A19="","",-SUMIFS(MOVIMIENTOS!$E$4:$E$20000,MOVIMIENTOS!$B$4:$B$20000,A19,MOVIMIENTOS!$H$4:$H$20000,"Gasto")+SUMIFS(FLEXIBLE!$D$4:$D$200,FLEXIBLE!$F$4:$F$200,A19)) | I19: =IF(A19="","",G19-H19) | J19: =IF(A19="","",IF(N19=0,"en curso",IF(N(G19)=0,"",I19/G19))) | K19: =IF(A19="","",SUM(B19:F19)) | L19: =IF(A19="","",YEAR(A19)) | M19: =IF(A19="","",COUNTIFS(MOVIMIENTOS!$B$4:$B$20000,A19,MOVIMIENTOS!$H$4:$H$20000,"Por revisar")) | N19: =IF(A19="","",IF(A19<DATE(YEAR(TODAY()),MONTH(TODAY()),1),1,0))
G20: =IF(A20="","",SUMIFS(MOVIMIENTOS!$E$4:$E$20000,MOVIMIENTOS!$B$4:$B$20000,A20,MOVIMIENTOS!$H$4:$H$20000,"Ingreso")+SUMIFS(FLEXIBLE!$D$4:$D$200,FLEXIBLE!$F$4:$F$200,A20)) | H20: =IF(A20="","",-SUMIFS(MOVIMIENTOS!$E$4:$E$20000,MOVIMIENTOS!$B$4:$B$20000,A20,MOVIMIENTOS!$H$4:$H$20000,"Gasto")+SUMIFS(FLEXIBLE!$D$4:$D$200,FLEXIBLE!$F$4:$F$200,A20)) | I20: =IF(A20="","",G20-H20) | J20: =IF(A20="","",IF(N20=0,"en curso",IF(N(G20)=0,"",I20/G20))) | K20: =IF(A20="","",SUM(B20:F20)) | L20: =IF(A20="","",YEAR(A20)) | M20: =IF(A20="","",COUNTIFS(MOVIMIENTOS!$B$4:$B$20000,A20,MOVIMIENTOS!$H$4:$H$20000,"Por revisar")) | N20: =IF(A20="","",IF(A20<DATE(YEAR(TODAY()),MONTH(TODAY()),1),1,0))
G21: =IF(A21="","",SUMIFS(MOVIMIENTOS!$E$4:$E$20000,MOVIMIENTOS!$B$4:$B$20000,A21,MOVIMIENTOS!$H$4:$H$20000,"Ingreso")+SUMIFS(FLEXIBLE!$D$4:$D$200,FLEXIBLE!$F$4:$F$200,A21)) | H21: =IF(A21="","",-SUMIFS(MOVIMIENTOS!$E$4:$E$20000,MOVIMIENTOS!$B$4:$B$20000,A21,MOVIMIENTOS!$H$4:$H$20000,"Gasto")+SUMIFS(FLEXIBLE!$D$4:$D$200,FLEXIBLE!$F$4:$F$200,A21)) | I21: =IF(A21="","",G21-H21) | J21: =IF(A21="","",IF(N21=0,"en curso",IF(N(G21)=0,"",I21/G21))) | K21: =IF(A21="","",SUM(B21:F21)) | L21: =IF(A21="","",YEAR(A21)) | M21: =IF(A21="","",COUNTIFS(MOVIMIENTOS!$B$4:$B$20000,A21,MOVIMIENTOS!$H$4:$H$20000,"Por revisar")) | N21: =IF(A21="","",IF(A21<DATE(YEAR(TODAY()),MONTH(TODAY()),1),1,0))
G22: =IF(A22="","",SUMIFS(MOVIMIENTOS!$E$4:$E$20000,MOVIMIENTOS!$B$4:$B$20000,A22,MOVIMIENTOS!$H$4:$H$20000,"Ingreso")+SUMIFS(FLEXIBLE!$D$4:$D$200,FLEXIBLE!$F$4:$F$200,A22)) | H22: =IF(A22="","",-SUMIFS(MOVIMIENTOS!$E$4:$E$20000,MOVIMIENTOS!$B$4:$B$20000,A22,MOVIMIENTOS!$H$4:$H$20000,"Gasto")+SUMIFS(FLEXIBLE!$D$4:$D$200,FLEXIBLE!$F$4:$F$200,A22)) | I22: =IF(A22="","",G22-H22) | J22: =IF(A22="","",IF(N22=0,"en curso",IF(N(G22)=0,"",I22/G22))) | K22: =IF(A22="","",SUM(B22:F22)) | L22: =IF(A22="","",YEAR(A22)) | M22: =IF(A22="","",COUNTIFS(MOVIMIENTOS!$B$4:$B$20000,A22,MOVIMIENTOS!$H$4:$H$20000,"Por revisar")) | N22: =IF(A22="","",IF(A22<DATE(YEAR(TODAY()),MONTH(TODAY()),1),1,0))
G23: =IF(A23="","",SUMIFS(MOVIMIENTOS!$E$4:$E$20000,MOVIMIENTOS!$B$4:$B$20000,A23,MOVIMIENTOS!$H$4:$H$20000,"Ingreso")+SUMIFS(FLEXIBLE!$D$4:$D$200,FLEXIBLE!$F$4:$F$200,A23)) | H23: =IF(A23="","",-SUMIFS(MOVIMIENTOS!$E$4:$E$20000,MOVIMIENTOS!$B$4:$B$20000,A23,MOVIMIENTOS!$H$4:$H$20000,"Gasto")+SUMIFS(FLEXIBLE!$D$4:$D$200,FLEXIBLE!$F$4:$F$200,A23)) | I23: =IF(A23="","",G23-H23) | J23: =IF(A23="","",IF(N23=0,"en curso",IF(N(G23)=0,"",I23/G23))) | K23: =IF(A23="","",SUM(B23:F23)) | L23: =IF(A23="","",YEAR(A23)) | M23: =IF(A23="","",COUNTIFS(MOVIMIENTOS!$B$4:$B$20000,A23,MOVIMIENTOS!$H$4:$H$20000,"Por revisar")) | N23: =IF(A23="","",IF(A23<DATE(YEAR(TODAY()),MONTH(TODAY()),1),1,0))
G24: =IF(A24="","",SUMIFS(MOVIMIENTOS!$E$4:$E$20000,MOVIMIENTOS!$B$4:$B$20000,A24,MOVIMIENTOS!$H$4:$H$20000,"Ingreso")+SUMIFS(FLEXIBLE!$D$4:$D$200,FLEXIBLE!$F$4:$F$200,A24)) | H24: =IF(A24="","",-SUMIFS(MOVIMIENTOS!$E$4:$E$20000,MOVIMIENTOS!$B$4:$B$20000,A24,MOVIMIENTOS!$H$4:$H$20000,"Gasto")+SUMIFS(FLEXIBLE!$D$4:$D$200,FLEXIBLE!$F$4:$F$200,A24)) | I24: =IF(A24="","",G24-H24) | J24: =IF(A24="","",IF(N24=0,"en curso",IF(N(G24)=0,"",I24/G24))) | K24: =IF(A24="","",SUM(B24:F24)) | L24: =IF(A24="","",YEAR(A24)) | M24: =IF(A24="","",COUNTIFS(MOVIMIENTOS!$B$4:$B$20000,A24,MOVIMIENTOS!$H$4:$H$20000,"Por revisar")) | N24: =IF(A24="","",IF(A24<DATE(YEAR(TODAY()),MONTH(TODAY()),1),1,0))
G25: =IF(A25="","",SUMIFS(MOVIMIENTOS!$E$4:$E$20000,MOVIMIENTOS!$B$4:$B$20000,A25,MOVIMIENTOS!$H$4:$H$20000,"Ingreso")+SUMIFS(FLEXIBLE!$D$4:$D$200,FLEXIBLE!$F$4:$F$200,A25)) | H25: =IF(A25="","",-SUMIFS(MOVIMIENTOS!$E$4:$E$20000,MOVIMIENTOS!$B$4:$B$20000,A25,MOVIMIENTOS!$H$4:$H$20000,"Gasto")+SUMIFS(FLEXIBLE!$D$4:$D$200,FLEXIBLE!$F$4:$F$200,A25)) | I25: =IF(A25="","",G25-H25) | J25: =IF(A25="","",IF(N25=0,"en curso",IF(N(G25)=0,"",I25/G25))) | K25: =IF(A25="","",SUM(B25:F25)) | L25: =IF(A25="","",YEAR(A25)) | M25: =IF(A25="","",COUNTIFS(MOVIMIENTOS!$B$4:$B$20000,A25,MOVIMIENTOS!$H$4:$H$20000,"Por revisar")) | N25: =IF(A25="","",IF(A25<DATE(YEAR(TODAY()),MONTH(TODAY()),1),1,0))
G26: =IF(A26="","",SUMIFS(MOVIMIENTOS!$E$4:$E$20000,MOVIMIENTOS!$B$4:$B$20000,A26,MOVIMIENTOS!$H$4:$H$20000,"Ingreso")+SUMIFS(FLEXIBLE!$D$4:$D$200,FLEXIBLE!$F$4:$F$200,A26)) | H26: =IF(A26="","",-SUMIFS(MOVIMIENTOS!$E$4:$E$20000,MOVIMIENTOS!$B$4:$B$20000,A26,MOVIMIENTOS!$H$4:$H$20000,"Gasto")+SUMIFS(FLEXIBLE!$D$4:$D$200,FLEXIBLE!$F$4:$F$200,A26)) | I26: =IF(A26="","",G26-H26) | J26: =IF(A26="","",IF(N26=0,"en curso",IF(N(G26)=0,"",I26/G26))) | K26: =IF(A26="","",SUM(B26:F26)) | L26: =IF(A26="","",YEAR(A26)) | M26: =IF(A26="","",COUNTIFS(MOVIMIENTOS!$B$4:$B$20000,A26,MOVIMIENTOS!$H$4:$H$20000,"Por revisar")) | N26: =IF(A26="","",IF(A26<DATE(YEAR(TODAY()),MONTH(TODAY()),1),1,0))
G27: =IF(A27="","",SUMIFS(MOVIMIENTOS!$E$4:$E$20000,MOVIMIENTOS!$B$4:$B$20000,A27,MOVIMIENTOS!$H$4:$H$20000,"Ingreso")+SUMIFS(FLEXIBLE!$D$4:$D$200,FLEXIBLE!$F$4:$F$200,A27)) | H27: =IF(A27="","",-SUMIFS(MOVIMIENTOS!$E$4:$E$20000,MOVIMIENTOS!$B$4:$B$20000,A27,MOVIMIENTOS!$H$4:$H$20000,"Gasto")+SUMIFS(FLEXIBLE!$D$4:$D$200,FLEXIBLE!$F$4:$F$200,A27)) | I27: =IF(A27="","",G27-H27) | J27: =IF(A27="","",IF(N27=0,"en curso",IF(N(G27)=0,"",I27/G27))) | K27: =IF(A27="","",SUM(B27:F27)) | L27: =IF(A27="","",YEAR(A27)) | M27: =IF(A27="","",COUNTIFS(MOVIMIENTOS!$B$4:$B$20000,A27,MOVIMIENTOS!$H$4:$H$20000,"Por revisar")) | N27: =IF(A27="","",IF(A27<DATE(YEAR(TODAY()),MONTH(TODAY()),1),1,0))
G28: =IF(A28="","",SUMIFS(MOVIMIENTOS!$E$4:$E$20000,MOVIMIENTOS!$B$4:$B$20000,A28,MOVIMIENTOS!$H$4:$H$20000,"Ingreso")+SUMIFS(FLEXIBLE!$D$4:$D$200,FLEXIBLE!$F$4:$F$200,A28)) | H28: =IF(A28="","",-SUMIFS(MOVIMIENTOS!$E$4:$E$20000,MOVIMIENTOS!$B$4:$B$20000,A28,MOVIMIENTOS!$H$4:$H$20000,"Gasto")+SUMIFS(FLEXIBLE!$D$4:$D$200,FLEXIBLE!$F$4:$F$200,A28)) | I28: =IF(A28="","",G28-H28) | J28: =IF(A28="","",IF(N28=0,"en curso",IF(N(G28)=0,"",I28/G28))) | K28: =IF(A28="","",SUM(B28:F28)) | L28: =IF(A28="","",YEAR(A28)) | M28: =IF(A28="","",COUNTIFS(MOVIMIENTOS!$B$4:$B$20000,A28,MOVIMIENTOS!$H$4:$H$20000,"Por revisar")) | N28: =IF(A28="","",IF(A28<DATE(YEAR(TODAY()),MONTH(TODAY()),1),1,0))
G29: =IF(A29="","",SUMIFS(MOVIMIENTOS!$E$4:$E$20000,MOVIMIENTOS!$B$4:$B$20000,A29,MOVIMIENTOS!$H$4:$H$20000,"Ingreso")+SUMIFS(FLEXIBLE!$D$4:$D$200,FLEXIBLE!$F$4:$F$200,A29)) | H29: =IF(A29="","",-SUMIFS(MOVIMIENTOS!$E$4:$E$20000,MOVIMIENTOS!$B$4:$B$20000,A29,MOVIMIENTOS!$H$4:$H$20000,"Gasto")+SUMIFS(FLEXIBLE!$D$4:$D$200,FLEXIBLE!$F$4:$F$200,A29)) | I29: =IF(A29="","",G29-H29) | J29: =IF(A29="","",IF(N29=0,"en curso",IF(N(G29)=0,"",I29/G29))) | K29: =IF(A29="","",SUM(B29:F29)) | L29: =IF(A29="","",YEAR(A29)) | M29: =IF(A29="","",COUNTIFS(MOVIMIENTOS!$B$4:$B$20000,A29,MOVIMIENTOS!$H$4:$H$20000,"Por revisar")) | N29: =IF(A29="","",IF(A29<DATE(YEAR(TODAY()),MONTH(TODAY()),1),1,0))
... G245: =IF(A245="","",SUMIFS(MOVIMIENTOS!$E$4:$E$20000,MOVIMIENTOS!$B$4:$B$20000,A245,MOVIMIENTOS!$H$4:$H$20000,"Ingreso")+SUMIFS(FLEXIBLE!$D$4:$D$200,FLEXIBLE!$F$4:$F$200,A245)) | H245: =IF(A245="","",-SUMIFS(MOVIMIENTOS!$E$4:$E$20000,MOVIMIENTOS!$B$4:$B$20000,A245,MOVIMIENTOS!$H$4:$H$20000,"Gasto")+SUMIFS(FLEXIBLE!$D$4:$D$200,FLEXIBLE!$F$4:$F$200,A245)) | I245: =IF(A245="","",G245-H245) | J245: =IF(A245="","",IF(N245=0,"en curso",IF(N(G245)=0,"",I245/G245))) | K245: =IF(A245="","",SUM(B245:F245)) | L245: =IF(A245="","",YEAR(A245)) | M245: =IF(A245="","",COUNTIFS(MOVIMIENTOS!$B$4:$B$20000,A245,MOVIMIENTOS!$H$4:$H$20000,"Por revisar")) | N245: =IF(A245="","",IF(A245<DATE(YEAR(TODAY()),MONTH(TODAY()),1),1,0))

Sheet MOVIMIENTOS
A1: MOVIMIENTOS
A2: Los trae el importador (menú Plan financiero). Tú solo cambias Categoría y escribes Nota; lo amarillo está por revisar.
A3: Fecha | B3: Mes | C3: Cuenta | D3: Concepto | E3: Importe | F3: Saldo | G3: Categoría | H3: Tipo | I3: Grupo | J3: Nota | K3: Clave
A4: 46295 | B4: =DATE(YEAR(A4),MONTH(A4),1) -> 46266 | C4: ING | D4: INTERESES CUENTA AHORRO | E4: 34.98 | F4: 56006 | G4: Intereses | H4: =IFERROR(VLOOKUP(G4,CATEGORÍAS!$A$4:$C$100,2,FALSE()),"Por revisar") -> Ingreso | I4: =IFERROR(VLOOKUP(G4,CATEGORÍAS!$A$4:$C$100,3,FALSE()),"") -> Ahorro | K4: ING|2026-09-30||34.98|56006.00#1
A5: 46293 | B5: =DATE(YEAR(A5),MONTH(A5),1) -> 46266 | C5: CaixaBank | D5: NOMINA EMPRESA EJEMPLO SL | E5: 2150 | F5: 10501.16 | G5: Nómina | H5: =IFERROR(VLOOKUP(G5,CATEGORÍAS!$A$4:$C$100,2,FALSE()),"Por revisar") -> Ingreso | I5: =IFERROR(VLOOKUP(G5,CATEGORÍAS!$A$4:$C$100,3,FALSE()),"") -> Trabajo | K5: CaixaBank|2026-09-28||2150.00|10501.16#1
A6: 46292 | B6: =DATE(YEAR(A6),MONTH(A6),1) -> 46266 | C6: Openbank tarjeta | D6: FRUTERIA LA HUERTA | E6: -11.6 | G6: Supermercado | H6: =IFERROR(VLOOKUP(G6,CATEGORÍAS!$A$4:$C$100,2,FALSE()),"Por revisar") -> Gasto | I6: =IFERROR(VLOOKUP(G6,CATEGORÍAS!$A$4:$C$100,3,FALSE()),"") -> Comida | K6: Openbank tarjeta|2026-09-27|20:00|-11.60|#1
A7: 46292 | B7: =DATE(YEAR(A7),MONTH(A7),1) -> 46266 | C7: Openbank tarjeta | D7: CAFETERIA CENTRAL | E7: -7.97 | G7: Restaurantes y caprichos | H7: =IFERROR(VLOOKUP(G7,CATEGORÍAS!$A$4:$C$100,2,FALSE()),"Por revisar") -> Gasto | I7: =IFERROR(VLOOKUP(G7,CATEGORÍAS!$A$4:$C$100,3,FALSE()),"") -> Comida | K7: Openbank tarjeta|2026-09-27|11:07|-7.97|#1
A8: 46289 | B8: =DATE(YEAR(A8),MONTH(A8),1) -> 46266 | C8: Openbank tarjeta | D8: RESTAURANTE LA PLAZA | E8: -37.23 | G8: Restaurantes y caprichos | H8: =IFERROR(VLOOKUP(G8,CATEGORÍAS!$A$4:$C$100,2,FALSE()),"Por revisar") -> Gasto | I8: =IFERROR(VLOOKUP(G8,CATEGORÍAS!$A$4:$C$100,3,FALSE()),"") -> Comida | K8: Openbank tarjeta|2026-09-24|21:15|-37.23|#1
A9: 46289 | B9: =DATE(YEAR(A9),MONTH(A9),1) -> 46266 | C9: Openbank tarjeta | D9: TRANSPORTE PUBLICO RECARGA | E9: -20 | G9: Transporte | H9: =IFERROR(VLOOKUP(G9,CATEGORÍAS!$A$4:$C$100,2,FALSE()),"Por revisar") -> Gasto | I9: =IFERROR(VLOOKUP(G9,CATEGORÍAS!$A$4:$C$100,3,FALSE()),"") -> Transporte | K9: Openbank tarjeta|2026-09-24|16:31|-20.00|#1
A10: 46289 | B10: =DATE(YEAR(A10),MONTH(A10),1) -> 46266 | C10: CaixaBank | D10: BIZUM CENA | E10: 19 | F10: 8351.16 | G10: ❓ Por revisar | H10: =IFERROR(VLOOKUP(G10,CATEGORÍAS!$A$4:$C$100,2,FALSE()),"Por revisar") -> Por revisar | I10: =IFERROR(VLOOKUP(G10,CATEGORÍAS!$A$4:$C$100,3,FALSE()),"") -> 0 | K10: CaixaBank|2026-09-24||19.00|8351.16#1
A11: 46288 | B11: =DATE(YEAR(A11),MONTH(A11),1) -> 46266 | C11: Openbank tarjeta | D11: TIENDA ONLINE | E11: -44.59 | G11: Compras online | H11: =IFERROR(VLOOKUP(G11,CATEGORÍAS!$A$4:$C$100,2,FALSE()),"Por revisar") -> Gasto | I11: =IFERROR(VLOOKUP(G11,CATEGORÍAS!$A$4:$C$100,3,FALSE()),"") -> Personal | K11: Openbank tarjeta|2026-09-23|19:07|-44.59|#1
A12: 46288 | B12: =DATE(YEAR(A12),MONTH(A12),1) -> 46266 | C12: Openbank tarjeta | D12: RESTAURANTE LA PLAZA | E12: -29.53 | G12: Restaurantes y caprichos | H12: =IFERROR(VLOOKUP(G12,CATEGORÍAS!$A$4:$C$100,2,FALSE()),"Por revisar") -> Gasto | I12: =IFERROR(VLOOKUP(G12,CATEGORÍAS!$A$4:$C$100,3,FALSE()),"") -> Comida | K12: Openbank tarjeta|2026-09-23|12:45|-29.53|#1
A13: 46287 | B13: =DATE(YEAR(A13),MONTH(A13),1) -> 46266 | C13: Openbank tarjeta | D13: CAFETERIA CENTRAL | E13: -8.79 | G13: Restaurantes y caprichos | H13: =IFERROR(VLOOKUP(G13,CATEGORÍAS!$A$4:$C$100,2,FALSE()),"Por revisar") -> Gasto | I13: =IFERROR(VLOOKUP(G13,CATEGORÍAS!$A$4:$C$100,3,FALSE()),"") -> Comida | K13: Openbank tarjeta|2026-09-22|11:15|-8.79|#1
A14: 46287 | B14: =DATE(YEAR(A14),MONTH(A14),1) -> 46266 | C14: CaixaBank | D14: PELUQUERIA ESTILO | E14: -22 | F14: 8332.16 | G14: Cuidado personal | H14: =IFERROR(VLOOKUP(G14,CATEGORÍAS!$A$4:$C$100,2,FALSE()),"Por revisar") -> Gasto | I14: =IFERROR(VLOOKUP(G14,CATEGORÍAS!$A$4:$C$100,3,FALSE()),"") -> Personal | K14: CaixaBank|2026-09-22||-22.00|8332.16#1
A15: 46284 | B15: =DATE(YEAR(A15),MONTH(A15),1) -> 46266 | C15: Openbank tarjeta | D15: FRUTERIA LA HUERTA | E15: -19.81 | G15: Supermercado | H15: =IFERROR(VLOOKUP(G15,CATEGORÍAS!$A$4:$C$100,2,FALSE()),"Por revisar") -> Gasto | I15: =IFERROR(VLOOKUP(G15,CATEGORÍAS!$A$4:$C$100,3,FALSE()),"") -> Comida | K15: Openbank tarjeta|2026-09-19|19:52|-19.81|#1
A16: 46282 | B16: =DATE(YEAR(A16),MONTH(A16),1) -> 46266 | C16: Openbank tarjeta | D16: SUPERMERCADO EL BARRIO | E16: -36.94 | G16: Supermercado | H16: =IFERROR(VLOOKUP(G16,CATEGORÍAS!$A$4:$C$100,2,FALSE()),"Por revisar") -> Gasto | I16: =IFERROR(VLOOKUP(G16,CATEGORÍAS!$A$4:$C$100,3,FALSE()),"") -> Comida | K16: Openbank tarjeta|2026-09-17|16:00|-36.94|#1
A17: 46281 | B17: =DATE(YEAR(A17),MONTH(A17),1) -> 46266 | C17: Openbank tarjeta | D17: GASOLINERA RUTA | E17: -36.84 | G17: Transporte | H17: =IFERROR(VLOOKUP(G17,CATEGORÍAS!$A$4:$C$100,2,FALSE()),"Por revisar") -> Gasto | I17: =IFERROR(VLOOKUP(G17,CATEGORÍAS!$A$4:$C$100,3,FALSE()),"") -> Transporte | K17: Openbank tarjeta|2026-09-16|11:45|-36.84|#1
A18: 46281 | B18: =DATE(YEAR(A18),MONTH(A18),1) -> 46266 | C18: Openbank tarjeta | D18: SUPERMERCADO EL BARRIO | E18: -18.39 | G18: Supermercado | H18: =IFERROR(VLOOKUP(G18,CATEGORÍAS!$A$4:$C$100,2,FALSE()),"Por revisar") -> Gasto | I18: =IFERROR(VLOOKUP(G18,CATEGORÍAS!$A$4:$C$100,3,FALSE()),"") -> Comida | K18: Openbank tarjeta|2026-09-16|09:15|-18.39|#1
A19: 46280 | B19: =DATE(YEAR(A19),MONTH(A19),1) -> 46266 | C19: Openbank tarjeta | D19: SUPERMERCADO EL BARRIO | E19: -53.38 | G19: Supermercado | H19: =IFERROR(VLOOKUP(G19,CATEGORÍAS!$A$4:$C$100,2,FALSE()),"Por revisar") -> Gasto | I19: =IFERROR(VLOOKUP(G19,CATEGORÍAS!$A$4:$C$100,3,FALSE()),"") -> Comida | K19: Openbank tarjeta|2026-09-15|14:07|-53.38|#1
A20: 46276 | B20: =DATE(YEAR(A20),MONTH(A20),1) -> 46266 | C20: Openbank tarjeta | D20: SUPERMERCADO EL BARRIO | E20: -25.57 | G20: Supermercado | H20: =IFERROR(VLOOKUP(G20,CATEGORÍAS!$A$4:$C$100,2,FALSE()),"Por revisar") -> Gasto | I20: =IFERROR(VLOOKUP(G20,CATEGORÍAS!$A$4:$C$100,3,FALSE()),"") -> Comida | K20: Openbank tarjeta|2026-09-11|16:00|-25.57|#1
A21: 46276 | B21: =DATE(YEAR(A21),MONTH(A21),1) -> 46266 | C21: CaixaBank | D21: BIZUM COMIDA DOMINGO | E21: 29 | F21: 8354.16 | G21: ❓ Por revisar | H21: =IFERROR(VLOOKUP(G21,CATEGORÍAS!$A$4:$C$100,2,FALSE()),"Por revisar") -> Por revisar | I21: =IFERROR(VLOOKUP(G21,CATEGORÍAS!$A$4:$C$100,3,FALSE()),"") -> 0 | K21: CaixaBank|2026-09-11||29.00|8354.16#1
A22: 46274 | B22: =DATE(YEAR(A22),MONTH(A22),1) -> 46266 | C22: CaixaBank | D22: RECIBO STREAMFLIX | E22: -12.99 | F22: 8325.16 | G22: Suscripciones | H22: =IFERROR(VLOOKUP(G22,CATEGORÍAS!$A$4:$C$100,2,FALSE()),"Por revisar") -> Gasto | I22: =IFERROR(VLOOKUP(G22,CATEGORÍAS!$A$4:$C$100,3,FALSE()),"") -> Personal | K22: CaixaBank|2026-09-09||-12.99|8325.16#1
A23: 46273 | B23: =DATE(YEAR(A23),MONTH(A23),1) -> 46266 | C23: CaixaBank | D23: RECIBO LUZ HOGAR ENERGIA | E23: -38.08 | F23: 8338.15 | G23: Luz y gas | H23: =IFERROR(VLOOKUP(G23,CATEGORÍAS!$A$4:$C$100,2,FALSE()),"Por revisar") -> Gasto | I23: =IFERROR(VLOOKUP(G23,CATEGORÍAS!$A$4:$C$100,3,FALSE()),"") -> Casa | K23: CaixaBank|2026-09-08||-38.08|8338.15#1
A24: 46272 | B24: =DATE(YEAR(A24),MONTH(A24),1) -> 46266 | C24: Openbank tarjeta | D24: FARMACIA SAN JOSE | E24: -8.55 | G24: Salud y farmacia | H24: =IFERROR(VLOOKUP(G24,CATEGORÍAS!$A$4:$C$100,2,FALSE()),"Por revisar") -> Gasto | I24: =IFERROR(VLOOKUP(G24,CATEGORÍAS!$A$4:$C$100,3,FALSE()),"") -> Salud | K24: Openbank tarjeta|2026-09-07|09:15|-8.55|#1
A25: 46271 | B25: =DATE(YEAR(A25),MONTH(A25),1) -> 46266 | C25: Openbank tarjeta | D25: CAFETERIA CENTRAL | E25: -5.77 | G25: Restaurantes y caprichos | H25: =IFERROR(VLOOKUP(G25,CATEGORÍAS!$A$4:$C$100,2,FALSE()),"Por revisar") -> Gasto | I25: =IFERROR(VLOOKUP(G25,CATEGORÍAS!$A$4:$C$100,3,FALSE()),"") -> Comida | K25: Openbank tarjeta|2026-09-06|21:52|-5.77|#1
A26: 46271 | B26: =DATE(YEAR(A26),MONTH(A26),1) -> 46266 | C26: Openbank tarjeta | D26: CAFETERIA CENTRAL | E26: -5.98 | G26: Restaurantes y caprichos | H26: =IFERROR(VLOOKUP(G26,CATEGORÍAS!$A$4:$C$100,2,FALSE()),"Por revisar") -> Gasto | I26: =IFERROR(VLOOKUP(G26,CATEGORÍAS!$A$4:$C$100,3,FALSE()),"") -> Comida | K26: Openbank tarjeta|2026-09-06|21:22|-5.98|#1
A27: 46271 | B27: =DATE(YEAR(A27),MONTH(A27),1) -> 46266 | C27: CaixaBank | D27: RECIBO MOVILCOM | E27: -14.95 | F27: 8376.23 | G27: Móvil | H27: =IFERROR(VLOOKUP(G27,CATEGORÍAS!$A$4:$C$100,2,FALSE()),"Por revisar") -> Gasto | I27: =IFERROR(VLOOKUP(G27,CATEGORÍAS!$A$4:$C$100,3,FALSE()),"") -> Personal | K27: CaixaBank|2026-09-06||-14.95|8376.23#1
A28: 46270 | B28: =DATE(YEAR(A28),MONTH(A28),1) -> 46266 | C28: CaixaBank | D28: RECIBO FIBRANET | E28: -39.9 | F28: 8391.18 | G28: Internet y teléfono fijo | H28: =IFERROR(VLOOKUP(G28,CATEGORÍAS!$A$4:$C$100,2,FALSE()),"Por revisar") -> Gasto | I28: =IFERROR(VLOOKUP(G28,CATEGORÍAS!$A$4:$C$100,3,FALSE()),"") -> Casa | K28: CaixaBank|2026-09-05||-39.90|8391.18#1
A29: 46270 | B29: =DATE(YEAR(A29),MONTH(A29),1) -> 46266 | C29: Openbank | D29: LIQUIDACION TARJETA CREDITO | E29: -417.87 | F29: 1449.9 | G29: Pago de la tarjeta | H29: =IFERROR(VLOOKUP(G29,CATEGORÍAS!$A$4:$C$100,2,FALSE()),"Por revisar") -> Traspaso | I29: =IFERROR(VLOOKUP(G29,CATEGORÍAS!$A$4:$C$100,3,FALSE()),"") -> Traspasos | K29: Openbank|2026-09-05||-417.87|1449.90#1
A30: 46269 | B30: =DATE(YEAR(A30),MONTH(A30),1) -> 46266 | C30: Openbank tarjeta | D30: CINE ESTRENOS | E30: -10.55 | G30: Ocio y cultura | H30: =IFERROR(VLOOKUP(G30,CATEGORÍAS!$A$4:$C$100,2,FALSE()),"Por revisar") -> Gasto | I30: =IFERROR(VLOOKUP(G30,CATEGORÍAS!$A$4:$C$100,3,FALSE()),"") -> Ocio | K30: Openbank tarjeta|2026-09-04|18:22|-10.55|#1
A31: 46268 | B31: =DATE(YEAR(A31),MONTH(A31),1) -> 46266 | C31: Openbank tarjeta | D31: CAFETERIA CENTRAL | E31: -5.25 | G31: Restaurantes y caprichos | H31: =IFERROR(VLOOKUP(G31,CATEGORÍAS!$A$4:$C$100,2,FALSE()),"Por revisar") -> Gasto | I31: =IFERROR(VLOOKUP(G31,CATEGORÍAS!$A$4:$C$100,3,FALSE()),"") -> Comida | K31: Openbank tarjeta|2026-09-03|14:07|-5.25|#1
A32: 46268 | B32: =DATE(YEAR(A32),MONTH(A32),1) -> 46266 | C32: CaixaBank | D32: TRANSFERENCIA CUENTA DE VIAJES | E32: -150 | F32: 8431.08 | G32: Aportación a la cuenta de viajes | H32: =IFERROR(VLOOKUP(G32,CATEGORÍAS!$A$4:$C$100,2,FALSE()),"Por revisar") -> Gasto | I32: =IFERROR(VLOOKUP(G32,CATEGORÍAS!$A$4:$C$100,3,FALSE()),"") -> Viajes | K32: CaixaBank|2026-09-03||-150.00|8431.08#1
A33: 46267 | B33: =DATE(YEAR(A33),MONTH(A33),1) -> 46266 | C33: CaixaBank | D33: TRASPASO A CUENTA AHORRO ING | E33: -300 | F33: 9061.08 | G33: Traspaso entre mis cuentas | H33: =IFERROR(VLOOKUP(G33,CATEGORÍAS!$A$4:$C$100,2,FALSE()),"Por revisar") -> Traspaso | I33: =IFERROR(VLOOKUP(G33,CATEGORÍAS!$A$4:$C$100,3,FALSE()),"") -> Traspasos | K33: CaixaBank|2026-09-02||-300.00|9061.08#1
A34: 46267 | B34: =DATE(YEAR(A34),MONTH(A34),1) -> 46266 | C34: CaixaBank | D34: TRASPASO A OPENBANK | E34: -480 | F34: 8581.08 | G34: Traspaso entre mis cuentas | H34: =IFERROR(VLOOKUP(G34,CATEGORÍAS!$A$4:$C$100,2,FALSE()),"Por revisar") -> Traspaso | I34: =IFERROR(VLOOKUP(G34,CATEGORÍAS!$A$4:$C$100,3,FALSE()),"") -> Traspasos | K34: CaixaBank|2026-09-02||-480.00|8581.08#1
A35: 46267 | B35: =DATE(YEAR(A35),MONTH(A35),1) -> 46266 | C35: ING | D35: TRASPASO DESDE CAIXABANK | E35: 300 | F35: 55971.02 | G35: Traspaso entre mis cuentas | H35: =IFERROR(VLOOKUP(G35,CATEGORÍAS!$A$4:$C$100,2,FALSE()),"Por revisar") -> Traspaso | I35: =IFERROR(VLOOKUP(G35,CATEGORÍAS!$A$4:$C$100,3,FALSE()),"") -> Traspasos | K35: ING|2026-09-02||300.00|55971.02#1
A36: 46267 | B36: =DATE(YEAR(A36),MONTH(A36),1) -> 46266 | C36: Openbank | D36: TRASPASO DESDE CAIXABANK | E36: 480 | F36: 1867.77 | G36: Traspaso entre mis cuentas | H36: =IFERROR(VLOOKUP(G36,CATEGORÍAS!$A$4:$C$100,2,FALSE()),"Por revisar") -> Traspaso | I36: =IFERROR(VLOOKUP(G36,CATEGORÍAS!$A$4:$C$100,3,FALSE()),"") -> Traspasos | K36: Openbank|2026-09-02||480.00|1867.77#1
A37: 46266 | B37: =DATE(YEAR(A37),MONTH(A37),1) -> 46266 | C37: CaixaBank | D37: ALQUILER VIVIENDA 09/2026 | E37: -850 | F37: 9361.08 | G37: Alquiler | H37: =IFERROR(VLOOKUP(G37,CATEGORÍAS!$A$4:$C$100,2,FALSE()),"Por revisar") -> Gasto | I37: =IFERROR(VLOOKUP(G37,CATEGORÍAS!$A$4:$C$100,3,FALSE()),"") -> Casa | K37: CaixaBank|2026-09-01||-850.00|9361.08#1
A38: 46265 | B38: =DATE(YEAR(A38),MONTH(A38),1) -> 46235 | C38: ING | D38: INTERESES CUENTA AHORRO | E38: 34.77 | F38: 55671.02 | G38: Intereses | H38: =IFERROR(VLOOKUP(G38,CATEGORÍAS!$A$4:$C$100,2,FALSE()),"Por revisar") -> Ingreso | I38: =IFERROR(VLOOKUP(G38,CATEGORÍAS!$A$4:$C$100,3,FALSE()),"") -> Ahorro | K38: ING|2026-08-31||34.77|55671.02#1
A39: 46262 | B39: =DATE(YEAR(A39),MONTH(A39),1) -> 46235 | C39: Openbank tarjeta | D39: FRUTERIA LA HUERTA | E39: -15.37 | G39: Supermercado | H39: =IFERROR(VLOOKUP(G39,CATEGORÍAS!$A$4:$C$100,2,FALSE()),"Por revisar") -> Gasto | I39: =IFERROR(VLOOKUP(G39,CATEGORÍAS!$A$4:$C$100,3,FALSE()),"") -> Comida | K39: Openbank tarjeta|2026-08-28|16:07|-15.37|#1
A40: 46262 | B40: =DATE(YEAR(A40),MONTH(A40),1) -> 46235 | C40: CaixaBank | D40: NOMINA EMPRESA EJEMPLO SL | E40: 2150 | F40: 10211.08 | G40: Nómina | H40: =IFERROR(VLOOKUP(G40,CATEGORÍAS!$A$4:$C$100,2,FALSE()),"Por revisar") -> Ingreso | I40: =IFERROR(VLOOKUP(G40,CATEGORÍAS!$A$4:$C$100,3,FALSE()),"") -> Trabajo | K40: CaixaBank|2026-08-28||2150.00|10211.08#1
A41: 46261 | B41: =DATE(YEAR(A41),MONTH(A41),1) -> 46235 | C41: Openbank tarjeta | D41: RESTAURANTE LA PLAZA | E41: -50.77 | G41: Restaurantes y caprichos | H41: =IFERROR(VLOOKUP(G41,CATEGORÍAS!$A$4:$C$100,2,FALSE()),"Por revisar") -> Gasto | I41: =IFERROR(VLOOKUP(G41,CATEGORÍAS!$A$4:$C$100,3,FALSE()),"") -> Comida | K41: Openbank tarjeta|2026-08-27|17:00|-50.77|#1
A42: 46261 | B42: =DATE(YEAR(A42),MONTH(A42),1) -> 46235 | C42: Openbank tarjeta | D42: CAFETERIA CENTRAL | E42: -8.07 | G42: Restaurantes y caprichos | H42: =IFERROR(VLOOKUP(G42,CATEGORÍAS!$A$4:$C$100,2,FALSE()),"Por revisar") -> Gasto | I42: =IFERROR(VLOOKUP(G42,CATEGORÍAS!$A$4:$C$100,3,FALSE()),"") -> Comida | K42: Openbank tarjeta|2026-08-27|13:45|-8.07|#1
A43: 46260 | B43: =DATE(YEAR(A43),MONTH(A43),1) -> 46235 | C43: Openbank tarjeta | D43: GASOLINERA RUTA | E43: -40.99 | G43: Transporte | H43: =IFERROR(VLOOKUP(G43,CATEGORÍAS!$A$4:$C$100,2,FALSE()),"Por revisar") -> Gasto | I43: =IFERROR(VLOOKUP(G43,CATEGORÍAS!$A$4:$C$100,3,FALSE()),"") -> Transporte | K43: Openbank tarjeta|2026-08-26|21:07|-40.99|#1
A44: 46260 | B44: =DATE(YEAR(A44),MONTH(A44),1) -> 46235 | C44: Openbank tarjeta | D44: CAFETERIA CENTRAL | E44: -8.1 | G44: Restaurantes y caprichos | H44: =IFERROR(VLOOKUP(G44,CATEGORÍAS!$A$4:$C$100,2,FALSE()),"Por revisar") -> Gasto | I44: =IFERROR(VLOOKUP(G44,CATEGORÍAS!$A$4:$C$100,3,FALSE()),"") -> Comida | K44: Openbank tarjeta|2026-08-26|20:52|-8.10|#1
A45: 46260 | B45: =DATE(YEAR(A45),MONTH(A45),1) -> 46235 | C45: Openbank tarjeta | D45: SUPERMERCADO EL BARRIO | E45: -27.07 | G45: Supermercado | H45: =IFERROR(VLOOKUP(G45,CATEGORÍAS!$A$4:$C$100,2,FALSE()),"Por revisar") -> Gasto | I45: =IFERROR(VLOOKUP(G45,CATEGORÍAS!$A$4:$C$100,3,FALSE()),"") -> Comida | K45: Openbank tarjeta|2026-08-26|12:52|-27.07|#1
A46: 46260 | B46: =DATE(YEAR(A46),MONTH(A46),1) -> 46235 | C46: Openbank tarjeta | D46: TRANSPORTE PUBLICO RECARGA | E46: -20 | G46: Transporte | H46: =IFERROR(VLOOKUP(G46,CATEGORÍAS!$A$4:$C$100,2,FALSE()),"Por revisar") -> Gasto | I46: =IFERROR(VLOOKUP(G46,CATEGORÍAS!$A$4:$C$100,3,FALSE()),"") -> Transporte | K46: Openbank tarjeta|2026-08-26|08:15|-20.00|#1
A47: 46258 | B47: =DATE(YEAR(A47),MONTH(A47),1) -> 46235 | C47: CaixaBank | D47: BIZUM COMPRA | E47: 23 | F47: 8061.08 | G47: Ajustes de gastos compartidos (comida) | H47: =IFERROR(VLOOKUP(G47,CATEGORÍAS!$A$4:$C$100,2,FALSE()),"Por revisar") -> Gasto | I47: =IFERROR(VLOOKUP(G47,CATEGORÍAS!$A$4:$C$100,3,FALSE()),"") -> Comida | K47: CaixaBank|2026-08-24||23.00|8061.08#1
A48: 46257 | B48: =DATE(YEAR(A48),MONTH(A48),1) -> 46235 | C48: Openbank tarjeta | D48: CAFETERIA CENTRAL | E48: -5.68 | G48: Restaurantes y caprichos | H48: =IFERROR(VLOOKUP(G48,CATEGORÍAS!$A$4:$C$100,2,FALSE()),"Por revisar") -> Gasto | I48: =IFERROR(VLOOKUP(G48,CATEGORÍAS!$A$4:$C$100,3,FALSE()),"") -> Comida | K48: Openbank tarjeta|2026-08-23|16:45|-5.68|#1
A49: 46257 | B49: =DATE(YEAR(A49),MONTH(A49),1) -> 46235 | C49: Openbank tarjeta | D49: CINE ESTRENOS | E49: -9.48 | G49: Ocio y cultura | H49: =IFERROR(VLOOKUP(G49,CATEGORÍAS!$A$4:$C$100,2,FALSE()),"Por revisar") -> Gasto | I49: =IFERROR(VLOOKUP(G49,CATEGORÍAS!$A$4:$C$100,3,FALSE()),"") -> Ocio | K49: Openbank tarjeta|2026-08-23|10:45|-9.48|#1
A50: 46251 | B50: =DATE(YEAR(A50),MONTH(A50),1) -> 46235 | C50: Openbank tarjeta | D50: SUPERMERCADO EL BARRIO | E50: -45.07 | G50: Supermercado | H50: =IFERROR(VLOOKUP(G50,CATEGORÍAS!$A$4:$C$100,2,FALSE()),"Por revisar") -> Gasto | I50: =IFERROR(VLOOKUP(G50,CATEGORÍAS!$A$4:$C$100,3,FALSE()),"") -> Comida | K50: Openbank tarjeta|2026-08-17|14:45|-45.07|#1
A51: 46249 | B51: =DATE(YEAR(A51),MONTH(A51),1) -> 46235 | C51: Openbank tarjeta | D51: FRUTERIA LA HUERTA | E51: -11.37 | G51: Supermercado | H51: =IFERROR(VLOOKUP(G51,CATEGORÍAS!$A$4:$C$100,2,FALSE()),"Por revisar") -> Gasto | I51: =IFERROR(VLOOKUP(G51,CATEGORÍAS!$A$4:$C$100,3,FALSE()),"") -> Comida | K51: Openbank tarjeta|2026-08-15|14:31|-11.37|#1
A52: 46247 | B52: =DATE(YEAR(A52),MONTH(A52),1) -> 46235 | C52: Openbank tarjeta | D52: CAFETERIA CENTRAL | E52: -5.96 | G52: Restaurantes y caprichos | H52: =IFERROR(VLOOKUP(G52,CATEGORÍAS!$A$4:$C$100,2,FALSE()),"Por revisar") -> Gasto | I52: =IFERROR(VLOOKUP(G52,CATEGORÍAS!$A$4:$C$100,3,FALSE()),"") -> Comida | K52: Openbank tarjeta|2026-08-13|19:31|-5.96|#1
A53: 46246 | B53: =DATE(YEAR(A53),MONTH(A53),1) -> 46235 | C53: Openbank tarjeta | D53: TIENDA ONLINE | E53: -18.14 | G53: Compras online | H53: =IFERROR(VLOOKUP(G53,CATEGORÍAS!$A$4:$C$100,2,FALSE()),"Por revisar") -> Gasto | I53: =IFERROR(VLOOKUP(G53,CATEGORÍAS!$A$4:$C$100,3,FALSE()),"") -> Personal | K53: Openbank tarjeta|2026-08-12|10:07|-18.14|#1
A54: 46246 | B54: =DATE(YEAR(A54),MONTH(A54),1) -> 46235 | C54: CaixaBank | D54: RECIBO AGUAS MUNICIPALES | E54: -37.55 | F54: 8038.08 | G54: Agua | H54: =IFERROR(VLOOKUP(G54,CATEGORÍAS!$A$4:$C$100,2,FALSE()),"Por revisar") -> Gasto | I54: =IFERROR(VLOOKUP(G54,CATEGORÍAS!$A$4:$C$100,3,FALSE()),"") -> Casa | K54: CaixaBank|2026-08-12||-37.55|8038.08#1
A55: 46245 | B55: =DATE(YEAR(A55),MONTH(A55),1) -> 46235 | C55: CaixaBank | D55: BIZUM COMIDA DOMINGO | E55: 27 | F55: 8075.63 | G55: Ajustes de gastos compartidos (comida) | H55: =IFERROR(VLOOKUP(G55,CATEGORÍAS!$A$4:$C$100,2,FALSE()),"Por revisar") -> Gasto | I55: =IFERROR(VLOOKUP(G55,CATEGORÍAS!$A$4:$C$100,3,FALSE()),"") -> Comida | K55: CaixaBank|2026-08-11||27.00|8075.63#1
A56: 46243 | B56: =DATE(YEAR(A56),MONTH(A56),1) -> 46235 | C56: CaixaBank | D56: RECIBO STREAMFLIX | E56: -12.99 | F56: 8048.63 | G56: Suscripciones | H56: =IFERROR(VLOOKUP(G56,CATEGORÍAS!$A$4:$C$100,2,FALSE()),"Por revisar") -> Gasto | I56: =IFERROR(VLOOKUP(G56,CATEGORÍAS!$A$4:$C$100,3,FALSE()),"") -> Personal | K56: CaixaBank|2026-08-09||-12.99|8048.63#1
A57: 46242 | B57: =DATE(YEAR(A57),MONTH(A57),1) -> 46235 | C57: CaixaBank | D57: RECIBO LUZ HOGAR ENERGIA | E57: -77.32 | F57: 8061.62 | G57: Luz y gas | H57: =IFERROR(VLOOKUP(G57,CATEGORÍAS!$A$4:$C$100,2,FALSE()),"Por revisar") -> Gasto | I57: =IFERROR(VLOOKUP(G57,CATEGORÍAS!$A$4:$C$100,3,FALSE()),"") -> Casa | K57: CaixaBank|2026-08-08||-77.32|8061.62#1
A58: 46241 | B58: =DATE(YEAR(A58),MONTH(A58),1) -> 46235 | C58: Openbank tarjeta | D58: CAFETERIA CENTRAL | E58: -3.49 | G58: Restaurantes y caprichos | H58: =IFERROR(VLOOKUP(G58,CATEGORÍAS!$A$4:$C$100,2,FALSE()),"Por revisar") -> Gasto | I58: =IFERROR(VLOOKUP(G58,CATEGORÍAS!$A$4:$C$100,3,FALSE()),"") -> Comida | K58: Openbank tarjeta|2026-08-07|16:45|-3.49|#1
A59: 46240 | B59: =DATE(YEAR(A59),MONTH(A59),1) -> 46235 | C59: Openbank tarjeta | D59: SUPERMERCADO EL BARRIO | E59: -22.06 | G59: Supermercado | H59: =IFERROR(VLOOKUP(G59,CATEGORÍAS!$A$4:$C$100,2,FALSE()),"Por revisar") -> Gasto | I59: =IFERROR(VLOOKUP(G59,CATEGORÍAS!$A$4:$C$100,3,FALSE()),"") -> Comida | K59: Openbank tarjeta|2026-08-06|16:52|-22.06|#1
A60: 46240 | B60: =DATE(YEAR(A60),MONTH(A60),1) -> 46235 | C60: CaixaBank | D60: RECIBO MOVILCOM | E60: -14.95 | F60: 8138.94 | G60: Móvil | H60: =IFERROR(VLOOKUP(G60,CATEGORÍAS!$A$4:$C$100,2,FALSE()),"Por revisar") -> Gasto | I60: =IFERROR(VLOOKUP(G60,CATEGORÍAS!$A$4:$C$100,3,FALSE()),"") -> Personal | K60: CaixaBank|2026-08-06||-14.95|8138.94#1
A61: 46239 | B61: =DATE(YEAR(A61),MONTH(A61),1) -> 46235 | C61: Openbank tarjeta | D61: FARMACIA SAN JOSE | E61: -11.89 | G61: Salud y farmacia | H61: =IFERROR(VLOOKUP(G61,CATEGORÍAS!$A$4:$C$100,2,FALSE()),"Por revisar") -> Gasto | I61: =IFERROR(VLOOKUP(G61,CATEGORÍAS!$A$4:$C$100,3,FALSE()),"") -> Salud | K61: Openbank tarjeta|2026-08-05|16:45|-11.89|#1
A62: 46239 | B62: =DATE(YEAR(A62),MONTH(A62),1) -> 46235 | C62: Openbank tarjeta | D62: RESTAURANTE LA PLAZA | E62: -48.23 | G62: Restaurantes y caprichos | H62: =IFERROR(VLOOKUP(G62,CATEGORÍAS!$A$4:$C$100,2,FALSE()),"Por revisar") -> Gasto | I62: =IFERROR(VLOOKUP(G62,CATEGORÍAS!$A$4:$C$100,3,FALSE()),"") -> Comida | K62: Openbank tarjeta|2026-08-05|10:52|-48.23|#1
A63: 46239 | B63: =DATE(YEAR(A63),MONTH(A63),1) -> 46235 | C63: CaixaBank | D63: RECIBO FIBRANET | E63: -39.9 | F63: 8153.89 | G63: Internet y teléfono fijo | H63: =IFERROR(VLOOKUP(G63,CATEGORÍAS!$A$4:$C$100,2,FALSE()),"Por revisar") -> Gasto | I63: =IFERROR(VLOOKUP(G63,CATEGORÍAS!$A$4:$C$100,3,FALSE()),"") -> Casa | K63: CaixaBank|2026-08-05||-39.90|8153.89#1
A64: 46239 | B64: =DATE(YEAR(A64),MONTH(A64),1) -> 46235 | C64: Openbank | D64: LIQUIDACION TARJETA CREDITO | E64: -489.08 | F64: 1387.77 | G64: Pago de la tarjeta | H64: =IFERROR(VLOOKUP(G64,CATEGORÍAS!$A$4:$C$100,2,FALSE()),"Por revisar") -> Traspaso | I64: =IFERROR(VLOOKUP(G64,CATEGORÍAS!$A$4:$C$100,3,FALSE()),"") -> Traspasos | K64: Openbank|2026-08-05||-489.08|1387.77#1
A65: 46238 | B65: =DATE(YEAR(A65),MONTH(A65),1) -> 46235 | C65: Openbank tarjeta | D65: SUPERMERCADO EL BARRIO | E65: -66.13 | G65: Supermercado | H65: =IFERROR(VLOOKUP(G65,CATEGORÍAS!$A$4:$C$100,2,FALSE()),"Por revisar") -> Gasto | I65: =IFERROR(VLOOKUP(G65,CATEGORÍAS!$A$4:$C$100,3,FALSE()),"") -> Comida | K65: Openbank tarjeta|2026-08-04|11:00|-66.13|#1
A66: 46237 | B66: =DATE(YEAR(A66),MONTH(A66),1) -> 46235 | C66: CaixaBank | D66: TRANSFERENCIA CUENTA DE VIAJES | E66: -150 | F66: 8193.79 | G66: Aportación a la cuenta de viajes | H66: =IFERROR(VLOOKUP(G66,CATEGORÍAS!$A$4:$C$100,2,FALSE()),"Por revisar") -> Gasto | I66: =IFERROR(VLOOKUP(G66,CATEGORÍAS!$A$4:$C$100,3,FALSE()),"") -> Viajes | K66: CaixaBank|2026-08-03||-150.00|8193.79#1
A67: 46236 | B67: =DATE(YEAR(A67),MONTH(A67),1) -> 46235 | C67: CaixaBank | D67: TRASPASO A CUENTA AHORRO ING | E67: -300 | F67: 8823.79 | G67: Traspaso entre mis cuentas | H67: =IFERROR(VLOOKUP(G67,CATEGORÍAS!$A$4:$C$100,2,FALSE()),"Por revisar") -> Traspaso | I67: =IFERROR(VLOOKUP(G67,CATEGORÍAS!$A$4:$C$100,3,FALSE()),"") -> Traspasos | K67: CaixaBank|2026-08-02||-300.00|8823.79#1
A68: 46236 | B68: =DATE(YEAR(A68),MONTH(A68),1) -> 46235 | C68: CaixaBank | D68: TRASPASO A OPENBANK | E68: -480 | F68: 8343.79 | G68: Traspaso entre mis cuentas | H68: =IFERROR(VLOOKUP(G68,CATEGORÍAS!$A$4:$C$100,2,FALSE()),"Por revisar") -> Traspaso | I68: =IFERROR(VLOOKUP(G68,CATEGORÍAS!$A$4:$C$100,3,FALSE()),"") -> Traspasos | K68: CaixaBank|2026-08-02||-480.00|8343.79#1
A69: 46236 | B69: =DATE(YEAR(A69),MONTH(A69),1) -> 46235 | C69: ING | D69: TRASPASO DESDE CAIXABANK | E69: 300 | F69: 55636.25 | G69: Traspaso entre mis cuentas | H69: =IFERROR(VLOOKUP(G69,CATEGORÍAS!$A$4:$C$100,2,FALSE()),"Por revisar") -> Traspaso | I69: =IFERROR(VLOOKUP(G69,CATEGORÍAS!$A$4:$C$100,3,FALSE()),"") -> Traspasos | K69: ING|2026-08-02||300.00|55636.25#1
A70: 46236 | B70: =DATE(YEAR(A70),MONTH(A70),1) -> 46235 | C70: Openbank | D70: TRASPASO DESDE CAIXABANK | E70: 480 | F70: 1876.85 | G70: Traspaso entre mis cuentas | H70: =IFERROR(VLOOKUP(G70,CATEGORÍAS!$A$4:$C$100,2,FALSE()),"Por revisar") -> Traspaso | I70: =IFERROR(VLOOKUP(G70,CATEGORÍAS!$A$4:$C$100,3,FALSE()),"") -> Traspasos | K70: Openbank|2026-08-02||480.00|1876.85#1
A71: 46235 | B71: =DATE(YEAR(A71),MONTH(A71),1) -> 46235 | C71: CaixaBank | D71: ALQUILER VIVIENDA 08/2026 | E71: -850 | F71: 9123.79 | G71: Alquiler | H71: =IFERROR(VLOOKUP(G71,CATEGORÍAS!$A$4:$C$100,2,FALSE()),"Por revisar") -> Gasto | I71: =IFERROR(VLOOKUP(G71,CATEGORÍAS!$A$4:$C$100,3,FALSE()),"") -> Casa | K71: CaixaBank|2026-08-01||-850.00|9123.79#1
A72: 46234 | B72: =DATE(YEAR(A72),MONTH(A72),1) -> 46204 | C72: ING | D72: INTERESES CUENTA AHORRO | E72: 34.56 | F72: 55336.25 | G72: Intereses | H72: =IFERROR(VLOOKUP(G72,CATEGORÍAS!$A$4:$C$100,2,FALSE()),"Por revisar") -> Ingreso | I72: =IFERROR(VLOOKUP(G72,CATEGORÍAS!$A$4:$C$100,3,FALSE()),"") -> Ahorro | K72: ING|2026-07-31||34.56|55336.25#1
A73: 46231 | B73: =DATE(YEAR(A73),MONTH(A73),1) -> 46204 | C73: CaixaBank | D73: NOMINA EMPRESA EJEMPLO SL | E73: 2150 | F73: 9973.79 | G73: Nómina | H73: =IFERROR(VLOOKUP(G73,CATEGORÍAS!$A$4:$C$100,2,FALSE()),"Por revisar") -> Ingreso | I73: =IFERROR(VLOOKUP(G73,CATEGORÍAS!$A$4:$C$100,3,FALSE()),"") -> Trabajo | K73: CaixaBank|2026-07-28||2150.00|9973.79#1
A74: 46227 | B74: =DATE(YEAR(A74),MONTH(A74),1) -> 46204 | C74: Openbank tarjeta | D74: TIENDA ONLINE | E74: -46.66 | G74: Compras online | H74: =IFERROR(VLOOKUP(G74,CATEGORÍAS!$A$4:$C$100,2,FALSE()),"Por revisar") -> Gasto | I74: =IFERROR(VLOOKUP(G74,CATEGORÍAS!$A$4:$C$100,3,FALSE()),"") -> Personal | K74: Openbank tarjeta|2026-07-24|18:31|-46.66|#1
A75: 46227 | B75: =DATE(YEAR(A75),MONTH(A75),1) -> 46204 | C75: Openbank tarjeta | D75: GASOLINERA RUTA | E75: -43 | G75: Transporte | H75: =IFERROR(VLOOKUP(G75,CATEGORÍAS!$A$4:$C$100,2,FALSE()),"Por revisar") -> Gasto | I75: =IFERROR(VLOOKUP(G75,CATEGORÍAS!$A$4:$C$100,3,FALSE()),"") -> Transporte | K75: Openbank tarjeta|2026-07-24|11:31|-43.00|#1
A76: 46227 | B76: =DATE(YEAR(A76),MONTH(A76),1) -> 46204 | C76: CaixaBank | D76: BIZUM COMPRA | E76: 14 | F76: 7823.79 | G76: Ajustes de gastos compartidos (comida) | H76: =IFERROR(VLOOKUP(G76,CATEGORÍAS!$A$4:$C$100,2,FALSE()),"Por revisar") -> Gasto | I76: =IFERROR(VLOOKUP(G76,CATEGORÍAS!$A$4:$C$100,3,FALSE()),"") -> Comida | K76: CaixaBank|2026-07-24||14.00|7823.79#1
A77: 46225 | B77: =DATE(YEAR(A77),MONTH(A77),1) -> 46204 | C77: Openbank tarjeta | D77: CINE ESTRENOS | E77: -13.79 | G77: Ocio y cultura | H77: =IFERROR(VLOOKUP(G77,CATEGORÍAS!$A$4:$C$100,2,FALSE()),"Por revisar") -> Gasto | I77: =IFERROR(VLOOKUP(G77,CATEGORÍAS!$A$4:$C$100,3,FALSE()),"") -> Ocio | K77: Openbank tarjeta|2026-07-22|21:15|-13.79|#1
A78: 46225 | B78: =DATE(YEAR(A78),MONTH(A78),1) -> 46204 | C78: Openbank tarjeta | D78: CAFETERIA CENTRAL | E78: -6.81 | G78: Restaurantes y caprichos | H78: =IFERROR(VLOOKUP(G78,CATEGORÍAS!$A$4:$C$100,2,FALSE()),"Por revisar") -> Gasto | I78: =IFERROR(VLOOKUP(G78,CATEGORÍAS!$A$4:$C$100,3,FALSE()),"") -> Comida | K78: Openbank tarjeta|2026-07-22|13:15|-6.81|#1
A79: 46225 | B79: =DATE(YEAR(A79),MONTH(A79),1) -> 46204 | C79: Openbank tarjeta | D79: SUPERMERCADO EL BARRIO | E79: -26.88 | G79: Supermercado | H79: =IFERROR(VLOOKUP(G79,CATEGORÍAS!$A$4:$C$100,2,FALSE()),"Por revisar") -> Gasto | I79: =IFERROR(VLOOKUP(G79,CATEGORÍAS!$A$4:$C$100,3,FALSE()),"") -> Comida | K79: Openbank tarjeta|2026-07-22|12:00|-26.88|#1
A80: 46225 | B80: =DATE(YEAR(A80),MONTH(A80),1) -> 46204 | C80: CaixaBank | D80: PELUQUERIA ESTILO | E80: -22 | F80: 7809.79 | G80: Cuidado personal | H80: =IFERROR(VLOOKUP(G80,CATEGORÍAS!$A$4:$C$100,2,FALSE()),"Por revisar") -> Gasto | I80: =IFERROR(VLOOKUP(G80,CATEGORÍAS!$A$4:$C$100,3,FALSE()),"") -> Personal | K80: CaixaBank|2026-07-22||-22.00|7809.79#1
A81: 46222 | B81: =DATE(YEAR(A81),MONTH(A81),1) -> 46204 | C81: Openbank tarjeta | D81: FRUTERIA LA HUERTA | E81: -13.84 | G81: Supermercado | H81: =IFERROR(VLOOKUP(G81,CATEGORÍAS!$A$4:$C$100,2,FALSE()),"Por revisar") -> Gasto | I81: =IFERROR(VLOOKUP(G81,CATEGORÍAS!$A$4:$C$100,3,FALSE()),"") -> Comida | K81: Openbank tarjeta|2026-07-19|16:45|-13.84|#1
A82: 46222 | B82: =DATE(YEAR(A82),MONTH(A82),1) -> 46204 | C82: Openbank tarjeta | D82: FRUTERIA LA HUERTA | E82: -15.83 | G82: Supermercado | H82: =IFERROR(VLOOKUP(G82,CATEGORÍAS!$A$4:$C$100,2,FALSE()),"Por revisar") -> Gasto | I82: =IFERROR(VLOOKUP(G82,CATEGORÍAS!$A$4:$C$100,3,FALSE()),"") -> Comida | K82: Openbank tarjeta|2026-07-19|09:00|-15.83|#1
A83: 46221 | B83: =DATE(YEAR(A83),MONTH(A83),1) -> 46204 | C83: Openbank tarjeta | D83: SUPERMERCADO EL BARRIO | E83: -54.01 | G83: Supermercado | H83: =IFERROR(VLOOKUP(G83,CATEGORÍAS!$A$4:$C$100,2,FALSE()),"Por revisar") -> Gasto | I83: =IFERROR(VLOOKUP(G83,CATEGORÍAS!$A$4:$C$100,3,FALSE()),"") -> Comida | K83: Openbank tarjeta|2026-07-18|16:52|-54.01|#1
A84: 46221 | B84: =DATE(YEAR(A84),MONTH(A84),1) -> 46204 | C84: Openbank tarjeta | D84: CAFETERIA CENTRAL | E84: -7.27 | G84: Restaurantes y caprichos | H84: =IFERROR(VLOOKUP(G84,CATEGORÍAS!$A$4:$C$100,2,FALSE()),"Por revisar") -> Gasto | I84: =IFERROR(VLOOKUP(G84,CATEGORÍAS!$A$4:$C$100,3,FALSE()),"") -> Comida | K84: Openbank tarjeta|2026-07-18|11:22|-7.27|#1
A85: 46221 | B85: =DATE(YEAR(A85),MONTH(A85),1) -> 46204 | C85: CaixaBank | D85: DEVOLUCION AEAT IRPF | E85: 412.36 | F85: 7831.79 | G85: Devolución de Hacienda | H85: =IFERROR(VLOOKUP(G85,CATEGORÍAS!$A$4:$C$100,2,FALSE()),"Por revisar") -> Ingreso | I85: =IFERROR(VLOOKUP(G85,CATEGORÍAS!$A$4:$C$100,3,FALSE()),"") -> Otros ingresos | K85: CaixaBank|2026-07-18||412.36|7831.79#1
A86: 46219 | B86: =DATE(YEAR(A86),MONTH(A86),1) -> 46204 | C86: Openbank tarjeta | D86: RESTAURANTE LA PLAZA | E86: -26.8 | G86: Restaurantes y caprichos | H86: =IFERROR(VLOOKUP(G86,CATEGORÍAS!$A$4:$C$100,2,FALSE()),"Por revisar") -> Gasto | I86: =IFERROR(VLOOKUP(G86,CATEGORÍAS!$A$4:$C$100,3,FALSE()),"") -> Comida | K86: Openbank tarjeta|2026-07-16|15:52|-26.80|#1
A87: 46215 | B87: =DATE(YEAR(A87),MONTH(A87),1) -> 46204 | C87: Openbank tarjeta | D87: RESTAURANTE LA PLAZA | E87: -31.14 | G87: Restaurantes y caprichos | H87: =IFERROR(VLOOKUP(G87,CATEGORÍAS!$A$4:$C$100,2,FALSE()),"Por revisar") -> Gasto | I87: =IFERROR(VLOOKUP(G87,CATEGORÍAS!$A$4:$C$100,3,FALSE()),"") -> Comida | K87: Openbank tarjeta|2026-07-12|20:22|-31.14|#1
A88: 46214 | B88: =DATE(YEAR(A88),MONTH(A88),1) -> 46204 | C88: Openbank tarjeta | D88: CAFETERIA CENTRAL | E88: -6.44 | G88: Restaurantes y caprichos | H88: =IFERROR(VLOOKUP(G88,CATEGORÍAS!$A$4:$C$100,2,FALSE()),"Por revisar") -> Gasto | I88: =IFERROR(VLOOKUP(G88,CATEGORÍAS!$A$4:$C$100,3,FALSE()),"") -> Comida | K88: Openbank tarjeta|2026-07-11|12:22|-6.44|#1
A89: 46214 | B89: =DATE(YEAR(A89),MONTH(A89),1) -> 46204 | C89: Openbank tarjeta | D89: CAFETERIA CENTRAL | E89: -7.95 | G89: Restaurantes y caprichos | H89: =IFERROR(VLOOKUP(G89,CATEGORÍAS!$A$4:$C$100,2,FALSE()),"Por revisar") -> Gasto | I89: =IFERROR(VLOOKUP(G89,CATEGORÍAS!$A$4:$C$100,3,FALSE()),"") -> Comida | K89: Openbank tarjeta|2026-07-11|08:45|-7.95|#1
A90: 46214 | B90: =DATE(YEAR(A90),MONTH(A90),1) -> 46204 | C90: CaixaBank | D90: BIZUM CENA | E90: 28 | F90: 7419.43 | G90: Ajustes de gastos compartidos (comida) | H90: =IFERROR(VLOOKUP(G90,CATEGORÍAS!$A$4:$C$100,2,FALSE()),"Por revisar") -> Gasto | I90: =IFERROR(VLOOKUP(G90,CATEGORÍAS!$A$4:$C$100,3,FALSE()),"") -> Comida | K90: CaixaBank|2026-07-11||28.00|7419.43#1
A91: 46212 | B91: =DATE(YEAR(A91),MONTH(A91),1) -> 46204 | C91: Openbank tarjeta | D91: CAFETERIA CENTRAL | E91: -8.6 | G91: Restaurantes y caprichos | H91: =IFERROR(VLOOKUP(G91,CATEGORÍAS!$A$4:$C$100,2,FALSE()),"Por revisar") -> Gasto | I91: =IFERROR(VLOOKUP(G91,CATEGORÍAS!$A$4:$C$100,3,FALSE()),"") -> Comida | K91: Openbank tarjeta|2026-07-09|08:07|-8.60|#1
A92: 46212 | B92: =DATE(YEAR(A92),MONTH(A92),1) -> 46204 | C92: CaixaBank | D92: RECIBO STREAMFLIX | E92: -12.99 | F92: 7391.43 | G92: Suscripciones | H92: =IFERROR(VLOOKUP(G92,CATEGORÍAS!$A$4:$C$100,2,FALSE()),"Por revisar") -> Gasto | I92: =IFERROR(VLOOKUP(G92,CATEGORÍAS!$A$4:$C$100,3,FALSE()),"") -> Personal | K92: CaixaBank|2026-07-09||-12.99|7391.43#1
A93: 46211 | B93: =DATE(YEAR(A93),MONTH(A93),1) -> 46204 | C93: Openbank tarjeta | D93: SUPERMERCADO EL BARRIO | E93: -67.04 | G93: Supermercado | H93: =IFERROR(VLOOKUP(G93,CATEGORÍAS!$A$4:$C$100,2,FALSE()),"Por revisar") -> Gasto | I93: =IFERROR(VLOOKUP(G93,CATEGORÍAS!$A$4:$C$100,3,FALSE()),"") -> Comida | K93: Openbank tarjeta|2026-07-08|11:31|-67.04|#1
A94: 46211 | B94: =DATE(YEAR(A94),MONTH(A94),1) -> 46204 | C94: CaixaBank | D94: RECIBO LUZ HOGAR ENERGIA | E94: -42.64 | F94: 7404.42 | G94: Luz y gas | H94: =IFERROR(VLOOKUP(G94,CATEGORÍAS!$A$4:$C$100,2,FALSE()),"Por revisar") -> Gasto | I94: =IFERROR(VLOOKUP(G94,CATEGORÍAS!$A$4:$C$100,3,FALSE()),"") -> Casa | K94: CaixaBank|2026-07-08||-42.64|7404.42#1
A95: 46210 | B95: =DATE(YEAR(A95),MONTH(A95),1) -> 46204 | C95: Openbank tarjeta | D95: TRANSPORTE PUBLICO RECARGA | E95: -20 | G95: Transporte | H95: =IFERROR(VLOOKUP(G95,CATEGORÍAS!$A$4:$C$100,2,FALSE()),"Por revisar") -> Gasto | I95: =IFERROR(VLOOKUP(G95,CATEGORÍAS!$A$4:$C$100,3,FALSE()),"") -> Transporte | K95: Openbank tarjeta|2026-07-07|16:52|-20.00|#1
A96: 46209 | B96: =DATE(YEAR(A96),MONTH(A96),1) -> 46204 | C96: CaixaBank | D96: RECIBO MOVILCOM | E96: -14.95 | F96: 7447.06 | G96: Móvil | H96: =IFERROR(VLOOKUP(G96,CATEGORÍAS!$A$4:$C$100,2,FALSE()),"Por revisar") -> Gasto | I96: =IFERROR(VLOOKUP(G96,CATEGORÍAS!$A$4:$C$100,3,FALSE()),"") -> Personal | K96: CaixaBank|2026-07-06||-14.95|7447.06#1
A97: 46208 | B97: =DATE(YEAR(A97),MONTH(A97),1) -> 46204 | C97: CaixaBank | D97: RECIBO FIBRANET | E97: -39.9 | F97: 7462.01 | G97: Internet y teléfono fijo | H97: =IFERROR(VLOOKUP(G97,CATEGORÍAS!$A$4:$C$100,2,FALSE()),"Por revisar") -> Gasto | I97: =IFERROR(VLOOKUP(G97,CATEGORÍAS!$A$4:$C$100,3,FALSE()),"") -> Casa | K97: CaixaBank|2026-07-05||-39.90|7462.01#1
A98: 46208 | B98: =DATE(YEAR(A98),MONTH(A98),1) -> 46204 | C98: Openbank | D98: LIQUIDACION TARJETA CREDITO | E98: -444.06 | F98: 1396.85 | G98: Pago de la tarjeta | H98: =IFERROR(VLOOKUP(G98,CATEGORÍAS!$A$4:$C$100,2,FALSE()),"Por revisar") -> Traspaso | I98: =IFERROR(VLOOKUP(G98,CATEGORÍAS!$A$4:$C$100,3,FALSE()),"") -> Traspasos | K98: Openbank|2026-07-05||-444.06|1396.85#1
A99: 46206 | B99: =DATE(YEAR(A99),MONTH(A99),1) -> 46204 | C99: CaixaBank | D99: TRANSFERENCIA CUENTA DE VIAJES | E99: -150 | F99: 7501.91 | G99: Aportación a la cuenta de viajes | H99: =IFERROR(VLOOKUP(G99,CATEGORÍAS!$A$4:$C$100,2,FALSE()),"Por revisar") -> Gasto | I99: =IFERROR(VLOOKUP(G99,CATEGORÍAS!$A$4:$C$100,3,FALSE()),"") -> Viajes | K99: CaixaBank|2026-07-03||-150.00|7501.91#1
A100: 46205 | B100: =DATE(YEAR(A100),MONTH(A100),1) -> 46204 | C100: Openbank tarjeta | D100: FARMACIA SAN JOSE | E100: -23.93 | G100: Salud y farmacia | H100: =IFERROR(VLOOKUP(G100,CATEGORÍAS!$A$4:$C$100,2,FALSE()),"Por revisar") -> Gasto | I100: =IFERROR(VLOOKUP(G100,CATEGORÍAS!$A$4:$C$100,3,FALSE()),"") -> Salud | K100: Openbank tarjeta|2026-07-02|21:00|-23.93|#1
...

Sheet FLEXIBLE
A1: FLEXIBLE · retribución flexible
A2: Lo que gastas con la tarjeta de retribución flexible de tu empresa y se descuenta de la nómina. Copia cada mes esas líneas de tu nómina. Cuenta a la vez como ingreso y como gasto: tu ahorro no cambia, tus gastos reales sí.
A3: Mes de la nómina | B3: Comida | C3: Transporte | D3: Total | E3: Nota | F3: mes (calc)
A4: 46174 | B4: 118.4 | C4: 40 | D4: =IF(A4="","",N(B4)+N(C4)) -> 158.4 | E4: Nómina de junio | F4: =IF(A4="","",DATE(YEAR(A4),MONTH(A4),1)) -> 46174
A5: 46204 | B5: 131.25 | C5: 40 | D5: =IF(A5="","",N(B5)+N(C5)) -> 171.25 | E5: Nómina de julio | F5: =IF(A5="","",DATE(YEAR(A5),MONTH(A5),1)) -> 46204
A6: 46235 | B6: 96.1 | C6: 20 | D6: =IF(A6="","",N(B6)+N(C6)) -> 116.1 | E6: Agosto, vacaciones | F6: =IF(A6="","",DATE(YEAR(A6),MONTH(A6),1)) -> 46235
A7: 46266 | B7: 124.8 | C7: 40 | D7: =IF(A7="","",N(B7)+N(C7)) -> 164.8 | E7: Nómina de septiembre | F7: =IF(A7="","",DATE(YEAR(A7),MONTH(A7),1)) -> 46266
D8: =IF(A8="","",N(B8)+N(C8)) | F8: =IF(A8="","",DATE(YEAR(A8),MONTH(A8),1))
D9: =IF(A9="","",N(B9)+N(C9)) | F9: =IF(A9="","",DATE(YEAR(A9),MONTH(A9),1))
D10: =IF(A10="","",N(B10)+N(C10)) | F10: =IF(A10="","",DATE(YEAR(A10),MONTH(A10),1))
D11: =IF(A11="","",N(B11)+N(C11)) | F11: =IF(A11="","",DATE(YEAR(A11),MONTH(A11),1))
D12: =IF(A12="","",N(B12)+N(C12)) | F12: =IF(A12="","",DATE(YEAR(A12),MONTH(A12),1))
D13: =IF(A13="","",N(B13)+N(C13)) | F13: =IF(A13="","",DATE(YEAR(A13),MONTH(A13),1))
D14: =IF(A14="","",N(B14)+N(C14)) | F14: =IF(A14="","",DATE(YEAR(A14),MONTH(A14),1))
D15: =IF(A15="","",N(B15)+N(C15)) | F15: =IF(A15="","",DATE(YEAR(A15),MONTH(A15),1))
D16: =IF(A16="","",N(B16)+N(C16)) | F16: =IF(A16="","",DATE(YEAR(A16),MONTH(A16),1))
D17: =IF(A17="","",N(B17)+N(C17)) | F17: =IF(A17="","",DATE(YEAR(A17),MONTH(A17),1))
D18: =IF(A18="","",N(B18)+N(C18)) | F18: =IF(A18="","",DATE(YEAR(A18),MONTH(A18),1))
D19: =IF(A19="","",N(B19)+N(C19)) | F19: =IF(A19="","",DATE(YEAR(A19),MONTH(A19),1))
... D200: =IF(A200="","",N(B200)+N(C200)) | F200: =IF(A200="","",DATE(YEAR(A200),MONTH(A200),1))

Sheet CASA
A1: CASA · gastos de la vivienda
A2: Gastos de la vivienda por concepto, últimos 12 meses. Sale de las categorías del grupo «Casa».
A3: Si añades una categoría del grupo «Casa» en CATEGORÍAS, añade aquí su fila.
A4: Concepto | B4: =EDATE(INDEX('MIS DATOS'!$A$6:$A$245,COUNT('MIS DATOS'!$A$6:$A$245)),-11) -> 45931 | C4: =EDATE(INDEX('MIS DATOS'!$A$6:$A$245,COUNT('MIS DATOS'!$A$6:$A$245)),-10) -> 45962 | D4: =EDATE(INDEX('MIS DATOS'!$A$6:$A$245,COUNT('MIS DATOS'!$A$6:$A$245)),-9) -> 45992 | E4: =EDATE(INDEX('MIS DATOS'!$A$6:$A$245,COUNT('MIS DATOS'!$A$6:$A$245)),-8) -> 46023 | F4: =EDATE(INDEX('MIS DATOS'!$A$6:$A$245,COUNT('MIS DATOS'!$A$6:$A$245)),-7) -> 46054 | G4: =EDATE(INDEX('MIS DATOS'!$A$6:$A$245,COUNT('MIS DATOS'!$A$6:$A$245)),-6) -> 46082 | H4: =EDATE(INDEX('MIS DATOS'!$A$6:$A$245,COUNT('MIS DATOS'!$A$6:$A$245)),-5) -> 46113 | I4: =EDATE(INDEX('MIS DATOS'!$A$6:$A$245,COUNT('MIS DATOS'!$A$6:$A$245)),-4) -> 46143 | J4: =EDATE(INDEX('MIS DATOS'!$A$6:$A$245,COUNT('MIS DATOS'!$A$6:$A$245)),-3) -> 46174 | K4: =EDATE(INDEX('MIS DATOS'!$A$6:$A$245,COUNT('MIS DATOS'!$A$6:$A$245)),-2) -> 46204 | L4: =EDATE(INDEX('MIS DATOS'!$A$6:$A$245,COUNT('MIS DATOS'!$A$6:$A$245)),-1) -> 46235 | M4: =EDATE(INDEX('MIS DATOS'!$A$6:$A$245,COUNT('MIS DATOS'!$A$6:$A$245)),0) -> 46266 | N4: Total 12 meses | O4: Media al mes | P4: Último mes
A5: Alquiler | B5: =-SUMIFS(MOVIMIENTOS!$E$4:$E$20000,MOVIMIENTOS!$G$4:$G$20000,$A5,MOVIMIENTOS!$B$4:$B$20000,B$4) -> 850 | C5: =-SUMIFS(MOVIMIENTOS!$E$4:$E$20000,MOVIMIENTOS!$G$4:$G$20000,$A5,MOVIMIENTOS!$B$4:$B$20000,C$4) -> 850 | D5: =-SUMIFS(MOVIMIENTOS!$E$4:$E$20000,MOVIMIENTOS!$G$4:$G$20000,$A5,MOVIMIENTOS!$B$4:$B$20000,D$4) -> 850 | E5: =-SUMIFS(MOVIMIENTOS!$E$4:$E$20000,MOVIMIENTOS!$G$4:$G$20000,$A5,MOVIMIENTOS!$B$4:$B$20000,E$4) -> 850 | F5: =-SUMIFS(MOVIMIENTOS!$E$4:$E$20000,MOVIMIENTOS!$G$4:$G$20000,$A5,MOVIMIENTOS!$B$4:$B$20000,F$4) -> 850 | G5: =-SUMIFS(MOVIMIENTOS!$E$4:$E$20000,MOVIMIENTOS!$G$4:$G$20000,$A5,MOVIMIENTOS!$B$4:$B$20000,G$4) -> 850 | H5: =-SUMIFS(MOVIMIENTOS!$E$4:$E$20000,MOVIMIENTOS!$G$4:$G$20000,$A5,MOVIMIENTOS!$B$4:$B$20000,H$4) -> 850 | I5: =-SUMIFS(MOVIMIENTOS!$E$4:$E$20000,MOVIMIENTOS!$G$4:$G$20000,$A5,MOVIMIENTOS!$B$4:$B$20000,I$4) -> 850 | ... M5: =-SUMIFS(MOVIMIENTOS!$E$4:$E$20000,MOVIMIENTOS!$G$4:$G$20000,$A5,MOVIMIENTOS!$B$4:$B$20000,M$4) -> 850 | N5: =SUM(B5:M5) -> 10200 | O5: =IFERROR(SUMIFS(B5:M5,$B$4:$M$4,"<"&DATE(YEAR(TODAY()),MONTH(TODAY()),1))/$B$15,0) -> 850 | P5: =M5 -> 850
A6: Comunidad | B6: =-SUMIFS(MOVIMIENTOS!$E$4:$E$20000,MOVIMIENTOS!$G$4:$G$20000,$A6,MOVIMIENTOS!$B$4:$B$20000,B$4) -> 0 | C6: =-SUMIFS(MOVIMIENTOS!$E$4:$E$20000,MOVIMIENTOS!$G$4:$G$20000,$A6,MOVIMIENTOS!$B$4:$B$20000,C$4) -> 0 | D6: =-SUMIFS(MOVIMIENTOS!$E$4:$E$20000,MOVIMIENTOS!$G$4:$G$20000,$A6,MOVIMIENTOS!$B$4:$B$20000,D$4) -> 0 | E6: =-SUMIFS(MOVIMIENTOS!$E$4:$E$20000,MOVIMIENTOS!$G$4:$G$20000,$A6,MOVIMIENTOS!$B$4:$B$20000,E$4) -> 0 | F6: =-SUMIFS(MOVIMIENTOS!$E$4:$E$20000,MOVIMIENTOS!$G$4:$G$20000,$A6,MOVIMIENTOS!$B$4:$B$20000,F$4) -> 0 | G6: =-SUMIFS(MOVIMIENTOS!$E$4:$E$20000,MOVIMIENTOS!$G$4:$G$20000,$A6,MOVIMIENTOS!$B$4:$B$20000,G$4) -> 0 | H6: =-SUMIFS(MOVIMIENTOS!$E$4:$E$20000,MOVIMIENTOS!$G$4:$G$20000,$A6,MOVIMIENTOS!$B$4:$B$20000,H$4) -> 0 | I6: =-SUMIFS(MOVIMIENTOS!$E$4:$E$20000,MOVIMIENTOS!$G$4:$G$20000,$A6,MOVIMIENTOS!$B$4:$B$20000,I$4) -> 0 | ... M6: =-SUMIFS(MOVIMIENTOS!$E$4:$E$20000,MOVIMIENTOS!$G$4:$G$20000,$A6,MOVIMIENTOS!$B$4:$B$20000,M$4) -> 0 | N6: =SUM(B6:M6) -> 0 | O6: =IFERROR(SUMIFS(B6:M6,$B$4:$M$4,"<"&DATE(YEAR(TODAY()),MONTH(TODAY()),1))/$B$15,0) -> 0 | P6: =M6 -> 0
A7: Luz y gas | B7: =-SUMIFS(MOVIMIENTOS!$E$4:$E$20000,MOVIMIENTOS!$G$4:$G$20000,$A7,MOVIMIENTOS!$B$4:$B$20000,B$4) -> 37.38 | C7: =-SUMIFS(MOVIMIENTOS!$E$4:$E$20000,MOVIMIENTOS!$G$4:$G$20000,$A7,MOVIMIENTOS!$B$4:$B$20000,C$4) -> 50.32 | D7: =-SUMIFS(MOVIMIENTOS!$E$4:$E$20000,MOVIMIENTOS!$G$4:$G$20000,$A7,MOVIMIENTOS!$B$4:$B$20000,D$4) -> 58.18 | E7: =-SUMIFS(MOVIMIENTOS!$E$4:$E$20000,MOVIMIENTOS!$G$4:$G$20000,$A7,MOVIMIENTOS!$B$4:$B$20000,E$4) -> 63.54 | F7: =-SUMIFS(MOVIMIENTOS!$E$4:$E$20000,MOVIMIENTOS!$G$4:$G$20000,$A7,MOVIMIENTOS!$B$4:$B$20000,F$4) -> 49.8 | G7: =-SUMIFS(MOVIMIENTOS!$E$4:$E$20000,MOVIMIENTOS!$G$4:$G$20000,$A7,MOVIMIENTOS!$B$4:$B$20000,G$4) -> 40.63 | H7: =-SUMIFS(MOVIMIENTOS!$E$4:$E$20000,MOVIMIENTOS!$G$4:$G$20000,$A7,MOVIMIENTOS!$B$4:$B$20000,H$4) -> 36.17 | I7: =-SUMIFS(MOVIMIENTOS!$E$4:$E$20000,MOVIMIENTOS!$G$4:$G$20000,$A7,MOVIMIENTOS!$B$4:$B$20000,I$4) -> 47.6 | ... M7: =-SUMIFS(MOVIMIENTOS!$E$4:$E$20000,MOVIMIENTOS!$G$4:$G$20000,$A7,MOVIMIENTOS!$B$4:$B$20000,M$4) -> 38.08 | N7: =SUM(B7:M7) -> 592.4 | O7: =IFERROR(SUMIFS(B7:M7,$B$4:$M$4,"<"&DATE(YEAR(TODAY()),MONTH(TODAY()),1))/$B$15,0) -> 49.366667 | P7: =M7 -> 38.08
A8: Agua | B8: =-SUMIFS(MOVIMIENTOS!$E$4:$E$20000,MOVIMIENTOS!$G$4:$G$20000,$A8,MOVIMIENTOS!$B$4:$B$20000,B$4) -> 36.52 | C8: =-SUMIFS(MOVIMIENTOS!$E$4:$E$20000,MOVIMIENTOS!$G$4:$G$20000,$A8,MOVIMIENTOS!$B$4:$B$20000,C$4) -> 0 | D8: =-SUMIFS(MOVIMIENTOS!$E$4:$E$20000,MOVIMIENTOS!$G$4:$G$20000,$A8,MOVIMIENTOS!$B$4:$B$20000,D$4) -> 32.13 | E8: =-SUMIFS(MOVIMIENTOS!$E$4:$E$20000,MOVIMIENTOS!$G$4:$G$20000,$A8,MOVIMIENTOS!$B$4:$B$20000,E$4) -> 0 | F8: =-SUMIFS(MOVIMIENTOS!$E$4:$E$20000,MOVIMIENTOS!$G$4:$G$20000,$A8,MOVIMIENTOS!$B$4:$B$20000,F$4) -> 37.59 | G8: =-SUMIFS(MOVIMIENTOS!$E$4:$E$20000,MOVIMIENTOS!$G$4:$G$20000,$A8,MOVIMIENTOS!$B$4:$B$20000,G$4) -> 0 | H8: =-SUMIFS(MOVIMIENTOS!$E$4:$E$20000,MOVIMIENTOS!$G$4:$G$20000,$A8,MOVIMIENTOS!$B$4:$B$20000,H$4) -> 34 | I8: =-SUMIFS(MOVIMIENTOS!$E$4:$E$20000,MOVIMIENTOS!$G$4:$G$20000,$A8,MOVIMIENTOS!$B$4:$B$20000,I$4) -> 0 | ... M8: =-SUMIFS(MOVIMIENTOS!$E$4:$E$20000,MOVIMIENTOS!$G$4:$G$20000,$A8,MOVIMIENTOS!$B$4:$B$20000,M$4) -> 0 | N8: =SUM(B8:M8) -> 213.48 | O8: =IFERROR(SUMIFS(B8:M8,$B$4:$M$4,"<"&DATE(YEAR(TODAY()),MONTH(TODAY()),1))/$B$15,0) -> 17.79 | P8: =M8 -> 0
A9: Internet y teléfono fijo | B9: =-SUMIFS(MOVIMIENTOS!$E$4:$E$20000,MOVIMIENTOS!$G$4:$G$20000,$A9,MOVIMIENTOS!$B$4:$B$20000,B$4) -> 39.9 | C9: =-SUMIFS(MOVIMIENTOS!$E$4:$E$20000,MOVIMIENTOS!$G$4:$G$20000,$A9,MOVIMIENTOS!$B$4:$B$20000,C$4) -> 39.9 | D9: =-SUMIFS(MOVIMIENTOS!$E$4:$E$20000,MOVIMIENTOS!$G$4:$G$20000,$A9,MOVIMIENTOS!$B$4:$B$20000,D$4) -> 39.9 | E9: =-SUMIFS(MOVIMIENTOS!$E$4:$E$20000,MOVIMIENTOS!$G$4:$G$20000,$A9,MOVIMIENTOS!$B$4:$B$20000,E$4) -> 39.9 | F9: =-SUMIFS(MOVIMIENTOS!$E$4:$E$20000,MOVIMIENTOS!$G$4:$G$20000,$A9,MOVIMIENTOS!$B$4:$B$20000,F$4) -> 39.9 | G9: =-SUMIFS(MOVIMIENTOS!$E$4:$E$20000,MOVIMIENTOS!$G$4:$G$20000,$A9,MOVIMIENTOS!$B$4:$B$20000,G$4) -> 39.9 | H9: =-SUMIFS(MOVIMIENTOS!$E$4:$E$20000,MOVIMIENTOS!$G$4:$G$20000,$A9,MOVIMIENTOS!$B$4:$B$20000,H$4) -> 39.9 | I9: =-SUMIFS(MOVIMIENTOS!$E$4:$E$20000,MOVIMIENTOS!$G$4:$G$20000,$A9,MOVIMIENTOS!$B$4:$B$20000,I$4) -> 39.9 | ... M9: =-SUMIFS(MOVIMIENTOS!$E$4:$E$20000,MOVIMIENTOS!$G$4:$G$20000,$A9,MOVIMIENTOS!$B$4:$B$20000,M$4) -> 39.9 | N9: =SUM(B9:M9) -> 478.8 | O9: =IFERROR(SUMIFS(B9:M9,$B$4:$M$4,"<"&DATE(YEAR(TODAY()),MONTH(TODAY()),1))/$B$15,0) -> 39.9 | P9: =M9 -> 39.9
A10: IBI y tasas | B10: =-SUMIFS(MOVIMIENTOS!$E$4:$E$20000,MOVIMIENTOS!$G$4:$G$20000,$A10,MOVIMIENTOS!$B$4:$B$20000,B$4) -> 0 | C10: =-SUMIFS(MOVIMIENTOS!$E$4:$E$20000,MOVIMIENTOS!$G$4:$G$20000,$A10,MOVIMIENTOS!$B$4:$B$20000,C$4) -> 0 | D10: =-SUMIFS(MOVIMIENTOS!$E$4:$E$20000,MOVIMIENTOS!$G$4:$G$20000,$A10,MOVIMIENTOS!$B$4:$B$20000,D$4) -> 0 | E10: =-SUMIFS(MOVIMIENTOS!$E$4:$E$20000,MOVIMIENTOS!$G$4:$G$20000,$A10,MOVIMIENTOS!$B$4:$B$20000,E$4) -> 0 | F10: =-SUMIFS(MOVIMIENTOS!$E$4:$E$20000,MOVIMIENTOS!$G$4:$G$20000,$A10,MOVIMIENTOS!$B$4:$B$20000,F$4) -> 0 | G10: =-SUMIFS(MOVIMIENTOS!$E$4:$E$20000,MOVIMIENTOS!$G$4:$G$20000,$A10,MOVIMIENTOS!$B$4:$B$20000,G$4) -> 0 | H10: =-SUMIFS(MOVIMIENTOS!$E$4:$E$20000,MOVIMIENTOS!$G$4:$G$20000,$A10,MOVIMIENTOS!$B$4:$B$20000,H$4) -> 0 | I10: =-SUMIFS(MOVIMIENTOS!$E$4:$E$20000,MOVIMIENTOS!$G$4:$G$20000,$A10,MOVIMIENTOS!$B$4:$B$20000,I$4) -> 0 | ... M10: =-SUMIFS(MOVIMIENTOS!$E$4:$E$20000,MOVIMIENTOS!$G$4:$G$20000,$A10,MOVIMIENTOS!$B$4:$B$20000,M$4) -> 0 | N10: =SUM(B10:M10) -> 0 | O10: =IFERROR(SUMIFS(B10:M10,$B$4:$M$4,"<"&DATE(YEAR(TODAY()),MONTH(TODAY()),1))/$B$15,0) -> 0 | P10: =M10 -> 0
A11: Seguro del hogar | B11: =-SUMIFS(MOVIMIENTOS!$E$4:$E$20000,MOVIMIENTOS!$G$4:$G$20000,$A11,MOVIMIENTOS!$B$4:$B$20000,B$4) -> 0 | C11: =-SUMIFS(MOVIMIENTOS!$E$4:$E$20000,MOVIMIENTOS!$G$4:$G$20000,$A11,MOVIMIENTOS!$B$4:$B$20000,C$4) -> 0 | D11: =-SUMIFS(MOVIMIENTOS!$E$4:$E$20000,MOVIMIENTOS!$G$4:$G$20000,$A11,MOVIMIENTOS!$B$4:$B$20000,D$4) -> 0 | E11: =-SUMIFS(MOVIMIENTOS!$E$4:$E$20000,MOVIMIENTOS!$G$4:$G$20000,$A11,MOVIMIENTOS!$B$4:$B$20000,E$4) -> 0 | F11: =-SUMIFS(MOVIMIENTOS!$E$4:$E$20000,MOVIMIENTOS!$G$4:$G$20000,$A11,MOVIMIENTOS!$B$4:$B$20000,F$4) -> 0 | G11: =-SUMIFS(MOVIMIENTOS!$E$4:$E$20000,MOVIMIENTOS!$G$4:$G$20000,$A11,MOVIMIENTOS!$B$4:$B$20000,G$4) -> 148 | H11: =-SUMIFS(MOVIMIENTOS!$E$4:$E$20000,MOVIMIENTOS!$G$4:$G$20000,$A11,MOVIMIENTOS!$B$4:$B$20000,H$4) -> 0 | I11: =-SUMIFS(MOVIMIENTOS!$E$4:$E$20000,MOVIMIENTOS!$G$4:$G$20000,$A11,MOVIMIENTOS!$B$4:$B$20000,I$4) -> 0 | ... M11: =-SUMIFS(MOVIMIENTOS!$E$4:$E$20000,MOVIMIENTOS!$G$4:$G$20000,$A11,MOVIMIENTOS!$B$4:$B$20000,M$4) -> 0 | N11: =SUM(B11:M11) -> 148 | O11: =IFERROR(SUMIFS(B11:M11,$B$4:$M$4,"<"&DATE(YEAR(TODAY()),MONTH(TODAY()),1))/$B$15,0) -> 12.333333 | P11: =M11 -> 0
A12: Mantenimiento del hogar | B12: =-SUMIFS(MOVIMIENTOS!$E$4:$E$20000,MOVIMIENTOS!$G$4:$G$20000,$A12,MOVIMIENTOS!$B$4:$B$20000,B$4) -> 0 | C12: =-SUMIFS(MOVIMIENTOS!$E$4:$E$20000,MOVIMIENTOS!$G$4:$G$20000,$A12,MOVIMIENTOS!$B$4:$B$20000,C$4) -> 0 | D12: =-SUMIFS(MOVIMIENTOS!$E$4:$E$20000,MOVIMIENTOS!$G$4:$G$20000,$A12,MOVIMIENTOS!$B$4:$B$20000,D$4) -> 0 | E12: =-SUMIFS(MOVIMIENTOS!$E$4:$E$20000,MOVIMIENTOS!$G$4:$G$20000,$A12,MOVIMIENTOS!$B$4:$B$20000,E$4) -> 0 | F12: =-SUMIFS(MOVIMIENTOS!$E$4:$E$20000,MOVIMIENTOS!$G$4:$G$20000,$A12,MOVIMIENTOS!$B$4:$B$20000,F$4) -> 0 | G12: =-SUMIFS(MOVIMIENTOS!$E$4:$E$20000,MOVIMIENTOS!$G$4:$G$20000,$A12,MOVIMIENTOS!$B$4:$B$20000,G$4) -> 0 | H12: =-SUMIFS(MOVIMIENTOS!$E$4:$E$20000,MOVIMIENTOS!$G$4:$G$20000,$A12,MOVIMIENTOS!$B$4:$B$20000,H$4) -> 0 | I12: =-SUMIFS(MOVIMIENTOS!$E$4:$E$20000,MOVIMIENTOS!$G$4:$G$20000,$A12,MOVIMIENTOS!$B$4:$B$20000,I$4) -> 0 | ... M12: =-SUMIFS(MOVIMIENTOS!$E$4:$E$20000,MOVIMIENTOS!$G$4:$G$20000,$A12,MOVIMIENTOS!$B$4:$B$20000,M$4) -> 0 | N12: =SUM(B12:M12) -> 0 | O12: =IFERROR(SUMIFS(B12:M12,$B$4:$M$4,"<"&DATE(YEAR(TODAY()),MONTH(TODAY()),1))/$B$15,0) -> 0 | P12: =M12 -> 0
A13: Total casa | B13: =SUM(B5:B12) -> 963.8 | C13: =SUM(C5:C12) -> 940.22 | D13: =SUM(D5:D12) -> 980.21 | E13: =SUM(E5:E12) -> 953.44 | F13: =SUM(F5:F12) -> 977.29 | G13: =SUM(G5:G12) -> 1078.53 | H13: =SUM(H5:H12) -> 960.07 | I13: =SUM(I5:I12) -> 937.5 | ... P13: =SUM(P5:P12) -> 927.98
A15: Meses con datos en la ventana | B15: =COUNTIFS($B$4:$M$4,">="&'MIS DATOS'!$A$6,$B$4:$M$4,"<"&DATE(YEAR(TODAY()),MONTH(TODAY()),1)) -> 12
A16: · La media usa solo meses completos con datos. Agua y algunos recibos son bimestrales: mira la media, no un mes suelto.

Sheet DECISIONES
A1: DECISIONES · ¿qué pasa si…?
A2: Cambia las palancas y mira en MI FUTURO cómo se mueve tu patrimonio frente al plan base.
A4: PALANCAS
A5: Pasar ya de tu efectivo a inversión | B5: 0 | C5: Si tu efectivo casi no da intereses, prueba qué pasa si inviertes una parte
A6: Aportación mensual a inversión | B6: 0
A7: Recorte de gastos mensuales | B7: 0
A8: ¿Inviertes lo que recortas? | B8: Sí
A9: Rentabilidad de la inversión en este escenario | B9: 0.05
A10: ¿Incluir la compra de la vivienda? | B10: Sí
A11: Escenario de compra | B11: Comprar ya | C11: Los números salen de VIVIENDA
A13: LO QUE ENTRA Y SALE (calculado)
A14: Dentro de cuántos años compras | B14: =IF(DECISIONES!$B$11="Comprar ya",0,VIVIENDA!$B$15) -> 0
A15: Sale de tus ahorros para la compra | B15: =IF(DECISIONES!$B$10="Sí",IF(DECISIONES!$B$11="Comprar ya",VIVIENDA!$B$26,VIVIENDA!$G$27),0) -> 55000
A16: Hipoteca | B16: =IF(DECISIONES!$B$10="Sí",IF(DECISIONES!$B$11="Comprar ya",VIVIENDA!$B$25,VIVIENDA!$G$26),0) -> 181100
A17: Cuota mensual | B17: =IF(DECISIONES!$B$10="Sí",IF(DECISIONES!$B$11="Comprar ya",VIVIENDA!$B$30,VIVIENDA!$G$30),0) -> 849.40697
A18: Años de hipoteca | B18: =IF(DECISIONES!$B$11="Comprar ya",VIVIENDA!$B$29,VIVIENDA!$G$29) -> 25
A19: Alquiler que dejas de pagar al comprar (al mes, € de hoy) | B19: =IF(DECISIONES!$B$10="Sí",VIVIENDA!$B$14,0) -> 850
A21: =IF(AND(DECISIONES!$B$10="Sí",DECISIONES!$B$14=0,DECISIONES!$B$15>PROYECCIÓN!$B$5+PROYECCIÓN!$B$6-PARÁMETROS!$B$15*PARÁMETROS!$B$18),"⚠️ Con tus saldos de hoy, la compra se come parte del colchón de emergencia","")
A22: =IF(AND(DECISIONES!$B$10="Sí",DECISIONES!$B$14+DECISIONES!$B$18>PARÁMETROS!$B$5-PARÁMETROS!$B$4),"ℹ️ La hipoteca sigue "&(DECISIONES!$B$14+DECISIONES!$B$18-(PARÁMETROS!$B$5-PARÁMETROS!$B$4))&" años después de jubilarte: la cuota se suma a lo que sacas","")
A24: · El escenario saca la compra de tu inversión y paga la cuota con lo que ibas a aportar. Desde que compras, el alquiler que ya no pagas va a tu inversión y deja de contar como gasto.
A25: · Los inmuebles no cuentan como libertad financiera: no dan para vivir salvo que den renta o los vendas.

Sheet HISTORIAL
A1: HISTORIAL · lo que he ido cambiando
A2: Cada vez que cambias una cifra del plan (aportación a viajes, pensión, una decisión…), apúntalo aquí: la más reciente arriba.
A3: Fecha | B3: Qué cambia | C3: Antes | D3: Ahora | E3: Por qué | F3: Dónde
A4: 46295 | B4: Cuenta de viajes | C4: — | D4: 150 €/mes | E4: Pagar mi parte de los viajes desde una cuenta aparte | F4: VIAJES
A5: 46280 | B5: Retribución flexible | C5: No se contaba | D5: Comida y transporte desde junio | E5: Se descuenta de la nómina: es gasto real aunque no pase por el banco | F5: FLEXIBLE

Sheet VIVIENDA
A1: VIVIENDA · ¿Comprar ahora o esperar?
A2: Compara comprar ya con seguir de alquiler unos años y comprar después, con el mismo esfuerzo al mes. Datos ficticios: pon los tuyos.
A4: SUPUESTOS
A5: Precio de la vivienda | B5: 220000 | C5: Ficticio. Lo que costaría hoy
A6: Parte que ya tienes | B6: 0 | C6: 0 % si la compras entera
A7: Ahorros que pones en la compra | B7: 55000 | C7: El resto lo financia la hipoteca
A8: Impuestos de la compra | B8: 0.06 | C8: ITP si es de segunda mano (cambia según la comunidad autónoma); IVA y AJD si es nueva. Confírmalo
A9: Notaría + registro + gestoría | B9: 2500 | C9: Estimación; pide presupuesto
A10: Coste de la tasación | B10: 400 | C10: La paga el comprador
A11: Tipo de interés de la hipoteca | B11: 0.029 | C11: Ficticio: compara ofertas
A12: Plazo de la hipoteca que pedirías (años) | B12: 25
A13: Edad máxima al terminar de pagar | B13: 75 | C13: Muchos bancos ponen el límite entre 70 y 75: pregúntalo. Si se pasa, el plazo se acorta solo
A14: Alquiler que pagas mientras no compras (al mes) | B14: 850 | C14: Si ya vives en tu casa, pon 0
A15: Años de espera (escenario B) | B15: 3
A16: Horizonte de comparación (años) | B16: 20 | C16: Máximo 30
A17: Revalorización anual de la vivienda | B17: =PARÁMETROS!$B$19 -> 0.03 | C17: Viene de PARÁMETROS
A18: Rentabilidad si el dinero sigue invertido | B18: =PARÁMETROS!$B$7 -> 0.05 | C18: Viene de PARÁMETROS
A20: ESCENARIO A · COMPRAR YA | F20: ESCENARIO B · ESPERAR
A21: Lo que compras (precio × lo que te falta) | B21: =$B$5*(1-$B$6) -> 220000 | F21: Precio de la vivienda cuando compres | G21: =$B$5*(1+$B$17)^$B$15 -> 240399.94
A22: Impuestos | B22: =B21*$B$8 -> 13200 | F22: Lo que compras entonces | G22: =G21*(1-$B$6) -> 240399.94
A23: Gastos totales (impuestos + notaría + tasación) | B23: =B22+$B$9+$B$10 -> 16100 | F23: Gastos totales | G23: =G22*$B$8+$B$9+$B$10 -> 17323.996
A24: Dinero necesario | B24: =B21+B23 -> 236100 | F24: Dinero necesario | G24: =G22+G23 -> 257723.94
A25: Hipoteca | B25: =MAX(0,B24-$B$7) -> 181100 | F25: Lo que habrás juntado (ahorros + lo que sobra de la cuota tras el alquiler) | G25: =$B$7*(1+$B$18)^$B$15+(B30-$B$14)*12*IFERROR(((1+$B$18)^$B$15-1)/$B$18,$B$15) -> 63646.941
A26: Sale de tus ahorros | B26: =B24-B25 -> 55000 | F26: Hipoteca | G26: =MAX(0,G24-G25) -> 194077
A27: % financiado de lo que compras | B27: =IFERROR(B25/B21,0) -> 0.82318182 | F27: Sale de lo que has juntado | G27: =G24-G26 -> 63646.941
A28: % sobre el valor de la vivienda (lo que mira el banco) | B28: =IFERROR(B25/$B$5,0) -> 0.82318182 | F28: % sobre el valor de la vivienda | G28: =IFERROR(G26/G21,0) -> 0.80730884
A29: Plazo real (con tu edad) | B29: =MAX(1,MIN($B$12,$B$13-PARÁMETROS!$B$4)) -> 25 | F29: Plazo real (con tu edad entonces) | G29: =MAX(1,MIN($B$12,$B$13-PARÁMETROS!$B$4-$B$15)) -> 25
A30: Cuota mensual | B30: =IF(B25=0,0,PMT($B$11/12,B29*12,-B25)) -> 849.40697 | F30: Cuota mensual | G30: =IF(G26=0,0,PMT($B$11/12,G29*12,-G26)) -> 910.27252
A31: Intereses totales | B31: =B30*B29*12-B25 -> 73722.091 | F31: Te cuesta de más por esperar | G31: =G22-B21 -> 20399.94
A33: RESULTADO
A34: Años de comparación | B34: =$B$16 -> 20
A35: Patrimonio si compras ya (A) | B35: =INDEX($E$46:$E$76,MIN(30,$B$16)+1) -> 349955.87
A36: Patrimonio si esperas (B) | B36: =INDEX($H$46:$H$76,MIN(30,$B$16)+1) -> 300564.78
A37: Diferencia (A − B) | B37: =B35-B36 -> 49391.087
A38: =IF(B37>=0,"✅ Comprar ya sale mejor por "&TEXT(B37,"#,##0")&" € a "&B34&" años","⏳ Esperar sale mejor por "&TEXT(-B37,"#,##0")&" € a "&B34&" años") -> ✅ Comprar ya sale mejor por 49,391 € a 20 años
A39: =IF(OR($B$29<$B$12,$G$29<$B$12),"⚠️ Por tu edad el plazo se acorta (A: "&$B$29&" años, B: "&$G$29&" años) y la cuota sube","")
A40: · Mismo esfuerzo al mes en los dos: en B pagas el alquiler e inviertes lo que te sobra de la cuota de A.
A41: · Lo que decide casi siempre: revalorización de la vivienda e intereses de la hipoteca frente a lo que rinde el dinero invertido y lo que se va en alquiler.
A42: · Riesgos de esperar que no salen en la cuenta: que los precios o los tipos suban más de lo previsto.
A43: · No es asesoramiento fiscal ni financiero: confirma impuestos y gastos con una gestoría antes de firmar.
A44: EVOLUCIÓN AÑO A AÑO (patrimonio ligado a la vivienda: vivienda − deuda + lo invertido)
A45: Año | B45: Valor de la vivienda | C45: A · Deuda | D45: A · Invertido | E45: A · Patrimonio | F45: B · Deuda | G45: B · Invertido | H45: B · Patrimonio | I45: A − B
A46: 0 | B46: =$B$5*(1+$B$17)^A46 -> 220000 | C46: =IF(A46>=$B$29,0,MAX(0,FV($B$11/12,A46*12,$B$30,-$B$25))) -> 181100 | D46: =MAX(0,$B$7-$B$24) -> 0 | E46: =B46-C46+D46 -> 38900 | F46: =IF(A46<$B$15,0,IF(A46-$B$15>=$G$29,0,MAX(0,FV($B$11/12,(A46-$B$15)*12,$G$30,-$G$26)))) -> 0 | G46: =IF($B$15=0,MAX(0,$G$25-$G$24),$B$7) -> 55000 | H46: =IF(A46<$B$15,B46*$B$6+G46,B46-F46+G46) -> 55000 | I46: =E46-H46 -> -16100
A47: 1 | B47: =$B$5*(1+$B$17)^A47 -> 226600 | C47: =IF(A47>=$B$29,0,MAX(0,FV($B$11/12,A47*12,$B$30,-$B$25))) -> 176092.81 | D47: =D46*(1+$B$18)+IF(A47>$B$29,$B$30*12,0) -> 0 | E47: =B47-C47+D47 -> 50507.189 | F47: =IF(A47<$B$15,0,IF(A47-$B$15>=$G$29,0,MAX(0,FV($B$11/12,(A47-$B$15)*12,$G$30,-$G$26)))) -> 0 | G47: =IF(A47<$B$15,G46*(1+$B$18)+($B$30-$B$14)*12,IF(A47=$B$15,MAX(0,$G$25-$G$24),G46*(1+$B$18)+IF(A47-$B$15<=$G$29,($B$30-$G$30)*12,$B$30*12))) -> 57742.884 | H47: =IF(A47<$B$15,B47*$B$6+G47,B47-F47+G47) -> 57742.884 | I47: =E47-H47 -> -7235.6942
A48: 2 | B48: =$B$5*(1+$B$17)^A48 -> 233398 | C48: =IF(A48>=$B$29,0,MAX(0,FV($B$11/12,A48*12,$B$30,-$B$25))) -> 170938.47 | D48: =D47*(1+$B$18)+IF(A48>$B$29,$B$30*12,0) -> 0 | E48: =B48-C48+D48 -> 62459.533 | F48: =IF(A48<$B$15,0,IF(A48-$B$15>=$G$29,0,MAX(0,FV($B$11/12,(A48-$B$15)*12,$G$30,-$G$26)))) -> 0 | G48: =IF(A48<$B$15,G47*(1+$B$18)+($B$30-$B$14)*12,IF(A48=$B$15,MAX(0,$G$25-$G$24),G47*(1+$B$18)+IF(A48-$B$15<=$G$29,($B$30-$G$30)*12,$B$30*12))) -> 60622.911 | H48: =IF(A48<$B$15,B48*$B$6+G48,B48-F48+G48) -> 60622.911 | I48: =E48-H48 -> 1836.6217
A49: 3 | B49: =$B$5*(1+$B$17)^A49 -> 240399.94 | C49: =IF(A49>=$B$29,0,MAX(0,FV($B$11/12,A49*12,$B$30,-$B$25))) -> 165632.64 | D49: =D48*(1+$B$18)+IF(A49>$B$29,$B$30*12,0) -> 0 | E49: =B49-C49+D49 -> 74767.296 | F49: =IF(A49<$B$15,0,IF(A49-$B$15>=$G$29,0,MAX(0,FV($B$11/12,(A49-$B$15)*12,$G$30,-$G$26)))) -> 194077 | G49: =IF(A49<$B$15,G48*(1+$B$18)+($B$30-$B$14)*12,IF(A49=$B$15,MAX(0,$G$25-$G$24),G48*(1+$B$18)+IF(A49-$B$15<=$G$29,($B$30-$G$30)*12,$B$30*12))) -> 0 | H49: =IF(A49<$B$15,B49*$B$6+G49,B49-F49+G49) -> 46322.944 | I49: =E49-H49 -> 28444.351
A50: 4 | B50: =$B$5*(1+$B$17)^A50 -> 247611.94 | C50: =IF(A50>=$B$29,0,MAX(0,FV($B$11/12,A50*12,$B$30,-$B$25))) -> 160170.89 | D50: =D49*(1+$B$18)+IF(A50>$B$29,$B$30*12,0) -> 0 | E50: =B50-C50+D50 -> 87441.047 | F50: =IF(A50<$B$15,0,IF(A50-$B$15>=$G$29,0,MAX(0,FV($B$11/12,(A50-$B$15)*12,$G$30,-$G$26)))) -> 188711.01 | G50: =IF(A50<$B$15,G49*(1+$B$18)+($B$30-$B$14)*12,IF(A50=$B$15,MAX(0,$G$25-$G$24),G49*(1+$B$18)+IF(A50-$B$15<=$G$29,($B$30-$G$30)*12,$B$30*12))) -> -730.38657 | H50: =IF(A50<$B$15,B50*$B$6+G50,B50-F50+G50) -> 58170.543 | I50: =E50-H50 -> 29270.504
A51: 5 | B51: =$B$5*(1+$B$17)^A51 -> 255040.3 | C51: =IF(A51>=$B$29,0,MAX(0,FV($B$11/12,A51*12,$B$30,-$B$25))) -> 154548.63 | D51: =D50*(1+$B$18)+IF(A51>$B$29,$B$30*12,0) -> 0 | E51: =B51-C51+D51 -> 100491.67 | F51: =IF(A51<$B$15,0,IF(A51-$B$15>=$G$29,0,MAX(0,FV($B$11/12,(A51-$B$15)*12,$G$30,-$G$26)))) -> 183187.32 | G51: =IF(A51<$B$15,G50*(1+$B$18)+($B$30-$B$14)*12,IF(A51=$B$15,MAX(0,$G$25-$G$24),G50*(1+$B$18)+IF(A51-$B$15<=$G$29,($B$30-$G$30)*12,$B$30*12))) -> -1497.2925 | H51: =IF(A51<$B$15,B51*$B$6+G51,B51-F51+G51) -> 70355.681 | I51: =E51-H51 -> 30135.99
A52: 6 | B52: =$B$5*(1+$B$17)^A52 -> 262691.51 | C52: =IF(A52>=$B$29,0,MAX(0,FV($B$11/12,A52*12,$B$30,-$B$25))) -> 148761.13 | D52: =D51*(1+$B$18)+IF(A52>$B$29,$B$30*12,0) -> 0 | E52: =B52-C52+D52 -> 113930.38 | F52: =IF(A52<$B$15,0,IF(A52-$B$15>=$G$29,0,MAX(0,FV($B$11/12,(A52-$B$15)*12,$G$30,-$G$26)))) -> 177501.3 | G52: =IF(A52<$B$15,G51*(1+$B$18)+($B$30-$B$14)*12,IF(A52=$B$15,MAX(0,$G$25-$G$24),G51*(1+$B$18)+IF(A52-$B$15<=$G$29,($B$30-$G$30)*12,$B$30*12))) -> -2302.5437 | H52: =IF(A52<$B$15,B52*$B$6+G52,B52-F52+G52) -> 82887.658 | I52: =E52-H52 -> 31042.719
A53: 7 | B53: =$B$5*(1+$B$17)^A53 -> 270572.25 | C53: =IF(A53>=$B$29,0,MAX(0,FV($B$11/12,A53*12,$B$30,-$B$25))) -> 142803.55 | D53: =D52*(1+$B$18)+IF(A53>$B$29,$B$30*12,0) -> 0 | E53: =B53-C53+D53 -> 127768.7 | F53: =IF(A53<$B$15,0,IF(A53-$B$15>=$G$29,0,MAX(0,FV($B$11/12,(A53-$B$15)*12,$G$30,-$G$26)))) -> 171648.18 | G53: =IF(A53<$B$15,G52*(1+$B$18)+($B$30-$B$14)*12,IF(A53=$B$15,MAX(0,$G$25-$G$24),G52*(1+$B$18)+IF(A53-$B$15<=$G$29,($B$30-$G$30)*12,$B$30*12))) -> -3148.0574 | H53: =IF(A53<$B$15,B53*$B$6+G53,B53-F53+G53) -> 95776.013 | I53: =E53-H53 -> 31992.692
A54: 8 | B54: =$B$5*(1+$B$17)^A54 -> 278689.42 | C54: =IF(A54>=$B$29,0,MAX(0,FV($B$11/12,A54*12,$B$30,-$B$25))) -> 136670.88 | D54: =D53*(1+$B$18)+IF(A54>$B$29,$B$30*12,0) -> 0 | E54: =B54-C54+D54 -> 142018.54 | F54: =IF(A54<$B$15,0,IF(A54-$B$15>=$G$29,0,MAX(0,FV($B$11/12,(A54-$B$15)*12,$G$30,-$G$26)))) -> 165623.04 | G54: =IF(A54<$B$15,G53*(1+$B$18)+($B$30-$B$14)*12,IF(A54=$B$15,MAX(0,$G$25-$G$24),G53*(1+$B$18)+IF(A54-$B$15<=$G$29,($B$30-$G$30)*12,$B$30*12))) -> -4035.8469 | H54: =IF(A54<$B$15,B54*$B$6+G54,B54-F54+G54) -> 109030.53 | I54: =E54-H54 -> 32988.011
A55: 9 | B55: =$B$5*(1+$B$17)^A55 -> 287050.1 | C55: =IF(A55>=$B$29,0,MAX(0,FV($B$11/12,A55*12,$B$30,-$B$25))) -> 130357.98 | D55: =D54*(1+$B$18)+IF(A55>$B$29,$B$30*12,0) -> 0 | E55: =B55-C55+D55 -> 156692.12 | F55: =IF(A55<$B$15,0,IF(A55-$B$15>=$G$29,0,MAX(0,FV($B$11/12,(A55-$B$15)*12,$G$30,-$G$26)))) -> 159420.83 | G55: =IF(A55<$B$15,G54*(1+$B$18)+($B$30-$B$14)*12,IF(A55=$B$15,MAX(0,$G$25-$G$24),G54*(1+$B$18)+IF(A55-$B$15<=$G$29,($B$30-$G$30)*12,$B$30*12))) -> -4968.0258 | H55: =IF(A55<$B$15,B55*$B$6+G55,B55-F55+G55) -> 122661.24 | I55: =E55-H55 -> 34030.88
A56: 10 | B56: =$B$5*(1+$B$17)^A56 -> 295661.6 | C56: =IF(A56>=$B$29,0,MAX(0,FV($B$11/12,A56*12,$B$30,-$B$25))) -> 123859.55 | D56: =D55*(1+$B$18)+IF(A56>$B$29,$B$30*12,0) -> 0 | E56: =B56-C56+D56 -> 171802.05 | F56: =IF(A56<$B$15,0,IF(A56-$B$15>=$G$29,0,MAX(0,FV($B$11/12,(A56-$B$15)*12,$G$30,-$G$26)))) -> 153036.35 | G56: =IF(A56<$B$15,G55*(1+$B$18)+($B$30-$B$14)*12,IF(A56=$B$15,MAX(0,$G$25-$G$24),G55*(1+$B$18)+IF(A56-$B$15<=$G$29,($B$30-$G$30)*12,$B$30*12))) -> -5946.8136 | H56: =IF(A56<$B$15,B56*$B$6+G56,B56-F56+G56) -> 136678.44 | I56: =E56-H56 -> 35123.61
A57: 11 | B57: =$B$5*(1+$B$17)^A57 -> 304531.45 | C57: =IF(A57>=$B$29,0,MAX(0,FV($B$11/12,A57*12,$B$30,-$B$25))) -> 117170.15 | D57: =D56*(1+$B$18)+IF(A57>$B$29,$B$30*12,0) -> 0 | E57: =B57-C57+D57 -> 187361.3 | F57: =IF(A57<$B$15,0,IF(A57-$B$15>=$G$29,0,MAX(0,FV($B$11/12,(A57-$B$15)*12,$G$30,-$G$26)))) -> 146464.24 | G57: =IF(A57<$B$15,G56*(1+$B$18)+($B$30-$B$14)*12,IF(A57=$B$15,MAX(0,$G$25-$G$24),G56*(1+$B$18)+IF(A57-$B$15<=$G$29,($B$30-$G$30)*12,$B$30*12))) -> -6974.5409 | H57: =IF(A57<$B$15,B57*$B$6+G57,B57-F57+G57) -> 151092.67 | I57: =E57-H57 -> 36268.629
A58: 12 | B58: =$B$5*(1+$B$17)^A58 -> 313667.4 | C58: =IF(A58>=$B$29,0,MAX(0,FV($B$11/12,A58*12,$B$30,-$B$25))) -> 110284.15 | D58: =D57*(1+$B$18)+IF(A58>$B$29,$B$30*12,0) -> 0 | E58: =B58-C58+D58 -> 203383.24 | F58: =IF(A58<$B$15,0,IF(A58-$B$15>=$G$29,0,MAX(0,FV($B$11/12,(A58-$B$15)*12,$G$30,-$G$26)))) -> 139698.98 | G58: =IF(A58<$B$15,G57*(1+$B$18)+($B$30-$B$14)*12,IF(A58=$B$15,MAX(0,$G$25-$G$24),G57*(1+$B$18)+IF(A58-$B$15<=$G$29,($B$30-$G$30)*12,$B$30*12))) -> -8053.6545 | H58: =IF(A58<$B$15,B58*$B$6+G58,B58-F58+G58) -> 165914.76 | I58: =E58-H58 -> 37468.481
... A76: 30 | B76: =$B$5*(1+$B$17)^A76 -> 533997.74 | C76: =IF(A76>=$B$29,0,MAX(0,FV($B$11/12,A76*12,$B$30,-$B$25))) -> 0 | D76: =D75*(1+$B$18)+IF(A76>$B$29,$B$30*12,0) -> 56322.116 | E76: =B76-C76+D76 -> 590319.86 | F76: =IF(A76<$B$15,0,IF(A76-$B$15>=$G$29,0,MAX(0,FV($B$11/12,(A76-$B$15)*12,$G$30,-$G$26)))) -> 0 | G76: =IF(A76<$B$15,G75*(1+$B$18)+($B$30-$B$14)*12,IF(A76=$B$15,MAX(0,$G$25-$G$24),G75*(1+$B$18)+IF(A76-$B$15<=$G$29,($B$30-$G$30)*12,$B$30*12))) -> -17536.892 | H76: =IF(A76<$B$15,B76*$B$6+G76,B76-F76+G76) -> 516460.85 | I76: =E76-H76 -> 73859.008

Sheet INMUEBLES
A1: INMUEBLES
A2: Lo que tienes en ladrillo. Suma a tu patrimonio; a la libertad financiera solo si da renta. Valores estimados: cámbialos.
A4: Inmueble | B4: Valor estimado (100 %) | C4: Tu % | D4: Tu parte | E4: Renta anual | F4: Gastos anuales | G4: Revalorización anual | H4: Nota
A5: Vivienda (la de VIVIENDA) | B5: =VIVIENDA!$B$5 -> 220000 | C5: =VIVIENDA!$B$6 -> 0 | D5: =IF(B5="",0,B5*C5) -> 0 | E5: 0 | F5: 0 | G5: =PARÁMETROS!$B$19 -> 0.03 | H5: Valor y % vienen de VIVIENDA: 0 % mientras no la compres
D6: =IF(B6="",0,B6*C6) -> 0
D7: =IF(B7="",0,B7*C7) -> 0
D8: =IF(B8="",0,B8*C8) -> 0
D9: =IF(B9="",0,B9*C9) -> 0
A10: Total | D10: =SUM(D5:D9) -> 0 | E10: =SUM(E5:E9) -> 0 | F10: =SUM(F5:F9) -> 0
A11: Renta neta anual | D11: =E10-F10 -> 0
A13: · La renta neta, si algún día la hay, se suma a la pensión en la fase de jubilación.
A14: · Cada inmueble lleva su revalorización: un local o un garaje no se mueven como la vivienda.

Sheet VIAJES
A1: VIAJES · tu cuenta de viajes
A2: Aportas cada mes a una cuenta de viajes y de ahí pagas tu parte. Cada viaje te dice cuánto queda en la cuenta y si llega.
A3: TU CUENTA DE VIAJES | E3: ¿Y SI APORTO OTRA CANTIDAD?
A4: Aportación mensual | B4: 150 | C4: € al mes | H4: Lo de ahora | I4: Opción A | J4: Opción B | K4: Opción C
A5: Primera aportación (mes) | B5: 45931 | E5: Aportación mensual | H5: =$B$4 -> 150 | I5: 100 | J5: 200 | K5: 250
A6: Saldo que ya había en la cuenta | B6: 0 | E6: Saldo de la cuenta a fin de 2026 | H6: =$B$6+H$5*MAX(0,(YEAR(DATE(2026,12,1))-YEAR($B$5))*12+MONTH(DATE(2026,12,1))-MONTH($B$5)+1)-SUMIFS($I$16:$I$65,$F$16:$F$65,"Cuenta de viajes",$B$16:$B$65,"<="&DATE(2026,12,31)) -> 1900 | I6: =$B$6+I$5*MAX(0,(YEAR(DATE(2026,12,1))-YEAR($B$5))*12+MONTH(DATE(2026,12,1))-MONTH($B$5)+1)-SUMIFS($I$16:$I$65,$F$16:$F$65,"Cuenta de viajes",$B$16:$B$65,"<="&DATE(2026,12,31)) -> 1150 | J6: =$B$6+J$5*MAX(0,(YEAR(DATE(2026,12,1))-YEAR($B$5))*12+MONTH(DATE(2026,12,1))-MONTH($B$5)+1)-SUMIFS($I$16:$I$65,$F$16:$F$65,"Cuenta de viajes",$B$16:$B$65,"<="&DATE(2026,12,31)) -> 2650 | K6: =$B$6+K$5*MAX(0,(YEAR(DATE(2026,12,1))-YEAR($B$5))*12+MONTH(DATE(2026,12,1))-MONTH($B$5)+1)-SUMIFS($I$16:$I$65,$F$16:$F$65,"Cuenta de viajes",$B$16:$B$65,"<="&DATE(2026,12,31)) -> 3400
A7: Año que miras | B7: 2026 | E7: Saldo de la cuenta a fin de 2027 | H7: =$B$6+H$5*MAX(0,(YEAR(DATE(2027,12,1))-YEAR($B$5))*12+MONTH(DATE(2027,12,1))-MONTH($B$5)+1)-SUMIFS($I$16:$I$65,$F$16:$F$65,"Cuenta de viajes",$B$16:$B$65,"<="&DATE(2027,12,31)) -> 2900 | I7: =$B$6+I$5*MAX(0,(YEAR(DATE(2027,12,1))-YEAR($B$5))*12+MONTH(DATE(2027,12,1))-MONTH($B$5)+1)-SUMIFS($I$16:$I$65,$F$16:$F$65,"Cuenta de viajes",$B$16:$B$65,"<="&DATE(2027,12,31)) -> 1550 | J7: =$B$6+J$5*MAX(0,(YEAR(DATE(2027,12,1))-YEAR($B$5))*12+MONTH(DATE(2027,12,1))-MONTH($B$5)+1)-SUMIFS($I$16:$I$65,$F$16:$F$65,"Cuenta de viajes",$B$16:$B$65,"<="&DATE(2027,12,31)) -> 4250 | K7: =$B$6+K$5*MAX(0,(YEAR(DATE(2027,12,1))-YEAR($B$5))*12+MONTH(DATE(2027,12,1))-MONTH($B$5)+1)-SUMIFS($I$16:$I$65,$F$16:$F$65,"Cuenta de viajes",$B$16:$B$65,"<="&DATE(2027,12,31)) -> 5600
A8: Aportado ese año | B8: =$B$4*(MAX(0,(YEAR(DATE($B$7,12,1))-YEAR($B$5))*12+MONTH(DATE($B$7,12,1))-MONTH($B$5)+1)-MAX(0,(YEAR(DATE($B$7-1,12,1))-YEAR($B$5))*12+MONTH(DATE($B$7-1,12,1))-MONTH($B$5)+1)) -> 1800 | E8: Saldo más bajo justo después de un viaje | H8: =IF(COUNT(P16:P65)=0,"",MIN(P16:P65)) -> 1700 | I8: =IF(COUNT(Q16:Q65)=0,"",MIN(Q16:Q65)) -> 750 | J8: =IF(COUNT(R16:R65)=0,"",MIN(R16:R65)) -> 2450 | K8: =IF(COUNT(S16:S65)=0,"",MIN(S16:S65)) -> 3150
A9: Pagado de la cuenta ese año (tu parte) | B9: =SUMIFS($I$16:$I$65,$F$16:$F$65,"Cuenta de viajes",$B$16:$B$65,">="&DATE($B$7,1,1),$B$16:$B$65,"<="&DATE($B$7,12,31)) -> 350 | E9: ¿Llegas a todos los viajes? | H9: =IF(H8="","Sin viajes de la cuenta",IF(H8<0,"🔴 No","🟢 Sí")) -> 🟢 Sí | I9: =IF(I8="","Sin viajes de la cuenta",IF(I8<0,"🔴 No","🟢 Sí")) -> 🟢 Sí | J9: =IF(J8="","Sin viajes de la cuenta",IF(J8<0,"🔴 No","🟢 Sí")) -> 🟢 Sí | K9: =IF(K8="","Sin viajes de la cuenta",IF(K8<0,"🔴 No","🟢 Sí")) -> 🟢 Sí
A10: Saldo a final de año | B10: =$B$6+$B$4*MAX(0,(YEAR(DATE($B$7,12,1))-YEAR($B$5))*12+MONTH(DATE($B$7,12,1))-MONTH($B$5)+1)-SUMIFS($I$16:$I$65,$F$16:$F$65,"Cuenta de viajes",$B$16:$B$65,"<="&DATE($B$7,12,31)) -> 1900 | E10: Ahorro que te queda al mes | H10: =PARÁMETROS!$B$13+IFERROR(SUMIFS(MOVIMIENTOS!$E$4:$E$20000,MOVIMIENTOS!$G$4:$G$20000,"Aportación a la cuenta de viajes",MOVIMIENTOS!$B$4:$B$20000,">="&'MIS DATOS'!$A$6,MOVIMIENTOS!$B$4:$B$20000,"<"&DATE(YEAR(TODAY()),MONTH(TODAY()),1))/-COUNTIFS('MIS DATOS'!$N$6:$N$245,1),0)-H$5 -> 976.86 | I10: =PARÁMETROS!$B$13+IFERROR(SUMIFS(MOVIMIENTOS!$E$4:$E$20000,MOVIMIENTOS!$G$4:$G$20000,"Aportación a la cuenta de viajes",MOVIMIENTOS!$B$4:$B$20000,">="&'MIS DATOS'!$A$6,MOVIMIENTOS!$B$4:$B$20000,"<"&DATE(YEAR(TODAY()),MONTH(TODAY()),1))/-COUNTIFS('MIS DATOS'!$N$6:$N$245,1),0)-I$5 -> 1026.86 | J10: =PARÁMETROS!$B$13+IFERROR(SUMIFS(MOVIMIENTOS!$E$4:$E$20000,MOVIMIENTOS!$G$4:$G$20000,"Aportación a la cuenta de viajes",MOVIMIENTOS!$B$4:$B$20000,">="&'MIS DATOS'!$A$6,MOVIMIENTOS!$B$4:$B$20000,"<"&DATE(YEAR(TODAY()),MONTH(TODAY()),1))/-COUNTIFS('MIS DATOS'!$N$6:$N$245,1),0)-J$5 -> 926.86 | K10: =PARÁMETROS!$B$13+IFERROR(SUMIFS(MOVIMIENTOS!$E$4:$E$20000,MOVIMIENTOS!$G$4:$G$20000,"Aportación a la cuenta de viajes",MOVIMIENTOS!$B$4:$B$20000,">="&'MIS DATOS'!$A$6,MOVIMIENTOS!$B$4:$B$20000,"<"&DATE(YEAR(TODAY()),MONTH(TODAY()),1))/-COUNTIFS('MIS DATOS'!$N$6:$N$245,1),0)-K$5 -> 876.86
A11: Viajes de ese año | B11: =COUNTIFS($B$16:$B$65,">="&DATE($B$7,1,1),$B$16:$B$65,"<="&DATE($B$7,12,31)) -> 2 | E11: % de tus ingresos que ahorras | H11: =IFERROR(H10/IFERROR(AVERAGEIFS('MIS DATOS'!$G$6:$G$245,'MIS DATOS'!$N$6:$N$245,1),0),"") -> 0.37179592 | I11: =IFERROR(I10/IFERROR(AVERAGEIFS('MIS DATOS'!$G$6:$G$245,'MIS DATOS'!$N$6:$N$245,1),0),"") -> 0.39082607 | J11: =IFERROR(J10/IFERROR(AVERAGEIFS('MIS DATOS'!$G$6:$G$245,'MIS DATOS'!$N$6:$N$245,1),0),"") -> 0.35276576 | K11: =IFERROR(K10/IFERROR(AVERAGEIFS('MIS DATOS'!$G$6:$G$245,'MIS DATOS'!$N$6:$N$245,1),0),"") -> 0.33373561
A12: Aviso | B12: =IFERROR(IF(MIN($J$16:$J$65)<0,"⚠️ No llega para "&INDEX($A$16:$A$65,MATCH(MIN($J$16:$J$65),$J$16:$J$65,0))&": faltan "&TEXT(-MIN($J$16:$J$65),"#,##0")&" €","✅ Llega para todos los viajes apuntados"),"") -> ✅ Llega para todos los viajes apuntados | E12: Patrimonio líquido a los 67 | H12: =INDEX(PROYECCIÓN!$G$15:$G$45,PROYECCIÓN!$B$11+1)+(IFERROR(SUMIFS(MOVIMIENTOS!$E$4:$E$20000,MOVIMIENTOS!$G$4:$G$20000,"Aportación a la cuenta de viajes",MOVIMIENTOS!$B$4:$B$20000,">="&'MIS DATOS'!$A$6,MOVIMIENTOS!$B$4:$B$20000,"<"&DATE(YEAR(TODAY()),MONTH(TODAY()),1))/-COUNTIFS('MIS DATOS'!$N$6:$N$245,1),0)-H$5)*12*IFERROR(((1+PARÁMETROS!$B$9)^PROYECCIÓN!$B$11-1)/PARÁMETROS!$B$9,PROYECCIÓN!$B$11) -> 502169.25 | I12: =INDEX(PROYECCIÓN!$G$15:$G$45,PROYECCIÓN!$B$11+1)+(IFERROR(SUMIFS(MOVIMIENTOS!$E$4:$E$20000,MOVIMIENTOS!$G$4:$G$20000,"Aportación a la cuenta de viajes",MOVIMIENTOS!$B$4:$B$20000,">="&'MIS DATOS'!$A$6,MOVIMIENTOS!$B$4:$B$20000,"<"&DATE(YEAR(TODAY()),MONTH(TODAY()),1))/-COUNTIFS('MIS DATOS'!$N$6:$N$245,1),0)-I$5)*12*IFERROR(((1+PARÁMETROS!$B$9)^PROYECCIÓN!$B$11-1)/PARÁMETROS!$B$9,PROYECCIÓN!$B$11) -> 518991.89 | J12: =INDEX(PROYECCIÓN!$G$15:$G$45,PROYECCIÓN!$B$11+1)+(IFERROR(SUMIFS(MOVIMIENTOS!$E$4:$E$20000,MOVIMIENTOS!$G$4:$G$20000,"Aportación a la cuenta de viajes",MOVIMIENTOS!$B$4:$B$20000,">="&'MIS DATOS'!$A$6,MOVIMIENTOS!$B$4:$B$20000,"<"&DATE(YEAR(TODAY()),MONTH(TODAY()),1))/-COUNTIFS('MIS DATOS'!$N$6:$N$245,1),0)-J$5)*12*IFERROR(((1+PARÁMETROS!$B$9)^PROYECCIÓN!$B$11-1)/PARÁMETROS!$B$9,PROYECCIÓN!$B$11) -> 485346.6 | K12: =INDEX(PROYECCIÓN!$G$15:$G$45,PROYECCIÓN!$B$11+1)+(IFERROR(SUMIFS(MOVIMIENTOS!$E$4:$E$20000,MOVIMIENTOS!$G$4:$G$20000,"Aportación a la cuenta de viajes",MOVIMIENTOS!$B$4:$B$20000,">="&'MIS DATOS'!$A$6,MOVIMIENTOS!$B$4:$B$20000,"<"&DATE(YEAR(TODAY()),MONTH(TODAY()),1))/-COUNTIFS('MIS DATOS'!$N$6:$N$245,1),0)-K$5)*12*IFERROR(((1+PARÁMETROS!$B$9)^PROYECCIÓN!$B$11-1)/PARÁMETROS!$B$9,PROYECCIÓN!$B$11) -> 468523.95
E13: Libertad financiera a los 67 | H13: =IFERROR(H12*PARÁMETROS!$B$16/((PARÁMETROS!$B$15+H$5-IFERROR(SUMIFS(MOVIMIENTOS!$E$4:$E$20000,MOVIMIENTOS!$G$4:$G$20000,"Aportación a la cuenta de viajes",MOVIMIENTOS!$B$4:$B$20000,">="&'MIS DATOS'!$A$6,MOVIMIENTOS!$B$4:$B$20000,"<"&DATE(YEAR(TODAY()),MONTH(TODAY()),1))/-COUNTIFS('MIS DATOS'!$N$6:$N$245,1),0))*12*(1+PARÁMETROS!$B$10)^PROYECCIÓN!$B$11),"") -> 0.53367873 | I13: =IFERROR(I12*PARÁMETROS!$B$16/((PARÁMETROS!$B$15+I$5-IFERROR(SUMIFS(MOVIMIENTOS!$E$4:$E$20000,MOVIMIENTOS!$G$4:$G$20000,"Aportación a la cuenta de viajes",MOVIMIENTOS!$B$4:$B$20000,">="&'MIS DATOS'!$A$6,MOVIMIENTOS!$B$4:$B$20000,"<"&DATE(YEAR(TODAY()),MONTH(TODAY()),1))/-COUNTIFS('MIS DATOS'!$N$6:$N$245,1),0))*12*(1+PARÁMETROS!$B$10)^PROYECCIÓN!$B$11),"") -> 0.56878718 | J13: =IFERROR(J12*PARÁMETROS!$B$16/((PARÁMETROS!$B$15+J$5-IFERROR(SUMIFS(MOVIMIENTOS!$E$4:$E$20000,MOVIMIENTOS!$G$4:$G$20000,"Aportación a la cuenta de viajes",MOVIMIENTOS!$B$4:$B$20000,">="&'MIS DATOS'!$A$6,MOVIMIENTOS!$B$4:$B$20000,"<"&DATE(YEAR(TODAY()),MONTH(TODAY()),1))/-COUNTIFS('MIS DATOS'!$N$6:$N$245,1),0))*12*(1+PARÁMETROS!$B$10)^PROYECCIÓN!$B$11),"") -> 0.50063481 | K13: =IFERROR(K12*PARÁMETROS!$B$16/((PARÁMETROS!$B$15+K$5-IFERROR(SUMIFS(MOVIMIENTOS!$E$4:$E$20000,MOVIMIENTOS!$G$4:$G$20000,"Aportación a la cuenta de viajes",MOVIMIENTOS!$B$4:$B$20000,">="&'MIS DATOS'!$A$6,MOVIMIENTOS!$B$4:$B$20000,"<"&DATE(YEAR(TODAY()),MONTH(TODAY()),1))/-COUNTIFS('MIS DATOS'!$N$6:$N$245,1),0))*12*(1+PARÁMETROS!$B$10)^PROYECCIÓN!$B$11),"") -> 0.46947853
E14: Ahorro sobre tu media real: suma lo que ya aportas a la cuenta de viajes y resta la opción. Patrimonio y libertad a los 67 suponen aportar esa cantidad cada año.
A15: Viaje | B15: Fecha | C15: Coste total | D15: Personas | E15: Tu parte | F15: Se paga con | G15: Estado | H15: Coste real (tu parte) | I15: Cuenta | J15: Saldo de la cuenta tras el viaje | K15: ¿Llega? | L15: Nota | M15: meses aportados | N15: pagado de la cuenta hasta aquí | P15: saldo · ahora | Q15: saldo · A | R15: saldo · B | S15: saldo · C
A16: Escapada a Oporto | B16: 46346 | C16: 700 | D16: 2 | E16: =IF(OR(A16="",C16=""),"",C16/MAX(1,N(D16))) -> 350 | F16: Cuenta de viajes | G16: Organizado | I16: =IF(A16="","",IF(H16<>"",H16,E16)) -> 350 | J16: =IF(N16="","",$B$6+$B$4*M16-N16) -> 1750 | K16: =IF(A16="","",IF(F16<>"Cuenta de viajes","— lo pagas tú",IF(OR(B16="",E16=""),"Falta fecha o coste",IF(J16<0,"🔴 Faltan "&TEXT(-J16,"#,##0")&" €",IF(J16<$B$4,"🟡 Justo","🟢 Llega"))))) -> 🟢 Llega | L16: Vuelos y hotel ya pagados | M16: =IF(OR(A16="",B16=""),"",MAX(0,(YEAR(B16)-YEAR($B$5))*12+MONTH(B16)-MONTH($B$5)+1)) -> 14 | N16: =IF(OR(A16="",B16="",F16<>"Cuenta de viajes"),"",SUMIFS($I$16:$I$65,$F$16:$F$65,"Cuenta de viajes",$B$16:$B$65,"<="&B16)) -> 350 | P16: =IF(N16="","",$B$6+H$5*M16-N16) -> 1750 | Q16: =IF(N16="","",$B$6+I$5*M16-N16) -> 1050 | R16: =IF(N16="","",$B$6+J$5*M16-N16) -> 2450 | S16: =IF(N16="","",$B$6+K$5*M16-N16) -> 3150
A17: Fin de semana rural | B17: 46361 | C17: 320 | D17: 2 | E17: =IF(OR(A17="",C17=""),"",C17/MAX(1,N(D17))) -> 160 | F17: Mi bolsillo | G17: Idea | I17: =IF(A17="","",IF(H17<>"",H17,E17)) -> 160 | J17: =IF(N17="","",$B$6+$B$4*M17-N17) | K17: =IF(A17="","",IF(F17<>"Cuenta de viajes","— lo pagas tú",IF(OR(B17="",E17=""),"Falta fecha o coste",IF(J17<0,"🔴 Faltan "&TEXT(-J17,"#,##0")&" €",IF(J17<$B$4,"🟡 Justo","🟢 Llega"))))) -> — lo pagas tú | L17: Si sale, lo pago aparte | M17: =IF(OR(A17="",B17=""),"",MAX(0,(YEAR(B17)-YEAR($B$5))*12+MONTH(B17)-MONTH($B$5)+1)) -> 15 | N17: =IF(OR(A17="",B17="",F17<>"Cuenta de viajes"),"",SUMIFS($I$16:$I$65,$F$16:$F$65,"Cuenta de viajes",$B$16:$B$65,"<="&B17)) | P17: =IF(N17="","",$B$6+H$5*M17-N17) | Q17: =IF(N17="","",$B$6+I$5*M17-N17) | R17: =IF(N17="","",$B$6+J$5*M17-N17) | S17: =IF(N17="","",$B$6+K$5*M17-N17)
A18: Roma | B18: 46487 | C18: 1600 | D18: 2 | E18: =IF(OR(A18="",C18=""),"",C18/MAX(1,N(D18))) -> 800 | F18: Cuenta de viajes | G18: Planificando | I18: =IF(A18="","",IF(H18<>"",H18,E18)) -> 800 | J18: =IF(N18="","",$B$6+$B$4*M18-N18) -> 1700 | K18: =IF(A18="","",IF(F18<>"Cuenta de viajes","— lo pagas tú",IF(OR(B18="",E18=""),"Falta fecha o coste",IF(J18<0,"🔴 Faltan "&TEXT(-J18,"#,##0")&" €",IF(J18<$B$4,"🟡 Justo","🟢 Llega"))))) -> 🟢 Llega | L18: Fecha aproximada | M18: =IF(OR(A18="",B18=""),"",MAX(0,(YEAR(B18)-YEAR($B$5))*12+MONTH(B18)-MONTH($B$5)+1)) -> 19 | N18: =IF(OR(A18="",B18="",F18<>"Cuenta de viajes"),"",SUMIFS($I$16:$I$65,$F$16:$F$65,"Cuenta de viajes",$B$16:$B$65,"<="&B18)) -> 1150 | P18: =IF(N18="","",$B$6+H$5*M18-N18) -> 1700 | Q18: =IF(N18="","",$B$6+I$5*M18-N18) -> 750 | R18: =IF(N18="","",$B$6+J$5*M18-N18) -> 2650 | S18: =IF(N18="","",$B$6+K$5*M18-N18) -> 3600
A19: Islandia | B19: 46645 | D19: 2 | E19: =IF(OR(A19="",C19=""),"",C19/MAX(1,N(D19))) | F19: Cuenta de viajes | G19: Idea | I19: =IF(A19="","",IF(H19<>"",H19,E19)) | J19: =IF(N19="","",$B$6+$B$4*M19-N19) -> 2450 | K19: =IF(A19="","",IF(F19<>"Cuenta de viajes","— lo pagas tú",IF(OR(B19="",E19=""),"Falta fecha o coste",IF(J19<0,"🔴 Faltan "&TEXT(-J19,"#,##0")&" €",IF(J19<$B$4,"🟡 Justo","🟢 Llega"))))) -> Falta fecha o coste | L19: Sin fecha ni coste todavía | M19: =IF(OR(A19="",B19=""),"",MAX(0,(YEAR(B19)-YEAR($B$5))*12+MONTH(B19)-MONTH($B$5)+1)) -> 24 | N19: =IF(OR(A19="",B19="",F19<>"Cuenta de viajes"),"",SUMIFS($I$16:$I$65,$F$16:$F$65,"Cuenta de viajes",$B$16:$B$65,"<="&B19)) -> 1150 | P19: =IF(N19="","",$B$6+H$5*M19-N19) -> 2450 | Q19: =IF(N19="","",$B$6+I$5*M19-N19) -> 1250 | R19: =IF(N19="","",$B$6+J$5*M19-N19) -> 3650 | S19: =IF(N19="","",$B$6+K$5*M19-N19) -> 4850
E20: =IF(OR(A20="",C20=""),"",C20/MAX(1,N(D20))) | I20: =IF(A20="","",IF(H20<>"",H20,E20)) | J20: =IF(N20="","",$B$6+$B$4*M20-N20) | K20: =IF(A20="","",IF(F20<>"Cuenta de viajes","— lo pagas tú",IF(OR(B20="",E20=""),"Falta fecha o coste",IF(J20<0,"🔴 Faltan "&TEXT(-J20,"#,##0")&" €",IF(J20<$B$4,"🟡 Justo","🟢 Llega"))))) | M20: =IF(OR(A20="",B20=""),"",MAX(0,(YEAR(B20)-YEAR($B$5))*12+MONTH(B20)-MONTH($B$5)+1)) | N20: =IF(OR(A20="",B20="",F20<>"Cuenta de viajes"),"",SUMIFS($I$16:$I$65,$F$16:$F$65,"Cuenta de viajes",$B$16:$B$65,"<="&B20)) | P20: =IF(N20="","",$B$6+H$5*M20-N20) | Q20: =IF(N20="","",$B$6+I$5*M20-N20) | R20: =IF(N20="","",$B$6+J$5*M20-N20) | S20: =IF(N20="","",$B$6+K$5*M20-N20)
E21: =IF(OR(A21="",C21=""),"",C21/MAX(1,N(D21))) | I21: =IF(A21="","",IF(H21<>"",H21,E21)) | J21: =IF(N21="","",$B$6+$B$4*M21-N21) | K21: =IF(A21="","",IF(F21<>"Cuenta de viajes","— lo pagas tú",IF(OR(B21="",E21=""),"Falta fecha o coste",IF(J21<0,"🔴 Faltan "&TEXT(-J21,"#,##0")&" €",IF(J21<$B$4,"🟡 Justo","🟢 Llega"))))) | M21: =IF(OR(A21="",B21=""),"",MAX(0,(YEAR(B21)-YEAR($B$5))*12+MONTH(B21)-MONTH($B$5)+1)) | N21: =IF(OR(A21="",B21="",F21<>"Cuenta de viajes"),"",SUMIFS($I$16:$I$65,$F$16:$F$65,"Cuenta de viajes",$B$16:$B$65,"<="&B21)) | P21: =IF(N21="","",$B$6+H$5*M21-N21) | Q21: =IF(N21="","",$B$6+I$5*M21-N21) | R21: =IF(N21="","",$B$6+J$5*M21-N21) | S21: =IF(N21="","",$B$6+K$5*M21-N21)
E22: =IF(OR(A22="",C22=""),"",C22/MAX(1,N(D22))) | I22: =IF(A22="","",IF(H22<>"",H22,E22)) | J22: =IF(N22="","",$B$6+$B$4*M22-N22) | K22: =IF(A22="","",IF(F22<>"Cuenta de viajes","— lo pagas tú",IF(OR(B22="",E22=""),"Falta fecha o coste",IF(J22<0,"🔴 Faltan "&TEXT(-J22,"#,##0")&" €",IF(J22<$B$4,"🟡 Justo","🟢 Llega"))))) | M22: =IF(OR(A22="",B22=""),"",MAX(0,(YEAR(B22)-YEAR($B$5))*12+MONTH(B22)-MONTH($B$5)+1)) | N22: =IF(OR(A22="",B22="",F22<>"Cuenta de viajes"),"",SUMIFS($I$16:$I$65,$F$16:$F$65,"Cuenta de viajes",$B$16:$B$65,"<="&B22)) | P22: =IF(N22="","",$B$6+H$5*M22-N22) | Q22: =IF(N22="","",$B$6+I$5*M22-N22) | R22: =IF(N22="","",$B$6+J$5*M22-N22) | S22: =IF(N22="","",$B$6+K$5*M22-N22)
E23: =IF(OR(A23="",C23=""),"",C23/MAX(1,N(D23))) | I23: =IF(A23="","",IF(H23<>"",H23,E23)) | J23: =IF(N23="","",$B$6+$B$4*M23-N23) | K23: =IF(A23="","",IF(F23<>"Cuenta de viajes","— lo pagas tú",IF(OR(B23="",E23=""),"Falta fecha o coste",IF(J23<0,"🔴 Faltan "&TEXT(-J23,"#,##0")&" €",IF(J23<$B$4,"🟡 Justo","🟢 Llega"))))) | M23: =IF(OR(A23="",B23=""),"",MAX(0,(YEAR(B23)-YEAR($B$5))*12+MONTH(B23)-MONTH($B$5)+1)) | N23: =IF(OR(A23="",B23="",F23<>"Cuenta de viajes"),"",SUMIFS($I$16:$I$65,$F$16:$F$65,"Cuenta de viajes",$B$16:$B$65,"<="&B23)) | P23: =IF(N23="","",$B$6+H$5*M23-N23) | Q23: =IF(N23="","",$B$6+I$5*M23-N23) | R23: =IF(N23="","",$B$6+J$5*M23-N23) | S23: =IF(N23="","",$B$6+K$5*M23-N23)
E24: =IF(OR(A24="",C24=""),"",C24/MAX(1,N(D24))) | I24: =IF(A24="","",IF(H24<>"",H24,E24)) | J24: =IF(N24="","",$B$6+$B$4*M24-N24) | K24: =IF(A24="","",IF(F24<>"Cuenta de viajes","— lo pagas tú",IF(OR(B24="",E24=""),"Falta fecha o coste",IF(J24<0,"🔴 Faltan "&TEXT(-J24,"#,##0")&" €",IF(J24<$B$4,"🟡 Justo","🟢 Llega"))))) | M24: =IF(OR(A24="",B24=""),"",MAX(0,(YEAR(B24)-YEAR($B$5))*12+MONTH(B24)-MONTH($B$5)+1)) | N24: =IF(OR(A24="",B24="",F24<>"Cuenta de viajes"),"",SUMIFS($I$16:$I$65,$F$16:$F$65,"Cuenta de viajes",$B$16:$B$65,"<="&B24)) | P24: =IF(N24="","",$B$6+H$5*M24-N24) | Q24: =IF(N24="","",$B$6+I$5*M24-N24) | R24: =IF(N24="","",$B$6+J$5*M24-N24) | S24: =IF(N24="","",$B$6+K$5*M24-N24)
E25: =IF(OR(A25="",C25=""),"",C25/MAX(1,N(D25))) | I25: =IF(A25="","",IF(H25<>"",H25,E25)) | J25: =IF(N25="","",$B$6+$B$4*M25-N25) | K25: =IF(A25="","",IF(F25<>"Cuenta de viajes","— lo pagas tú",IF(OR(B25="",E25=""),"Falta fecha o coste",IF(J25<0,"🔴 Faltan "&TEXT(-J25,"#,##0")&" €",IF(J25<$B$4,"🟡 Justo","🟢 Llega"))))) | M25: =IF(OR(A25="",B25=""),"",MAX(0,(YEAR(B25)-YEAR($B$5))*12+MONTH(B25)-MONTH($B$5)+1)) | N25: =IF(OR(A25="",B25="",F25<>"Cuenta de viajes"),"",SUMIFS($I$16:$I$65,$F$16:$F$65,"Cuenta de viajes",$B$16:$B$65,"<="&B25)) | P25: =IF(N25="","",$B$6+H$5*M25-N25) | Q25: =IF(N25="","",$B$6+I$5*M25-N25) | R25: =IF(N25="","",$B$6+J$5*M25-N25) | S25: =IF(N25="","",$B$6+K$5*M25-N25)
E26: =IF(OR(A26="",C26=""),"",C26/MAX(1,N(D26))) | I26: =IF(A26="","",IF(H26<>"",H26,E26)) | J26: =IF(N26="","",$B$6+$B$4*M26-N26) | K26: =IF(A26="","",IF(F26<>"Cuenta de viajes","— lo pagas tú",IF(OR(B26="",E26=""),"Falta fecha o coste",IF(J26<0,"🔴 Faltan "&TEXT(-J26,"#,##0")&" €",IF(J26<$B$4,"🟡 Justo","🟢 Llega"))))) | M26: =IF(OR(A26="",B26=""),"",MAX(0,(YEAR(B26)-YEAR($B$5))*12+MONTH(B26)-MONTH($B$5)+1)) | N26: =IF(OR(A26="",B26="",F26<>"Cuenta de viajes"),"",SUMIFS($I$16:$I$65,$F$16:$F$65,"Cuenta de viajes",$B$16:$B$65,"<="&B26)) | P26: =IF(N26="","",$B$6+H$5*M26-N26) | Q26: =IF(N26="","",$B$6+I$5*M26-N26) | R26: =IF(N26="","",$B$6+J$5*M26-N26) | S26: =IF(N26="","",$B$6+K$5*M26-N26)
E27: =IF(OR(A27="",C27=""),"",C27/MAX(1,N(D27))) | I27: =IF(A27="","",IF(H27<>"",H27,E27)) | J27: =IF(N27="","",$B$6+$B$4*M27-N27) | K27: =IF(A27="","",IF(F27<>"Cuenta de viajes","— lo pagas tú",IF(OR(B27="",E27=""),"Falta fecha o coste",IF(J27<0,"🔴 Faltan "&TEXT(-J27,"#,##0")&" €",IF(J27<$B$4,"🟡 Justo","🟢 Llega"))))) | M27: =IF(OR(A27="",B27=""),"",MAX(0,(YEAR(B27)-YEAR($B$5))*12+MONTH(B27)-MONTH($B$5)+1)) | N27: =IF(OR(A27="",B27="",F27<>"Cuenta de viajes"),"",SUMIFS($I$16:$I$65,$F$16:$F$65,"Cuenta de viajes",$B$16:$B$65,"<="&B27)) | P27: =IF(N27="","",$B$6+H$5*M27-N27) | Q27: =IF(N27="","",$B$6+I$5*M27-N27) | R27: =IF(N27="","",$B$6+J$5*M27-N27) | S27: =IF(N27="","",$B$6+K$5*M27-N27)
E28: =IF(OR(A28="",C28=""),"",C28/MAX(1,N(D28))) | I28: =IF(A28="","",IF(H28<>"",H28,E28)) | J28: =IF(N28="","",$B$6+$B$4*M28-N28) | K28: =IF(A28="","",IF(F28<>"Cuenta de viajes","— lo pagas tú",IF(OR(B28="",E28=""),"Falta fecha o coste",IF(J28<0,"🔴 Faltan "&TEXT(-J28,"#,##0")&" €",IF(J28<$B$4,"🟡 Justo","🟢 Llega"))))) | M28: =IF(OR(A28="",B28=""),"",MAX(0,(YEAR(B28)-YEAR($B$5))*12+MONTH(B28)-MONTH($B$5)+1)) | N28: =IF(OR(A28="",B28="",F28<>"Cuenta de viajes"),"",SUMIFS($I$16:$I$65,$F$16:$F$65,"Cuenta de viajes",$B$16:$B$65,"<="&B28)) | P28: =IF(N28="","",$B$6+H$5*M28-N28) | Q28: =IF(N28="","",$B$6+I$5*M28-N28) | R28: =IF(N28="","",$B$6+J$5*M28-N28) | S28: =IF(N28="","",$B$6+K$5*M28-N28)
E29: =IF(OR(A29="",C29=""),"",C29/MAX(1,N(D29))) | I29: =IF(A29="","",IF(H29<>"",H29,E29)) | J29: =IF(N29="","",$B$6+$B$4*M29-N29) | K29: =IF(A29="","",IF(F29<>"Cuenta de viajes","— lo pagas tú",IF(OR(B29="",E29=""),"Falta fecha o coste",IF(J29<0,"🔴 Faltan "&TEXT(-J29,"#,##0")&" €",IF(J29<$B$4,"🟡 Justo","🟢 Llega"))))) | M29: =IF(OR(A29="",B29=""),"",MAX(0,(YEAR(B29)-YEAR($B$5))*12+MONTH(B29)-MONTH($B$5)+1)) | N29: =IF(OR(A29="",B29="",F29<>"Cuenta de viajes"),"",SUMIFS($I$16:$I$65,$F$16:$F$65,"Cuenta de viajes",$B$16:$B$65,"<="&B29)) | P29: =IF(N29="","",$B$6+H$5*M29-N29) | Q29: =IF(N29="","",$B$6+I$5*M29-N29) | R29: =IF(N29="","",$B$6+J$5*M29-N29) | S29: =IF(N29="","",$B$6+K$5*M29-N29)
E30: =IF(OR(A30="",C30=""),"",C30/MAX(1,N(D30))) | I30: =IF(A30="","",IF(H30<>"",H30,E30)) | J30: =IF(N30="","",$B$6+$B$4*M30-N30) | K30: =IF(A30="","",IF(F30<>"Cuenta de viajes","— lo pagas tú",IF(OR(B30="",E30=""),"Falta fecha o coste",IF(J30<0,"🔴 Faltan "&TEXT(-J30,"#,##0")&" €",IF(J30<$B$4,"🟡 Justo","🟢 Llega"))))) | M30: =IF(OR(A30="",B30=""),"",MAX(0,(YEAR(B30)-YEAR($B$5))*12+MONTH(B30)-MONTH($B$5)+1)) | N30: =IF(OR(A30="",B30="",F30<>"Cuenta de viajes"),"",SUMIFS($I$16:$I$65,$F$16:$F$65,"Cuenta de viajes",$B$16:$B$65,"<="&B30)) | P30: =IF(N30="","",$B$6+H$5*M30-N30) | Q30: =IF(N30="","",$B$6+I$5*M30-N30) | R30: =IF(N30="","",$B$6+J$5*M30-N30) | S30: =IF(N30="","",$B$6+K$5*M30-N30)
E31: =IF(OR(A31="",C31=""),"",C31/MAX(1,N(D31))) | I31: =IF(A31="","",IF(H31<>"",H31,E31)) | J31: =IF(N31="","",$B$6+$B$4*M31-N31) | K31: =IF(A31="","",IF(F31<>"Cuenta de viajes","— lo pagas tú",IF(OR(B31="",E31=""),"Falta fecha o coste",IF(J31<0,"🔴 Faltan "&TEXT(-J31,"#,##0")&" €",IF(J31<$B$4,"🟡 Justo","🟢 Llega"))))) | M31: =IF(OR(A31="",B31=""),"",MAX(0,(YEAR(B31)-YEAR($B$5))*12+MONTH(B31)-MONTH($B$5)+1)) | N31: =IF(OR(A31="",B31="",F31<>"Cuenta de viajes"),"",SUMIFS($I$16:$I$65,$F$16:$F$65,"Cuenta de viajes",$B$16:$B$65,"<="&B31)) | P31: =IF(N31="","",$B$6+H$5*M31-N31) | Q31: =IF(N31="","",$B$6+I$5*M31-N31) | R31: =IF(N31="","",$B$6+J$5*M31-N31) | S31: =IF(N31="","",$B$6+K$5*M31-N31)
... E65: =IF(OR(A65="",C65=""),"",C65/MAX(1,N(D65))) | I65: =IF(A65="","",IF(H65<>"",H65,E65)) | J65: =IF(N65="","",$B$6+$B$4*M65-N65) | K65: =IF(A65="","",IF(F65<>"Cuenta de viajes","— lo pagas tú",IF(OR(B65="",E65=""),"Falta fecha o coste",IF(J65<0,"🔴 Faltan "&TEXT(-J65,"#,##0")&" €",IF(J65<$B$4,"🟡 Justo","🟢 Llega"))))) | M65: =IF(OR(A65="",B65=""),"",MAX(0,(YEAR(B65)-YEAR($B$5))*12+MONTH(B65)-MONTH($B$5)+1)) | N65: =IF(OR(A65="",B65="",F65<>"Cuenta de viajes"),"",SUMIFS($I$16:$I$65,$F$16:$F$65,"Cuenta de viajes",$B$16:$B$65,"<="&B65)) | P65: =IF(N65="","",$B$6+H$5*M65-N65) | Q65: =IF(N65="","",$B$6+I$5*M65-N65) | R65: =IF(N65="","",$B$6+J$5*M65-N65) | S65: =IF(N65="","",$B$6+K$5*M65-N65)

Sheet PARÁMETROS
A1: PARÁMETROS
A2: Supuestos del plan. Amarillo/azul: los cambias tú. Verde: salen de tus movimientos (puedes escribir encima una cifra).
A3: Parámetro | B3: Valor | C3: Nota
A4: Edad actual | B4: 41
A5: Edad de jubilación | B5: 67
A6: Año actual | B6: 2026 | C6: Año de la primera fila de la proyección
A7: Rentabilidad anual de la inversión | B7: 0.05 | C7: Supuesto nominal, antes de impuestos
A8: Rentabilidad anual del plan de pensiones | B8: 0.04 | C8: Supuesto nominal
A9: Rentabilidad anual del efectivo | B9: =IFERROR(SUMIFS(MOVIMIENTOS!$E$4:$E$20000,MOVIMIENTOS!$G$4:$G$20000,"Intereses",MOVIMIENTOS!$A$4:$A$20000,">="&EDATE(TODAY(),-12))/SUM(INDEX('MIS DATOS'!$B$6:$B$245,COUNT('MIS DATOS'!$A$6:$A$245)),INDEX('MIS DATOS'!$C$6:$C$245,COUNT('MIS DATOS'!$A$6:$A$245)),INDEX('MIS DATOS'!$D$6:$D$245,COUNT('MIS DATOS'!$A$6:$A$245))),0) -> 0.0059743609 | C9: Intereses de los últimos 12 meses ÷ tu efectivo de hoy. Si tus cuentas no pagan intereses, sale casi cero
A10: Inflación anual | B10: 0.025 | C10: Para pasar a € de hoy
A11: Aportación mensual a inversión | B11: 0 | C11: Hoy no inviertes: pruébalo en DECISIONES
A12: Aportación mensual al plan de pensiones | B12: 0 | C12: Si no tienes plan de pensiones, déjalo en 0
A13: Ahorro mensual que dejas en efectivo | B13: =IFERROR(AVERAGEIFS('MIS DATOS'!$I$6:$I$245,'MIS DATOS'!$N$6:$N$245,1),0) -> 976.86 | C13: Media de tus meses completos en MIS DATOS
A14: Subida anual de las aportaciones | B14: 0.02 | C14: Si tu sueldo sube, aportas algo más
A15: Gastos mensuales (€ de hoy) | B15: =IFERROR(AVERAGEIFS('MIS DATOS'!$H$6:$H$245,'MIS DATOS'!$N$6:$N$245,1),0) -> 1650.5492 | C15: Media de tus meses completos. Ojo: no incluye lo que queda por revisar, ni lo que pague otra persona o se pague en efectivo. Si sabes que gastas más, escribe tu cifra encima
A16: Regla de retirada | B16: 0.04 | C16: Regla del 4 %: lo que podrías sacar al año sin agotar el capital
A17: Pensión pública estimada al mes (€ de hoy, 14 pagas) | B17: 1250 | C17: Ficticio. Consulta la tuya en Tu Seguridad Social; se supone que sube con la inflación
A18: Meses de colchón de emergencia | B18: 6
A19: Revalorización anual de la vivienda | B19: 0.03 | C19: Supuesto
A20: Rentabilidad del capital en la jubilación | B20: 0.03 | C20: Más prudente que en la fase de ahorro
A23: NIVELES (por % de libertad financiera)
A24: Desde | B24: Nivel
A25: 0 | B25: 🌱 Semilla
A26: 0.05 | B26: 🛡️ Escudo
A27: 0.15 | B27: 🧭 Brújula
A28: 0.3 | B28: 🏗️ Cimientos
A29: 0.5 | B29: 🌉 Puente
A30: 0.75 | B30: 🏔️ Cumbre
A31: 1 | B31: 🕊️ Libre

Sheet REGLAS
A1: REGLAS
A2: Si el concepto contiene el texto → esa categoría. Gana la primera que encaje (de arriba abajo). Sin mayúsculas ni acentos que importen.
A3: El concepto contiene | B3: Solo en la cuenta (opcional) | C3: Signo (+ / − / vacío) | D3: Categoría | E3: Nota
A4: NOMINA | C4: + | D4: Nómina
A5: INTERESES | C5: + | D5: Intereses
A6: DEVOLUCION AEAT | C6: + | D6: Devolución de Hacienda
A7: TRASPASO | D7: Traspaso entre mis cuentas | E7: Entre tus propias cuentas: no es ingreso ni gasto
A8: LIQUIDACION TARJETA | D8: Pago de la tarjeta | E8: Lo que cuenta es cada compra de la tarjeta, no el cargo mensual
A9: CUENTA DE VIAJES | C9: - | D9: Aportación a la cuenta de viajes
A10: ALQUILER | C10: - | D10: Alquiler
A11: LUZ HOGAR | D11: Luz y gas
A12: AGUAS MUNICIPALES | D12: Agua | E12: Bimestral
A13: FIBRANET | D13: Internet y teléfono fijo
A14: SEGURO HOGAR | D14: Seguro del hogar | E14: Anual
A15: MOVILCOM | D15: Móvil
A16: SUPERMERCADO | D16: Supermercado
A17: FRUTERIA | D17: Supermercado
A18: RESTAURANTE | D18: Restaurantes y caprichos
A19: CAFETERIA | D19: Restaurantes y caprichos
A20: TRANSPORTE PUBLICO | D20: Transporte
A21: GASOLINERA | D21: Transporte
A22: FARMACIA | D22: Salud y farmacia
A23: STREAMFLIX | D23: Suscripciones
A24: TIENDA ONLINE | D24: Compras online
A25: MODA CENTRO | D25: Ropa y calzado
A26: PELUQUERIA | D26: Cuidado personal
... A28: LIBRERIA | D28: Ocio y cultura
A30: Lo que no encaja en ninguna regla (Bizum, ingresos en efectivo…) entra como «❓ Por revisar». Tras añadir reglas: menú Plan financiero → Reaplicar reglas a lo pendiente.

Sheet CATEGORÍAS
A1: CATEGORÍAS
A2: Tipo decide si cuenta como ingreso, gasto o nada (traspaso). Grupo «Casa» es lo que sale en la pestaña CASA. Puedes añadir filas.
A3: Categoría | B3: Tipo | C3: Grupo
A4: Nómina | B4: Ingreso | C4: Trabajo
A5: Intereses | B5: Ingreso | C5: Ahorro
A6: Devolución de Hacienda | B6: Ingreso | C6: Otros ingresos
A7: Regalos recibidos | B7: Ingreso | C7: Otros ingresos
A8: Otros ingresos | B8: Ingreso | C8: Otros ingresos
A9: Ingreso de efectivo propio | B9: Traspaso | C9: Traspasos
A10: Traspaso entre mis cuentas | B10: Traspaso | C10: Traspasos
A11: Pago de la tarjeta | B11: Traspaso | C11: Traspasos
A12: Alquiler | B12: Gasto | C12: Casa
A13: Comunidad | B13: Gasto | C13: Casa
A14: Luz y gas | B14: Gasto | C14: Casa
... A37: Otros gastos | B37: Gasto | C37: Otros
A38: ❓ Por revisar | B38: Por revisar

Sheet PROYECCIÓN
A1: PROYECCIÓN
A2: Cálculo año a año. No hace falta tocar nada aquí. Si «Inversión con decisiones» sale negativa, ese dinero sale del efectivo.
A3: PUNTO DE PARTIDA (último mes de MIS DATOS)
A4: Último mes registrado | B4: =INDEX('MIS DATOS'!$A$6:$A$245,COUNT('MIS DATOS'!$A$6:$A$245)) -> 46266
A5: Efectivo (CaixaBank + Openbank + ING) | B5: =INDEX('MIS DATOS'!$B$6:$B$245,COUNT('MIS DATOS'!$A$6:$A$245))+INDEX('MIS DATOS'!$C$6:$C$245,COUNT('MIS DATOS'!$A$6:$A$245))+INDEX('MIS DATOS'!$D$6:$D$245,COUNT('MIS DATOS'!$A$6:$A$245)) -> 67957.06
A6: Inversión | B6: =INDEX('MIS DATOS'!$E$6:$E$245,COUNT('MIS DATOS'!$A$6:$A$245)) -> 0
A7: Plan de pensiones | B7: =INDEX('MIS DATOS'!$F$6:$F$245,COUNT('MIS DATOS'!$A$6:$A$245)) -> 0
A8: Patrimonio líquido | B8: =B5+B6+B7 -> 67957.06
A9: Tus inmuebles (tu parte) | B9: =INMUEBLES!$D$10 -> 0
A10: Patrimonio total con inmuebles | B10: =B8+B9 -> 67957.06
A11: Años hasta la jubilación | B11: =PARÁMETROS!$B$5-PARÁMETROS!$B$4 -> 26
A13: FASE DE AHORRO (hasta la jubilación)
A14: t | B14: Edad | C14: Año | D14: Efectivo | E14: Inversión | F14: Pensiones | G14: Total líquido | H14: Total en € de hoy | I14: Lo que tenías hoy | J14: Lo que ahorras | K14: Lo que generan tus inversiones | L14: Gastos anuales | M14: % libertad financiera | N14: Inversión con decisiones | O14: Total con decisiones | P14: Gastos con decisiones | Q14: % libertad con decisiones | R14: Inmuebles (sin decisiones) | S14: Inmuebles netos de hipoteca (con decisiones) | T14: Total con inmuebles (sin decisiones) | U14: Total con inmuebles (con decisiones) | V14: Efectivo con decisiones
A15: 0 | B15: =IF($A15>$B$11,"",PARÁMETROS!$B$4+A15) -> 41 | C15: =IF($A15>$B$11,"",PARÁMETROS!$B$6+A15) -> 2026 | D15: =$B$5 -> 67957.06 | E15: =$B$6 -> 0 | F15: =$B$7 -> 0 | G15: =IF($A15>$B$11,"",D15+E15+F15) -> 67957.06 | H15: =IF($A15>$B$11,"",G15/(1+PARÁMETROS!$B$10)^A15) -> 67957.06 | I15: =IF($A15>$B$11,"",$G$15) -> 67957.06 | J15: =0 -> 0 | K15: =IF($A15>$B$11,"",G15-I15-J15) -> 0 | L15: =IF($A15>$B$11,"",PARÁMETROS!$B$15*12*(1+PARÁMETROS!$B$10)^A15) -> 19806.59 | M15: =IF($A15>$B$11,"",G15*PARÁMETROS!$B$16/L15) -> 0.13724131 | N15: =E15+DECISIONES!$B$5-IF(DECISIONES!$B$14=0,DECISIONES!$B$15,0) -> -55000 | O15: =IF($A15>$B$11,"",V15+N15+F15) -> 12957.06 | P15: =IF($A15>$B$11,"",(PARÁMETROS!$B$15-DECISIONES!$B$7)*12*(1+PARÁMETROS!$B$10)^A15-IF(A15>DECISIONES!$B$14,DECISIONES!$B$19*12*(1+PARÁMETROS!$B$10)^A15,0)) -> 19806.59 | Q15: =IF($A15>$B$11,"",O15*PARÁMETROS!$B$16/P15) -> 0.02616717 | R15: =IF($A15>$B$11,"",SUMPRODUCT(INMUEBLES!$D$5:$D$9,(1+INMUEBLES!$G$5:$G$9)^A15)) -> 0 | S15: =IF($A15>$B$11,"",R15-VIVIENDA!$B$5*(1+PARÁMETROS!$B$19)^A15*VIVIENDA!$B$6+IF(AND(DECISIONES!$B$10="Sí",A15>=DECISIONES!$B$14),VIVIENDA!$B$5*(1+PARÁMETROS!$B$19)^A15-IF(A15-DECISIONES!$B$14>=DECISIONES!$B$18,0,MAX(0,FV(VIVIENDA!$B$11/12,(A15-DECISIONES!$B$14)*12,DECISIONES!$B$17,-DECISIONES!$B$16))),VIVIENDA!$B$5*(1+PARÁMETROS!$B$19)^A15*VIVIENDA!$B$6)) -> 38900 | T15: =IF($A15>$B$11,"",G15+R15) -> 67957.06 | U15: =IF($A15>$B$11,"",O15+S15) -> 51857.06 | V15: =IF($A15>$B$11,"",D15-DECISIONES!$B$5*(1+PARÁMETROS!$B$9)^A15) -> 67957.06
A16: 1 | B16: =IF($A16>$B$11,"",PARÁMETROS!$B$4+A16) -> 42 | C16: =IF($A16>$B$11,"",PARÁMETROS!$B$6+A16) -> 2027 | D16: =IF($A16>$B$11,"",D15*(1+PARÁMETROS!$B$9)+PARÁMETROS!$B$13*12*(1+PARÁMETROS!$B$14)^(A16-1)) -> 80085.38 | E16: =IF($A16>$B$11,"",E15*(1+PARÁMETROS!$B$7)+PARÁMETROS!$B$11*12*(1+PARÁMETROS!$B$14)^(A16-1)) -> 0 | F16: =IF($A16>$B$11,"",F15*(1+PARÁMETROS!$B$8)+PARÁMETROS!$B$12*12*(1+PARÁMETROS!$B$14)^(A16-1)) -> 0 | G16: =IF($A16>$B$11,"",D16+E16+F16) -> 80085.38 | H16: =IF($A16>$B$11,"",G16/(1+PARÁMETROS!$B$10)^A16) -> 78132.078 | I16: =IF($A16>$B$11,"",$G$15) -> 67957.06 | J16: =IF($A16>$B$11,"",J15+(PARÁMETROS!$B$13+PARÁMETROS!$B$11+PARÁMETROS!$B$12)*12*(1+PARÁMETROS!$B$14)^(A16-1)) -> 11722.32 | K16: =IF($A16>$B$11,"",G16-I16-J16) -> 406 | L16: =IF($A16>$B$11,"",PARÁMETROS!$B$15*12*(1+PARÁMETROS!$B$10)^A16) -> 20301.755 | M16: =IF($A16>$B$11,"",G16*PARÁMETROS!$B$16/L16) -> 0.15779006 | N16: =IF($A16>$B$11,"",N15*(1+DECISIONES!$B$9)+(PARÁMETROS!$B$11+DECISIONES!$B$6+IF(DECISIONES!$B$8="Sí",DECISIONES!$B$7,0))*12*(1+PARÁMETROS!$B$14)^(A16-1)-IF(A16=DECISIONES!$B$14,DECISIONES!$B$15,0)-IF(AND(A16>DECISIONES!$B$14,A16<=DECISIONES!$B$14+DECISIONES!$B$18),DECISIONES!$B$17*12,0)+IF(A16>DECISIONES!$B$14,DECISIONES!$B$19*12*(1+PARÁMETROS!$B$10)^A16,0)) -> -57487.884 | O16: =IF($A16>$B$11,"",V16+N16+F16) -> 22597.496 | P16: =IF($A16>$B$11,"",(PARÁMETROS!$B$15-DECISIONES!$B$7)*12*(1+PARÁMETROS!$B$10)^A16-IF(A16>DECISIONES!$B$14,DECISIONES!$B$19*12*(1+PARÁMETROS!$B$10)^A16,0)) -> 9846.7548 | Q16: =IF($A16>$B$11,"",O16*PARÁMETROS!$B$16/P16) -> 0.091796727 | R16: =IF($A16>$B$11,"",SUMPRODUCT(INMUEBLES!$D$5:$D$9,(1+INMUEBLES!$G$5:$G$9)^A16)) -> 0 | S16: =IF($A16>$B$11,"",R16-VIVIENDA!$B$5*(1+PARÁMETROS!$B$19)^A16*VIVIENDA!$B$6+IF(AND(DECISIONES!$B$10="Sí",A16>=DECISIONES!$B$14),VIVIENDA!$B$5*(1+PARÁMETROS!$B$19)^A16-IF(A16-DECISIONES!$B$14>=DECISIONES!$B$18,0,MAX(0,FV(VIVIENDA!$B$11/12,(A16-DECISIONES!$B$14)*12,DECISIONES!$B$17,-DECISIONES!$B$16))),VIVIENDA!$B$5*(1+PARÁMETROS!$B$19)^A16*VIVIENDA!$B$6)) -> 50507.189 | T16: =IF($A16>$B$11,"",G16+R16) -> 80085.38 | U16: =IF($A16>$B$11,"",O16+S16) -> 73104.686 | V16: =IF($A16>$B$11,"",D16-DECISIONES!$B$5*(1+PARÁMETROS!$B$9)^A16) -> 80085.38
A17: 2 | B17: =IF($A17>$B$11,"",PARÁMETROS!$B$4+A17) -> 43 | C17: =IF($A17>$B$11,"",PARÁMETROS!$B$6+A17) -> 2028 | D17: =IF($A17>$B$11,"",D16*(1+PARÁMETROS!$B$9)+PARÁMETROS!$B$13*12*(1+PARÁMETROS!$B$14)^(A17-1)) -> 92520.605 | E17: =IF($A17>$B$11,"",E16*(1+PARÁMETROS!$B$7)+PARÁMETROS!$B$11*12*(1+PARÁMETROS!$B$14)^(A17-1)) -> 0 | F17: =IF($A17>$B$11,"",F16*(1+PARÁMETROS!$B$8)+PARÁMETROS!$B$12*12*(1+PARÁMETROS!$B$14)^(A17-1)) -> 0 | G17: =IF($A17>$B$11,"",D17+E17+F17) -> 92520.605 | H17: =IF($A17>$B$11,"",G17/(1+PARÁMETROS!$B$10)^A17) -> 88062.444 | I17: =IF($A17>$B$11,"",$G$15) -> 67957.06 | J17: =IF($A17>$B$11,"",J16+(PARÁMETROS!$B$13+PARÁMETROS!$B$11+PARÁMETROS!$B$12)*12*(1+PARÁMETROS!$B$14)^(A17-1)) -> 23679.086 | K17: =IF($A17>$B$11,"",G17-I17-J17) -> 884.45896 | L17: =IF($A17>$B$11,"",PARÁMETROS!$B$15*12*(1+PARÁMETROS!$B$10)^A17) -> 20809.299 | M17: =IF($A17>$B$11,"",G17*PARÁMETROS!$B$16/L17) -> 0.17784474 | N17: =IF($A17>$B$11,"",N16*(1+DECISIONES!$B$9)+(PARÁMETROS!$B$11+DECISIONES!$B$6+IF(DECISIONES!$B$8="Sí",DECISIONES!$B$7,0))*12*(1+PARÁMETROS!$B$14)^(A17-1)-IF(A17=DECISIONES!$B$14,DECISIONES!$B$15,0)-IF(AND(A17>DECISIONES!$B$14,A17<=DECISIONES!$B$14+DECISIONES!$B$18),DECISIONES!$B$17*12,0)+IF(A17>DECISIONES!$B$14,DECISIONES!$B$19*12*(1+PARÁMETROS!$B$10)^A17,0)) -> -59838.786 | O17: =IF($A17>$B$11,"",V17+N17+F17) -> 32681.819 | P17: =IF($A17>$B$11,"",(PARÁMETROS!$B$15-DECISIONES!$B$7)*12*(1+PARÁMETROS!$B$10)^A17-IF(A17>DECISIONES!$B$14,DECISIONES!$B$19*12*(1+PARÁMETROS!$B$10)^A17,0)) -> 10092.924 | Q17: =IF($A17>$B$11,"",O17*PARÁMETROS!$B$16/P17) -> 0.12952369 | R17: =IF($A17>$B$11,"",SUMPRODUCT(INMUEBLES!$D$5:$D$9,(1+INMUEBLES!$G$5:$G$9)^A17)) -> 0 | S17: =IF($A17>$B$11,"",R17-VIVIENDA!$B$5*(1+PARÁMETROS!$B$19)^A17*VIVIENDA!$B$6+IF(AND(DECISIONES!$B$10="Sí",A17>=DECISIONES!$B$14),VIVIENDA!$B$5*(1+PARÁMETROS!$B$19)^A17-IF(A17-DECISIONES!$B$14>=DECISIONES!$B$18,0,MAX(0,FV(VIVIENDA!$B$11/12,(A17-DECISIONES!$B$14)*12,DECISIONES!$B$17,-DECISIONES!$B$16))),VIVIENDA!$B$5*(1+PARÁMETROS!$B$19)^A17*VIVIENDA!$B$6)) -> 62459.533 | T17: =IF($A17>$B$11,"",G17+R17) -> 92520.605 | U17: =IF($A17>$B$11,"",O17+S17) -> 95141.352 | V17: =IF($A17>$B$11,"",D17-DECISIONES!$B$5*(1+PARÁMETROS!$B$9)^A17) -> 92520.605
A18: 3 | B18: =IF($A18>$B$11,"",PARÁMETROS!$B$4+A18) -> 44 | C18: =IF($A18>$B$11,"",PARÁMETROS!$B$6+A18) -> 2029 | D18: =IF($A18>$B$11,"",D17*(1+PARÁMETROS!$B$9)+PARÁMETROS!$B$13*12*(1+PARÁMETROS!$B$14)^(A18-1)) -> 105269.26 | E18: =IF($A18>$B$11,"",E17*(1+PARÁMETROS!$B$7)+PARÁMETROS!$B$11*12*(1+PARÁMETROS!$B$14)^(A18-1)) -> 0 | F18: =IF($A18>$B$11,"",F17*(1+PARÁMETROS!$B$8)+PARÁMETROS!$B$12*12*(1+PARÁMETROS!$B$14)^(A18-1)) -> 0 | G18: =IF($A18>$B$11,"",D18+E18+F18) -> 105269.26 | H18: =IF($A18>$B$11,"",G18/(1+PARÁMETROS!$B$10)^A18) -> 97752.971 | I18: =IF($A18>$B$11,"",$G$15) -> 67957.06 | J18: =IF($A18>$B$11,"",J17+(PARÁMETROS!$B$13+PARÁMETROS!$B$11+PARÁMETROS!$B$12)*12*(1+PARÁMETROS!$B$14)^(A18-1)) -> 35874.988 | K18: =IF($A18>$B$11,"",G18-I18-J18) -> 1437.2104 | L18: =IF($A18>$B$11,"",PARÁMETROS!$B$15*12*(1+PARÁMETROS!$B$10)^A18) -> 21329.531 | M18: =IF($A18>$B$11,"",G18*PARÁMETROS!$B$16/L18) -> 0.19741505 | N18: =IF($A18>$B$11,"",N17*(1+DECISIONES!$B$9)+(PARÁMETROS!$B$11+DECISIONES!$B$6+IF(DECISIONES!$B$8="Sí",DECISIONES!$B$7,0))*12*(1+PARÁMETROS!$B$14)^(A18-1)-IF(A18=DECISIONES!$B$14,DECISIONES!$B$15,0)-IF(AND(A18>DECISIONES!$B$14,A18<=DECISIONES!$B$14+DECISIONES!$B$18),DECISIONES!$B$17*12,0)+IF(A18>DECISIONES!$B$14,DECISIONES!$B$19*12*(1+PARÁMETROS!$B$10)^A18,0)) -> -62039.325 | O18: =IF($A18>$B$11,"",V18+N18+F18) -> 43229.934 | P18: =IF($A18>$B$11,"",(PARÁMETROS!$B$15-DECISIONES!$B$7)*12*(1+PARÁMETROS!$B$10)^A18-IF(A18>DECISIONES!$B$14,DECISIONES!$B$19*12*(1+PARÁMETROS!$B$10)^A18,0)) -> 10345.247 | Q18: =IF($A18>$B$11,"",O18*PARÁMETROS!$B$16/P18) -> 0.16714897 | R18: =IF($A18>$B$11,"",SUMPRODUCT(INMUEBLES!$D$5:$D$9,(1+INMUEBLES!$G$5:$G$9)^A18)) -> 0 | S18: =IF($A18>$B$11,"",R18-VIVIENDA!$B$5*(1+PARÁMETROS!$B$19)^A18*VIVIENDA!$B$6+IF(AND(DECISIONES!$B$10="Sí",A18>=DECISIONES!$B$14),VIVIENDA!$B$5*(1+PARÁMETROS!$B$19)^A18-IF(A18-DECISIONES!$B$14>=DECISIONES!$B$18,0,MAX(0,FV(VIVIENDA!$B$11/12,(A18-DECISIONES!$B$14)*12,DECISIONES!$B$17,-DECISIONES!$B$16))),VIVIENDA!$B$5*(1+PARÁMETROS!$B$19)^A18*VIVIENDA!$B$6)) -> 74767.296 | T18: =IF($A18>$B$11,"",G18+R18) -> 105269.26 | U18: =IF($A18>$B$11,"",O18+S18) -> 117997.23 | V18: =IF($A18>$B$11,"",D18-DECISIONES!$B$5*(1+PARÁMETROS!$B$9)^A18) -> 105269.26
A19: 4 | B19: =IF($A19>$B$11,"",PARÁMETROS!$B$4+A19) -> 45 | C19: =IF($A19>$B$11,"",PARÁMETROS!$B$6+A19) -> 2030 | D19: =IF($A19>$B$11,"",D18*(1+PARÁMETROS!$B$9)+PARÁMETROS!$B$13*12*(1+PARÁMETROS!$B$14)^(A19-1)) -> 118337.99 | E19: =IF($A19>$B$11,"",E18*(1+PARÁMETROS!$B$7)+PARÁMETROS!$B$11*12*(1+PARÁMETROS!$B$14)^(A19-1)) -> 0 | F19: =IF($A19>$B$11,"",F18*(1+PARÁMETROS!$B$8)+PARÁMETROS!$B$12*12*(1+PARÁMETROS!$B$14)^(A19-1)) -> 0 | G19: =IF($A19>$B$11,"",D19+E19+F19) -> 118337.99 | H19: =IF($A19>$B$11,"",G19/(1+PARÁMETROS!$B$10)^A19) -> 107208.38 | I19: =IF($A19>$B$11,"",$G$15) -> 67957.06 | J19: =IF($A19>$B$11,"",J18+(PARÁMETROS!$B$13+PARÁMETROS!$B$11+PARÁMETROS!$B$12)*12*(1+PARÁMETROS!$B$14)^(A19-1)) -> 48314.808 | K19: =IF($A19>$B$11,"",G19-I19-J19) -> 2066.127 | L19: =IF($A19>$B$11,"",PARÁMETROS!$B$15*12*(1+PARÁMETROS!$B$10)^A19) -> 21862.769 | M19: =IF($A19>$B$11,"",G19*PARÁMETROS!$B$16/L19) -> 0.21651053 | N19: =IF($A19>$B$11,"",N18*(1+DECISIONES!$B$9)+(PARÁMETROS!$B$11+DECISIONES!$B$6+IF(DECISIONES!$B$8="Sí",DECISIONES!$B$7,0))*12*(1+PARÁMETROS!$B$14)^(A19-1)-IF(A19=DECISIONES!$B$14,DECISIONES!$B$15,0)-IF(AND(A19>DECISIONES!$B$14,A19<=DECISIONES!$B$14+DECISIONES!$B$18),DECISIONES!$B$17*12,0)+IF(A19>DECISIONES!$B$14,DECISIONES!$B$19*12*(1+PARÁMETROS!$B$10)^A19,0)) -> -64075.283 | O19: =IF($A19>$B$11,"",V19+N19+F19) -> 54262.711 | P19: =IF($A19>$B$11,"",(PARÁMETROS!$B$15-DECISIONES!$B$7)*12*(1+PARÁMETROS!$B$10)^A19-IF(A19>DECISIONES!$B$14,DECISIONES!$B$19*12*(1+PARÁMETROS!$B$10)^A19,0)) -> 10603.878 | Q19: =IF($A19>$B$11,"",O19*PARÁMETROS!$B$16/P19) -> 0.20469007 | R19: =IF($A19>$B$11,"",SUMPRODUCT(INMUEBLES!$D$5:$D$9,(1+INMUEBLES!$G$5:$G$9)^A19)) -> 0 | S19: =IF($A19>$B$11,"",R19-VIVIENDA!$B$5*(1+PARÁMETROS!$B$19)^A19*VIVIENDA!$B$6+IF(AND(DECISIONES!$B$10="Sí",A19>=DECISIONES!$B$14),VIVIENDA!$B$5*(1+PARÁMETROS!$B$19)^A19-IF(A19-DECISIONES!$B$14>=DECISIONES!$B$18,0,MAX(0,FV(VIVIENDA!$B$11/12,(A19-DECISIONES!$B$14)*12,DECISIONES!$B$17,-DECISIONES!$B$16))),VIVIENDA!$B$5*(1+PARÁMETROS!$B$19)^A19*VIVIENDA!$B$6)) -> 87441.047 | T19: =IF($A19>$B$11,"",G19+R19) -> 118337.99 | U19: =IF($A19>$B$11,"",O19+S19) -> 141703.76 | V19: =IF($A19>$B$11,"",D19-DECISIONES!$B$5*(1+PARÁMETROS!$B$9)^A19) -> 118337.99
A20: 5 | B20: =IF($A20>$B$11,"",PARÁMETROS!$B$4+A20) -> 46 | C20: =IF($A20>$B$11,"",PARÁMETROS!$B$6+A20) -> 2031 | D20: =IF($A20>$B$11,"",D19*(1+PARÁMETROS!$B$9)+PARÁMETROS!$B$13*12*(1+PARÁMETROS!$B$14)^(A20-1)) -> 131733.6 | E20: =IF($A20>$B$11,"",E19*(1+PARÁMETROS!$B$7)+PARÁMETROS!$B$11*12*(1+PARÁMETROS!$B$14)^(A20-1)) -> 0 | F20: =IF($A20>$B$11,"",F19*(1+PARÁMETROS!$B$8)+PARÁMETROS!$B$12*12*(1+PARÁMETROS!$B$14)^(A20-1)) -> 0 | G20: =IF($A20>$B$11,"",D20+E20+F20) -> 131733.6 | H20: =IF($A20>$B$11,"",G20/(1+PARÁMETROS!$B$10)^A20) -> 116433.31 | I20: =IF($A20>$B$11,"",$G$15) -> 67957.06 | J20: =IF($A20>$B$11,"",J19+(PARÁMETROS!$B$13+PARÁMETROS!$B$11+PARÁMETROS!$B$12)*12*(1+PARÁMETROS!$B$14)^(A20-1)) -> 61003.424 | K20: =IF($A20>$B$11,"",G20-I20-J20) -> 2773.1209 | L20: =IF($A20>$B$11,"",PARÁMETROS!$B$15*12*(1+PARÁMETROS!$B$10)^A20) -> 22409.339 | M20: =IF($A20>$B$11,"",G20*PARÁMETROS!$B$16/L20) -> 0.23514055 | N20: =IF($A20>$B$11,"",N19*(1+DECISIONES!$B$9)+(PARÁMETROS!$B$11+DECISIONES!$B$6+IF(DECISIONES!$B$8="Sí",DECISIONES!$B$7,0))*12*(1+PARÁMETROS!$B$14)^(A20-1)-IF(A20=DECISIONES!$B$14,DECISIONES!$B$15,0)-IF(AND(A20>DECISIONES!$B$14,A20<=DECISIONES!$B$14+DECISIONES!$B$18),DECISIONES!$B$17*12,0)+IF(A20>DECISIONES!$B$14,DECISIONES!$B$19*12*(1+PARÁMETROS!$B$10)^A20,0)) -> -65931.567 | O20: =IF($A20>$B$11,"",V20+N20+F20) -> 65802.037 | P20: =IF($A20>$B$11,"",(PARÁMETROS!$B$15-DECISIONES!$B$7)*12*(1+PARÁMETROS!$B$10)^A20-IF(A20>DECISIONES!$B$14,DECISIONES!$B$19*12*(1+PARÁMETROS!$B$10)^A20,0)) -> 10868.975 | Q20: =IF($A20>$B$11,"",O20*PARÁMETROS!$B$16/P20) -> 0.24216465 | R20: =IF($A20>$B$11,"",SUMPRODUCT(INMUEBLES!$D$5:$D$9,(1+INMUEBLES!$G$5:$G$9)^A20)) -> 0 | S20: =IF($A20>$B$11,"",R20-VIVIENDA!$B$5*(1+PARÁMETROS!$B$19)^A20*VIVIENDA!$B$6+IF(AND(DECISIONES!$B$10="Sí",A20>=DECISIONES!$B$14),VIVIENDA!$B$5*(1+PARÁMETROS!$B$19)^A20-IF(A20-DECISIONES!$B$14>=DECISIONES!$B$18,0,MAX(0,FV(VIVIENDA!$B$11/12,(A20-DECISIONES!$B$14)*12,DECISIONES!$B$17,-DECISIONES!$B$16))),VIVIENDA!$B$5*(1+PARÁMETROS!$B$19)^A20*VIVIENDA!$B$6)) -> 100491.67 | T20: =IF($A20>$B$11,"",G20+R20) -> 131733.6 | U20: =IF($A20>$B$11,"",O20+S20) -> 166293.71 | V20: =IF($A20>$B$11,"",D20-DECISIONES!$B$5*(1+PARÁMETROS!$B$9)^A20) -> 131733.6
A21: 6 | B21: =IF($A21>$B$11,"",PARÁMETROS!$B$4+A21) -> 47 | C21: =IF($A21>$B$11,"",PARÁMETROS!$B$6+A21) -> 2032 | D21: =IF($A21>$B$11,"",D20*(1+PARÁMETROS!$B$9)+PARÁMETROS!$B$13*12*(1+PARÁMETROS!$B$14)^(A21-1)) -> 145463.02 | E21: =IF($A21>$B$11,"",E20*(1+PARÁMETROS!$B$7)+PARÁMETROS!$B$11*12*(1+PARÁMETROS!$B$14)^(A21-1)) -> 0 | F21: =IF($A21>$B$11,"",F20*(1+PARÁMETROS!$B$8)+PARÁMETROS!$B$12*12*(1+PARÁMETROS!$B$14)^(A21-1)) -> 0 | G21: =IF($A21>$B$11,"",D21+E21+F21) -> 145463.02 | H21: =IF($A21>$B$11,"",G21/(1+PARÁMETROS!$B$10)^A21) -> 125432.3 | I21: =IF($A21>$B$11,"",$G$15) -> 67957.06 | J21: =IF($A21>$B$11,"",J20+(PARÁMETROS!$B$13+PARÁMETROS!$B$11+PARÁMETROS!$B$12)*12*(1+PARÁMETROS!$B$14)^(A21-1)) -> 73945.813 | K21: =IF($A21>$B$11,"",G21-I21-J21) -> 3560.145 | L21: =IF($A21>$B$11,"",PARÁMETROS!$B$15*12*(1+PARÁMETROS!$B$10)^A21) -> 22969.572 | M21: =IF($A21>$B$11,"",G21*PARÁMETROS!$B$16/L21) -> 0.25331428 | N21: =IF($A21>$B$11,"",N20*(1+DECISIONES!$B$9)+(PARÁMETROS!$B$11+DECISIONES!$B$6+IF(DECISIONES!$B$8="Sí",DECISIONES!$B$7,0))*12*(1+PARÁMETROS!$B$14)^(A21-1)-IF(A21=DECISIONES!$B$14,DECISIONES!$B$15,0)-IF(AND(A21>DECISIONES!$B$14,A21<=DECISIONES!$B$14+DECISIONES!$B$18),DECISIONES!$B$17*12,0)+IF(A21>DECISIONES!$B$14,DECISIONES!$B$19*12*(1+PARÁMETROS!$B$10)^A21,0)) -> -67592.157 | O21: =IF($A21>$B$11,"",V21+N21+F21) -> 77870.861 | P21: =IF($A21>$B$11,"",(PARÁMETROS!$B$15-DECISIONES!$B$7)*12*(1+PARÁMETROS!$B$10)^A21-IF(A21>DECISIONES!$B$14,DECISIONES!$B$19*12*(1+PARÁMETROS!$B$10)^A21,0)) -> 11140.699 | Q21: =IF($A21>$B$11,"",O21*PARÁMETROS!$B$16/P21) -> 0.27959057 | R21: =IF($A21>$B$11,"",SUMPRODUCT(INMUEBLES!$D$5:$D$9,(1+INMUEBLES!$G$5:$G$9)^A21)) -> 0 | S21: =IF($A21>$B$11,"",R21-VIVIENDA!$B$5*(1+PARÁMETROS!$B$19)^A21*VIVIENDA!$B$6+IF(AND(DECISIONES!$B$10="Sí",A21>=DECISIONES!$B$14),VIVIENDA!$B$5*(1+PARÁMETROS!$B$19)^A21-IF(A21-DECISIONES!$B$14>=DECISIONES!$B$18,0,MAX(0,FV(VIVIENDA!$B$11/12,(A21-DECISIONES!$B$14)*12,DECISIONES!$B$17,-DECISIONES!$B$16))),VIVIENDA!$B$5*(1+PARÁMETROS!$B$19)^A21*VIVIENDA!$B$6)) -> 113930.38 | T21: =IF($A21>$B$11,"",G21+R21) -> 145463.02 | U21: =IF($A21>$B$11,"",O21+S21) -> 191801.24 | V21: =IF($A21>$B$11,"",D21-DECISIONES!$B$5*(1+PARÁMETROS!$B$9)^A21) -> 145463.02
A22: 7 | B22: =IF($A22>$B$11,"",PARÁMETROS!$B$4+A22) -> 48 | C22: =IF($A22>$B$11,"",PARÁMETROS!$B$6+A22) -> 2033 | D22: =IF($A22>$B$11,"",D21*(1+PARÁMETROS!$B$9)+PARÁMETROS!$B$13*12*(1+PARÁMETROS!$B$14)^(A22-1)) -> 159533.3 | E22: =IF($A22>$B$11,"",E21*(1+PARÁMETROS!$B$7)+PARÁMETROS!$B$11*12*(1+PARÁMETROS!$B$14)^(A22-1)) -> 0 | F22: =IF($A22>$B$11,"",F21*(1+PARÁMETROS!$B$8)+PARÁMETROS!$B$12*12*(1+PARÁMETROS!$B$14)^(A22-1)) -> 0 | G22: =IF($A22>$B$11,"",D22+E22+F22) -> 159533.3 | H22: =IF($A22>$B$11,"",G22/(1+PARÁMETROS!$B$10)^A22) -> 134209.82 | I22: =IF($A22>$B$11,"",$G$15) -> 67957.06 | J22: =IF($A22>$B$11,"",J21+(PARÁMETROS!$B$13+PARÁMETROS!$B$11+PARÁMETROS!$B$12)*12*(1+PARÁMETROS!$B$14)^(A22-1)) -> 87147.049 | K22: =IF($A22>$B$11,"",G22-I22-J22) -> 4429.1935 | L22: =IF($A22>$B$11,"",PARÁMETROS!$B$15*12*(1+PARÁMETROS!$B$10)^A22) -> 23543.811 | M22: =IF($A22>$B$11,"",G22*PARÁMETROS!$B$16/L22) -> 0.27104074 | N22: =IF($A22>$B$11,"",N21*(1+DECISIONES!$B$9)+(PARÁMETROS!$B$11+DECISIONES!$B$6+IF(DECISIONES!$B$8="Sí",DECISIONES!$B$7,0))*12*(1+PARÁMETROS!$B$14)^(A22-1)-IF(A22=DECISIONES!$B$14,DECISIONES!$B$15,0)-IF(AND(A22>DECISIONES!$B$14,A22<=DECISIONES!$B$14+DECISIONES!$B$18),DECISIONES!$B$17*12,0)+IF(A22>DECISIONES!$B$14,DECISIONES!$B$19*12*(1+PARÁMETROS!$B$10)^A22,0)) -> -69040.053 | O22: =IF($A22>$B$11,"",V22+N22+F22) -> 90493.249 | P22: =IF($A22>$B$11,"",(PARÁMETROS!$B$15-DECISIONES!$B$7)*12*(1+PARÁMETROS!$B$10)^A22-IF(A22>DECISIONES!$B$14,DECISIONES!$B$19*12*(1+PARÁMETROS!$B$10)^A22,0)) -> 11419.217 | Q22: =IF($A22>$B$11,"",O22*PARÁMETROS!$B$16/P22) -> 0.31698584 | R22: =IF($A22>$B$11,"",SUMPRODUCT(INMUEBLES!$D$5:$D$9,(1+INMUEBLES!$G$5:$G$9)^A22)) -> 0 | S22: =IF($A22>$B$11,"",R22-VIVIENDA!$B$5*(1+PARÁMETROS!$B$19)^A22*VIVIENDA!$B$6+IF(AND(DECISIONES!$B$10="Sí",A22>=DECISIONES!$B$14),VIVIENDA!$B$5*(1+PARÁMETROS!$B$19)^A22-IF(A22-DECISIONES!$B$14>=DECISIONES!$B$18,0,MAX(0,FV(VIVIENDA!$B$11/12,(A22-DECISIONES!$B$14)*12,DECISIONES!$B$17,-DECISIONES!$B$16))),VIVIENDA!$B$5*(1+PARÁMETROS!$B$19)^A22*VIVIENDA!$B$6)) -> 127768.7 | T22: =IF($A22>$B$11,"",G22+R22) -> 159533.3 | U22: =IF($A22>$B$11,"",O22+S22) -> 218261.95 | V22: =IF($A22>$B$11,"",D22-DECISIONES!$B$5*(1+PARÁMETROS!$B$9)^A22) -> 159533.3
A23: 8 | B23: =IF($A23>$B$11,"",PARÁMETROS!$B$4+A23) -> 49 | C23: =IF($A23>$B$11,"",PARÁMETROS!$B$6+A23) -> 2034 | D23: =IF($A23>$B$11,"",D22*(1+PARÁMETROS!$B$9)+PARÁMETROS!$B$13*12*(1+PARÁMETROS!$B$14)^(A23-1)) -> 173951.67 | E23: =IF($A23>$B$11,"",E22*(1+PARÁMETROS!$B$7)+PARÁMETROS!$B$11*12*(1+PARÁMETROS!$B$14)^(A23-1)) -> 0 | F23: =IF($A23>$B$11,"",F22*(1+PARÁMETROS!$B$8)+PARÁMETROS!$B$12*12*(1+PARÁMETROS!$B$14)^(A23-1)) -> 0 | G23: =IF($A23>$B$11,"",D23+E23+F23) -> 173951.67 | H23: =IF($A23>$B$11,"",G23/(1+PARÁMETROS!$B$10)^A23) -> 142770.24 | I23: =IF($A23>$B$11,"",$G$15) -> 67957.06 | J23: =IF($A23>$B$11,"",J22+(PARÁMETROS!$B$13+PARÁMETROS!$B$11+PARÁMETROS!$B$12)*12*(1+PARÁMETROS!$B$14)^(A23-1)) -> 100612.31 | K23: =IF($A23>$B$11,"",G23-I23-J23) -> 5382.303 | L23: =IF($A23>$B$11,"",PARÁMETROS!$B$15*12*(1+PARÁMETROS!$B$10)^A23) -> 24132.407 | M23: =IF($A23>$B$11,"",G23*PARÁMETROS!$B$16/L23) -> 0.28832876 | N23: =IF($A23>$B$11,"",N22*(1+DECISIONES!$B$9)+(PARÁMETROS!$B$11+DECISIONES!$B$6+IF(DECISIONES!$B$8="Sí",DECISIONES!$B$7,0))*12*(1+PARÁMETROS!$B$14)^(A23-1)-IF(A23=DECISIONES!$B$14,DECISIONES!$B$15,0)-IF(AND(A23>DECISIONES!$B$14,A23<=DECISIONES!$B$14+DECISIONES!$B$18),DECISIONES!$B$17*12,0)+IF(A23>DECISIONES!$B$14,DECISIONES!$B$19*12*(1+PARÁMETROS!$B$10)^A23,0)) -> -70257.23 | O23: =IF($A23>$B$11,"",V23+N23+F23) -> 103694.44 | P23: =IF($A23>$B$11,"",(PARÁMETROS!$B$15-DECISIONES!$B$7)*12*(1+PARÁMETROS!$B$10)^A23-IF(A23>DECISIONES!$B$14,DECISIONES!$B$19*12*(1+PARÁMETROS!$B$10)^A23,0)) -> 11704.697 | Q23: =IF($A23>$B$11,"",O23*PARÁMETROS!$B$16/P23) -> 0.35436865 | R23: =IF($A23>$B$11,"",SUMPRODUCT(INMUEBLES!$D$5:$D$9,(1+INMUEBLES!$G$5:$G$9)^A23)) -> 0 | S23: =IF($A23>$B$11,"",R23-VIVIENDA!$B$5*(1+PARÁMETROS!$B$19)^A23*VIVIENDA!$B$6+IF(AND(DECISIONES!$B$10="Sí",A23>=DECISIONES!$B$14),VIVIENDA!$B$5*(1+PARÁMETROS!$B$19)^A23-IF(A23-DECISIONES!$B$14>=DECISIONES!$B$18,0,MAX(0,FV(VIVIENDA!$B$11/12,(A23-DECISIONES!$B$14)*12,DECISIONES!$B$17,-DECISIONES!$B$16))),VIVIENDA!$B$5*(1+PARÁMETROS!$B$19)^A23*VIVIENDA!$B$6)) -> 142018.54 | T23: =IF($A23>$B$11,"",G23+R23) -> 173951.67 | U23: =IF($A23>$B$11,"",O23+S23) -> 245712.98 | V23: =IF($A23>$B$11,"",D23-DECISIONES!$B$5*(1+PARÁMETROS!$B$9)^A23) -> 173951.67
A24: 9 | B24: =IF($A24>$B$11,"",PARÁMETROS!$B$4+A24) -> 50 | C24: =IF($A24>$B$11,"",PARÁMETROS!$B$6+A24) -> 2035 | D24: =IF($A24>$B$11,"",D23*(1+PARÁMETROS!$B$9)+PARÁMETROS!$B$13*12*(1+PARÁMETROS!$B$14)^(A24-1)) -> 188725.49 | E24: =IF($A24>$B$11,"",E23*(1+PARÁMETROS!$B$7)+PARÁMETROS!$B$11*12*(1+PARÁMETROS!$B$14)^(A24-1)) -> 0 | F24: =IF($A24>$B$11,"",F23*(1+PARÁMETROS!$B$8)+PARÁMETROS!$B$12*12*(1+PARÁMETROS!$B$14)^(A24-1)) -> 0 | G24: =IF($A24>$B$11,"",D24+E24+F24) -> 188725.49 | H24: =IF($A24>$B$11,"",G24/(1+PARÁMETROS!$B$10)^A24) -> 151117.85 | I24: =IF($A24>$B$11,"",$G$15) -> 67957.06 | J24: =IF($A24>$B$11,"",J23+(PARÁMETROS!$B$13+PARÁMETROS!$B$11+PARÁMETROS!$B$12)*12*(1+PARÁMETROS!$B$14)^(A24-1)) -> 114346.88 | K24: =IF($A24>$B$11,"",G24-I24-J24) -> 6421.5531 | L24: =IF($A24>$B$11,"",PARÁMETROS!$B$15*12*(1+PARÁMETROS!$B$10)^A24) -> 24735.717 | M24: =IF($A24>$B$11,"",G24*PARÁMETROS!$B$16/L24) -> 0.30518701 | N24: =IF($A24>$B$11,"",N23*(1+DECISIONES!$B$9)+(PARÁMETROS!$B$11+DECISIONES!$B$6+IF(DECISIONES!$B$8="Sí",DECISIONES!$B$7,0))*12*(1+PARÁMETROS!$B$14)^(A24-1)-IF(A24=DECISIONES!$B$14,DECISIONES!$B$15,0)-IF(AND(A24>DECISIONES!$B$14,A24<=DECISIONES!$B$14+DECISIONES!$B$18),DECISIONES!$B$17*12,0)+IF(A24>DECISIONES!$B$14,DECISIONES!$B$19*12*(1+PARÁMETROS!$B$10)^A24,0)) -> -71224.573 | O24: =IF($A24>$B$11,"",V24+N24+F24) -> 117500.92 | P24: =IF($A24>$B$11,"",(PARÁMETROS!$B$15-DECISIONES!$B$7)*12*(1+PARÁMETROS!$B$10)^A24-IF(A24>DECISIONES!$B$14,DECISIONES!$B$19*12*(1+PARÁMETROS!$B$10)^A24,0)) -> 11997.315 | Q24: =IF($A24>$B$11,"",O24*PARÁMETROS!$B$16/P24) -> 0.39175739 | R24: =IF($A24>$B$11,"",SUMPRODUCT(INMUEBLES!$D$5:$D$9,(1+INMUEBLES!$G$5:$G$9)^A24)) -> 0 | S24: =IF($A24>$B$11,"",R24-VIVIENDA!$B$5*(1+PARÁMETROS!$B$19)^A24*VIVIENDA!$B$6+IF(AND(DECISIONES!$B$10="Sí",A24>=DECISIONES!$B$14),VIVIENDA!$B$5*(1+PARÁMETROS!$B$19)^A24-IF(A24-DECISIONES!$B$14>=DECISIONES!$B$18,0,MAX(0,FV(VIVIENDA!$B$11/12,(A24-DECISIONES!$B$14)*12,DECISIONES!$B$17,-DECISIONES!$B$16))),VIVIENDA!$B$5*(1+PARÁMETROS!$B$19)^A24*VIVIENDA!$B$6)) -> 156692.12 | T24: =IF($A24>$B$11,"",G24+R24) -> 188725.49 | U24: =IF($A24>$B$11,"",O24+S24) -> 274193.04 | V24: =IF($A24>$B$11,"",D24-DECISIONES!$B$5*(1+PARÁMETROS!$B$9)^A24) -> 188725.49
A25: 10 | B25: =IF($A25>$B$11,"",PARÁMETROS!$B$4+A25) -> 51 | C25: =IF($A25>$B$11,"",PARÁMETROS!$B$6+A25) -> 2036 | D25: =IF($A25>$B$11,"",D24*(1+PARÁMETROS!$B$9)+PARÁMETROS!$B$13*12*(1+PARÁMETROS!$B$14)^(A25-1)) -> 203862.26 | E25: =IF($A25>$B$11,"",E24*(1+PARÁMETROS!$B$7)+PARÁMETROS!$B$11*12*(1+PARÁMETROS!$B$14)^(A25-1)) -> 0 | F25: =IF($A25>$B$11,"",F24*(1+PARÁMETROS!$B$8)+PARÁMETROS!$B$12*12*(1+PARÁMETROS!$B$14)^(A25-1)) -> 0 | G25: =IF($A25>$B$11,"",D25+E25+F25) -> 203862.26 | H25: =IF($A25>$B$11,"",G25/(1+PARÁMETROS!$B$10)^A25) -> 159256.87 | I25: =IF($A25>$B$11,"",$G$15) -> 67957.06 | J25: =IF($A25>$B$11,"",J24+(PARÁMETROS!$B$13+PARÁMETROS!$B$11+PARÁMETROS!$B$12)*12*(1+PARÁMETROS!$B$14)^(A25-1)) -> 128356.13 | K25: =IF($A25>$B$11,"",G25-I25-J25) -> 7549.0673 | L25: =IF($A25>$B$11,"",PARÁMETROS!$B$15*12*(1+PARÁMETROS!$B$10)^A25) -> 25354.11 | M25: =IF($A25>$B$11,"",G25*PARÁMETROS!$B$16/L25) -> 0.32162401 | N25: =IF($A25>$B$11,"",N24*(1+DECISIONES!$B$9)+(PARÁMETROS!$B$11+DECISIONES!$B$6+IF(DECISIONES!$B$8="Sí",DECISIONES!$B$7,0))*12*(1+PARÁMETROS!$B$14)^(A25-1)-IF(A25=DECISIONES!$B$14,DECISIONES!$B$15,0)-IF(AND(A25>DECISIONES!$B$14,A25<=DECISIONES!$B$14+DECISIONES!$B$18),DECISIONES!$B$17*12,0)+IF(A25>DECISIONES!$B$14,DECISIONES!$B$19*12*(1+PARÁMETROS!$B$10)^A25,0)) -> -71921.823 | O25: =IF($A25>$B$11,"",V25+N25+F25) -> 131940.44 | P25: =IF($A25>$B$11,"",(PARÁMETROS!$B$15-DECISIONES!$B$7)*12*(1+PARÁMETROS!$B$10)^A25-IF(A25>DECISIONES!$B$14,DECISIONES!$B$19*12*(1+PARÁMETROS!$B$10)^A25,0)) -> 12297.247 | Q25: =IF($A25>$B$11,"",O25*PARÁMETROS!$B$16/P25) -> 0.42917064 | R25: =IF($A25>$B$11,"",SUMPRODUCT(INMUEBLES!$D$5:$D$9,(1+INMUEBLES!$G$5:$G$9)^A25)) -> 0 | S25: =IF($A25>$B$11,"",R25-VIVIENDA!$B$5*(1+PARÁMETROS!$B$19)^A25*VIVIENDA!$B$6+IF(AND(DECISIONES!$B$10="Sí",A25>=DECISIONES!$B$14),VIVIENDA!$B$5*(1+PARÁMETROS!$B$19)^A25-IF(A25-DECISIONES!$B$14>=DECISIONES!$B$18,0,MAX(0,FV(VIVIENDA!$B$11/12,(A25-DECISIONES!$B$14)*12,DECISIONES!$B$17,-DECISIONES!$B$16))),VIVIENDA!$B$5*(1+PARÁMETROS!$B$19)^A25*VIVIENDA!$B$6)) -> 171802.05 | T25: =IF($A25>$B$11,"",G25+R25) -> 203862.26 | U25: =IF($A25>$B$11,"",O25+S25) -> 303742.49 | V25: =IF($A25>$B$11,"",D25-DECISIONES!$B$5*(1+PARÁMETROS!$B$9)^A25) -> 203862.26
A26: 11 | B26: =IF($A26>$B$11,"",PARÁMETROS!$B$4+A26) -> 52 | C26: =IF($A26>$B$11,"",PARÁMETROS!$B$6+A26) -> 2037 | D26: =IF($A26>$B$11,"",D25*(1+PARÁMETROS!$B$9)+PARÁMETROS!$B$13*12*(1+PARÁMETROS!$B$14)^(A26-1)) -> 219369.65 | E26: =IF($A26>$B$11,"",E25*(1+PARÁMETROS!$B$7)+PARÁMETROS!$B$11*12*(1+PARÁMETROS!$B$14)^(A26-1)) -> 0 | F26: =IF($A26>$B$11,"",F25*(1+PARÁMETROS!$B$8)+PARÁMETROS!$B$12*12*(1+PARÁMETROS!$B$14)^(A26-1)) -> 0 | G26: =IF($A26>$B$11,"",D26+E26+F26) -> 219369.65 | H26: =IF($A26>$B$11,"",G26/(1+PARÁMETROS!$B$10)^A26) -> 167191.43 | I26: =IF($A26>$B$11,"",$G$15) -> 67957.06 | J26: =IF($A26>$B$11,"",J25+(PARÁMETROS!$B$13+PARÁMETROS!$B$11+PARÁMETROS!$B$12)*12*(1+PARÁMETROS!$B$14)^(A26-1)) -> 142645.58 | K26: =IF($A26>$B$11,"",G26-I26-J26) -> 8767.014 | L26: =IF($A26>$B$11,"",PARÁMETROS!$B$15*12*(1+PARÁMETROS!$B$10)^A26) -> 25987.962 | M26: =IF($A26>$B$11,"",G26*PARÁMETROS!$B$16/L26) -> 0.33764809 | N26: =IF($A26>$B$11,"",N25*(1+DECISIONES!$B$9)+(PARÁMETROS!$B$11+DECISIONES!$B$6+IF(DECISIONES!$B$8="Sí",DECISIONES!$B$7,0))*12*(1+PARÁMETROS!$B$14)^(A26-1)-IF(A26=DECISIONES!$B$14,DECISIONES!$B$15,0)-IF(AND(A26>DECISIONES!$B$14,A26<=DECISIONES!$B$14+DECISIONES!$B$18),DECISIONES!$B$17*12,0)+IF(A26>DECISIONES!$B$14,DECISIONES!$B$19*12*(1+PARÁMETROS!$B$10)^A26,0)) -> -72327.514 | O26: =IF($A26>$B$11,"",V26+N26+F26) -> 147042.14 | P26: =IF($A26>$B$11,"",(PARÁMETROS!$B$15-DECISIONES!$B$7)*12*(1+PARÁMETROS!$B$10)^A26-IF(A26>DECISIONES!$B$14,DECISIONES!$B$19*12*(1+PARÁMETROS!$B$10)^A26,0)) -> 12604.679 | Q26: =IF($A26>$B$11,"",O26*PARÁMETROS!$B$16/P26) -> 0.46662717 | R26: =IF($A26>$B$11,"",SUMPRODUCT(INMUEBLES!$D$5:$D$9,(1+INMUEBLES!$G$5:$G$9)^A26)) -> 0 | S26: =IF($A26>$B$11,"",R26-VIVIENDA!$B$5*(1+PARÁMETROS!$B$19)^A26*VIVIENDA!$B$6+IF(AND(DECISIONES!$B$10="Sí",A26>=DECISIONES!$B$14),VIVIENDA!$B$5*(1+PARÁMETROS!$B$19)^A26-IF(A26-DECISIONES!$B$14>=DECISIONES!$B$18,0,MAX(0,FV(VIVIENDA!$B$11/12,(A26-DECISIONES!$B$14)*12,DECISIONES!$B$17,-DECISIONES!$B$16))),VIVIENDA!$B$5*(1+PARÁMETROS!$B$19)^A26*VIVIENDA!$B$6)) -> 187361.3 | T26: =IF($A26>$B$11,"",G26+R26) -> 219369.65 | U26: =IF($A26>$B$11,"",O26+S26) -> 334403.44 | V26: =IF($A26>$B$11,"",D26-DECISIONES!$B$5*(1+PARÁMETROS!$B$9)^A26) -> 219369.65
A27: 12 | B27: =IF($A27>$B$11,"",PARÁMETROS!$B$4+A27) -> 53 | C27: =IF($A27>$B$11,"",PARÁMETROS!$B$6+A27) -> 2038 | D27: =IF($A27>$B$11,"",D26*(1+PARÁMETROS!$B$9)+PARÁMETROS!$B$13*12*(1+PARÁMETROS!$B$14)^(A27-1)) -> 235255.48 | E27: =IF($A27>$B$11,"",E26*(1+PARÁMETROS!$B$7)+PARÁMETROS!$B$11*12*(1+PARÁMETROS!$B$14)^(A27-1)) -> 0 | F27: =IF($A27>$B$11,"",F26*(1+PARÁMETROS!$B$8)+PARÁMETROS!$B$12*12*(1+PARÁMETROS!$B$14)^(A27-1)) -> 0 | G27: =IF($A27>$B$11,"",D27+E27+F27) -> 235255.48 | H27: =IF($A27>$B$11,"",G27/(1+PARÁMETROS!$B$10)^A27) -> 174925.59 | I27: =IF($A27>$B$11,"",$G$15) -> 67957.06 | J27: =IF($A27>$B$11,"",J26+(PARÁMETROS!$B$13+PARÁMETROS!$B$11+PARÁMETROS!$B$12)*12*(1+PARÁMETROS!$B$14)^(A27-1)) -> 157220.81 | K27: =IF($A27>$B$11,"",G27-I27-J27) -> 10077.607 | L27: =IF($A27>$B$11,"",PARÁMETROS!$B$15*12*(1+PARÁMETROS!$B$10)^A27) -> 26637.662 | M27: =IF($A27>$B$11,"",G27*PARÁMETROS!$B$16/L27) -> 0.35326746 | N27: =IF($A27>$B$11,"",N26*(1+DECISIONES!$B$9)+(PARÁMETROS!$B$11+DECISIONES!$B$6+IF(DECISIONES!$B$8="Sí",DECISIONES!$B$7,0))*12*(1+PARÁMETROS!$B$14)^(A27-1)-IF(A27=DECISIONES!$B$14,DECISIONES!$B$15,0)-IF(AND(A27>DECISIONES!$B$14,A27<=DECISIONES!$B$14+DECISIONES!$B$18),DECISIONES!$B$17*12,0)+IF(A27>DECISIONES!$B$14,DECISIONES!$B$19*12*(1+PARÁMETROS!$B$10)^A27,0)) -> -72418.907 | O27: =IF($A27>$B$11,"",V27+N27+F27) -> 162836.57 | P27: =IF($A27>$B$11,"",(PARÁMETROS!$B$15-DECISIONES!$B$7)*12*(1+PARÁMETROS!$B$10)^A27-IF(A27>DECISIONES!$B$14,DECISIONES!$B$19*12*(1+PARÁMETROS!$B$10)^A27,0)) -> 12919.796 | Q27: =IF($A27>$B$11,"",O27*PARÁMETROS!$B$16/P27) -> 0.50414596 | R27: =IF($A27>$B$11,"",SUMPRODUCT(INMUEBLES!$D$5:$D$9,(1+INMUEBLES!$G$5:$G$9)^A27)) -> 0 | S27: =IF($A27>$B$11,"",R27-VIVIENDA!$B$5*(1+PARÁMETROS!$B$19)^A27*VIVIENDA!$B$6+IF(AND(DECISIONES!$B$10="Sí",A27>=DECISIONES!$B$14),VIVIENDA!$B$5*(1+PARÁMETROS!$B$19)^A27-IF(A27-DECISIONES!$B$14>=DECISIONES!$B$18,0,MAX(0,FV(VIVIENDA!$B$11/12,(A27-DECISIONES!$B$14)*12,DECISIONES!$B$17,-DECISIONES!$B$16))),VIVIENDA!$B$5*(1+PARÁMETROS!$B$19)^A27*VIVIENDA!$B$6)) -> 203383.24 | T27: =IF($A27>$B$11,"",G27+R27) -> 235255.48 | U27: =IF($A27>$B$11,"",O27+S27) -> 366219.81 | V27: =IF($A27>$B$11,"",D27-DECISIONES!$B$5*(1+PARÁMETROS!$B$9)^A27) -> 235255.48
... A45: 30 | B45: =IF($A45>$B$11,"",PARÁMETROS!$B$4+A45) | C45: =IF($A45>$B$11,"",PARÁMETROS!$B$6+A45) | D45: =IF($A45>$B$11,"",D44*(1+PARÁMETROS!$B$9)+PARÁMETROS!$B$13*12*(1+PARÁMETROS!$B$14)^(A45-1)) | E45: =IF($A45>$B$11,"",E44*(1+PARÁMETROS!$B$7)+PARÁMETROS!$B$11*12*(1+PARÁMETROS!$B$14)^(A45-1)) | F45: =IF($A45>$B$11,"",F44*(1+PARÁMETROS!$B$8)+PARÁMETROS!$B$12*12*(1+PARÁMETROS!$B$14)^(A45-1)) | G45: =IF($A45>$B$11,"",D45+E45+F45) | H45: =IF($A45>$B$11,"",G45/(1+PARÁMETROS!$B$10)^A45) | I45: =IF($A45>$B$11,"",$G$15) | J45: =IF($A45>$B$11,"",J44+(PARÁMETROS!$B$13+PARÁMETROS!$B$11+PARÁMETROS!$B$12)*12*(1+PARÁMETROS!$B$14)^(A45-1)) | K45: =IF($A45>$B$11,"",G45-I45-J45) | L45: =IF($A45>$B$11,"",PARÁMETROS!$B$15*12*(1+PARÁMETROS!$B$10)^A45) | M45: =IF($A45>$B$11,"",G45*PARÁMETROS!$B$16/L45) | N45: =IF($A45>$B$11,"",N44*(1+DECISIONES!$B$9)+(PARÁMETROS!$B$11+DECISIONES!$B$6+IF(DECISIONES!$B$8="Sí",DECISIONES!$B$7,0))*12*(1+PARÁMETROS!$B$14)^(A45-1)-IF(A45=DECISIONES!$B$14,DECISIONES!$B$15,0)-IF(AND(A45>DECISIONES!$B$14,A45<=DECISIONES!$B$14+DECISIONES!$B$18),DECISIONES!$B$17*12,0)+IF(A45>DECISIONES!$B$14,DECISIONES!$B$19*12*(1+PARÁMETROS!$B$10)^A45,0)) | O45: =IF($A45>$B$11,"",V45+N45+F45) | P45: =IF($A45>$B$11,"",(PARÁMETROS!$B$15-DECISIONES!$B$7)*12*(1+PARÁMETROS!$B$10)^A45-IF(A45>DECISIONES!$B$14,DECISIONES!$B$19*12*(1+PARÁMETROS!$B$10)^A45,0)) | Q45: =IF($A45>$B$11,"",O45*PARÁMETROS!$B$16/P45) | R45: =IF($A45>$B$11,"",SUMPRODUCT(INMUEBLES!$D$5:$D$9,(1+INMUEBLES!$G$5:$G$9)^A45)) | S45: =IF($A45>$B$11,"",R45-VIVIENDA!$B$5*(1+PARÁMETROS!$B$19)^A45*VIVIENDA!$B$6+IF(AND(DECISIONES!$B$10="Sí",A45>=DECISIONES!$B$14),VIVIENDA!$B$5*(1+PARÁMETROS!$B$19)^A45-IF(A45-DECISIONES!$B$14>=DECISIONES!$B$18,0,MAX(0,FV(VIVIENDA!$B$11/12,(A45-DECISIONES!$B$14)*12,DECISIONES!$B$17,-DECISIONES!$B$16))),VIVIENDA!$B$5*(1+PARÁMETROS!$B$19)^A45*VIVIENDA!$B$6)) | T45: =IF($A45>$B$11,"",G45+R45) | U45: =IF($A45>$B$11,"",O45+S45) | V45: =IF($A45>$B$11,"",D45-DECISIONES!$B$5*(1+PARÁMETROS!$B$9)^A45)
A48: FASE DE JUBILACIÓN (sacas cada año lo que no cubren la pensión y las rentas)
A49: k | B49: Edad | C49: Año | D49: Capital al empezar | E49: Gastos del año | F49: Pensión del año | G49: Rentas inmuebles | H49: Lo que sacas | I49: Capital al acabar | J49: Capital al empezar (con decisiones) | K49: Gastos (con decisiones) | L49: Cuota hipoteca pendiente | M49: Lo que sacas (con decisiones) | N49: Capital al acabar (con decisiones)
A50: 0 | B50: =PARÁMETROS!$B$5+A50 -> 67 | C50: =PARÁMETROS!$B$6+($B$11+A50) -> 2052 | D50: =INDEX($G$15:$G$45,$B$11+1) -> 502169.25 | E50: =PARÁMETROS!$B$15*12*(1+PARÁMETROS!$B$10)^($B$11+A50) -> 37638.318 | F50: =PARÁMETROS!$B$17*14*(1+PARÁMETROS!$B$10)^($B$11+A50) -> 33255.122 | G50: =INMUEBLES!$D$11*(1+PARÁMETROS!$B$10)^($B$11+A50) -> 0 | H50: =MAX(0,E50-F50-G50) -> 4383.1961 | I50: =MAX(0,D50*(1+PARÁMETROS!$B$20)-H50) -> 512851.13 | J50: =INDEX($O$15:$O$45,$B$11+1) -> 488086.56 | K50: =(PARÁMETROS!$B$15-DECISIONES!$B$7)*12*(1+PARÁMETROS!$B$10)^($B$11+A50)-IF(($B$11+A50)>DECISIONES!$B$14,DECISIONES!$B$19*12*(1+PARÁMETROS!$B$10)^($B$11+A50),0) -> 18255.333 | L50: =IF(AND(($B$11+A50)>=DECISIONES!$B$14,($B$11+A50)<DECISIONES!$B$14+DECISIONES!$B$18),DECISIONES!$B$17*12,0) -> 0 | M50: =MAX(0,K50+L50-F50-G50) -> 0 | N50: =MAX(0,J50*(1+PARÁMETROS!$B$20)-M50) -> 502729.15
A51: 1 | B51: =PARÁMETROS!$B$5+A51 -> 68 | C51: =PARÁMETROS!$B$6+($B$11+A51) -> 2053 | D51: =I50 -> 512851.13 | E51: =PARÁMETROS!$B$15*12*(1+PARÁMETROS!$B$10)^($B$11+A51) -> 38579.276 | F51: =PARÁMETROS!$B$17*14*(1+PARÁMETROS!$B$10)^($B$11+A51) -> 34086.5 | G51: =INMUEBLES!$D$11*(1+PARÁMETROS!$B$10)^($B$11+A51) -> 0 | H51: =MAX(0,E51-F51-G51) -> 4492.776 | I51: =MAX(0,D51*(1+PARÁMETROS!$B$20)-H51) -> 523743.88 | J51: =N50 -> 502729.15 | K51: =(PARÁMETROS!$B$15-DECISIONES!$B$7)*12*(1+PARÁMETROS!$B$10)^($B$11+A51)-IF(($B$11+A51)>DECISIONES!$B$14,DECISIONES!$B$19*12*(1+PARÁMETROS!$B$10)^($B$11+A51),0) -> 18711.716 | L51: =IF(AND(($B$11+A51)>=DECISIONES!$B$14,($B$11+A51)<DECISIONES!$B$14+DECISIONES!$B$18),DECISIONES!$B$17*12,0) -> 0 | M51: =MAX(0,K51+L51-F51-G51) -> 0 | N51: =MAX(0,J51*(1+PARÁMETROS!$B$20)-M51) -> 517811.03
A52: 2 | B52: =PARÁMETROS!$B$5+A52 -> 69 | C52: =PARÁMETROS!$B$6+($B$11+A52) -> 2054 | D52: =I51 -> 523743.88 | E52: =PARÁMETROS!$B$15*12*(1+PARÁMETROS!$B$10)^($B$11+A52) -> 39543.758 | F52: =PARÁMETROS!$B$17*14*(1+PARÁMETROS!$B$10)^($B$11+A52) -> 34938.663 | G52: =INMUEBLES!$D$11*(1+PARÁMETROS!$B$10)^($B$11+A52) -> 0 | H52: =MAX(0,E52-F52-G52) -> 4605.0954 | I52: =MAX(0,D52*(1+PARÁMETROS!$B$20)-H52) -> 534851.11 | J52: =N51 -> 517811.03 | K52: =(PARÁMETROS!$B$15-DECISIONES!$B$7)*12*(1+PARÁMETROS!$B$10)^($B$11+A52)-IF(($B$11+A52)>DECISIONES!$B$14,DECISIONES!$B$19*12*(1+PARÁMETROS!$B$10)^($B$11+A52),0) -> 19179.509 | L52: =IF(AND(($B$11+A52)>=DECISIONES!$B$14,($B$11+A52)<DECISIONES!$B$14+DECISIONES!$B$18),DECISIONES!$B$17*12,0) -> 0 | M52: =MAX(0,K52+L52-F52-G52) -> 0 | N52: =MAX(0,J52*(1+PARÁMETROS!$B$20)-M52) -> 533345.36
A53: 3 | B53: =PARÁMETROS!$B$5+A53 -> 70 | C53: =PARÁMETROS!$B$6+($B$11+A53) -> 2055 | D53: =I52 -> 534851.11 | E53: =PARÁMETROS!$B$15*12*(1+PARÁMETROS!$B$10)^($B$11+A53) -> 40532.352 | F53: =PARÁMETROS!$B$17*14*(1+PARÁMETROS!$B$10)^($B$11+A53) -> 35812.129 | G53: =INMUEBLES!$D$11*(1+PARÁMETROS!$B$10)^($B$11+A53) -> 0 | H53: =MAX(0,E53-F53-G53) -> 4720.2228 | I53: =MAX(0,D53*(1+PARÁMETROS!$B$20)-H53) -> 546176.42 | J53: =N52 -> 533345.36 | K53: =(PARÁMETROS!$B$15-DECISIONES!$B$7)*12*(1+PARÁMETROS!$B$10)^($B$11+A53)-IF(($B$11+A53)>DECISIONES!$B$14,DECISIONES!$B$19*12*(1+PARÁMETROS!$B$10)^($B$11+A53),0) -> 19658.997 | L53: =IF(AND(($B$11+A53)>=DECISIONES!$B$14,($B$11+A53)<DECISIONES!$B$14+DECISIONES!$B$18),DECISIONES!$B$17*12,0) -> 0 | M53: =MAX(0,K53+L53-F53-G53) -> 0 | N53: =MAX(0,J53*(1+PARÁMETROS!$B$20)-M53) -> 549345.72
A54: 4 | B54: =PARÁMETROS!$B$5+A54 -> 71 | C54: =PARÁMETROS!$B$6+($B$11+A54) -> 2056 | D54: =I53 -> 546176.42 | E54: =PARÁMETROS!$B$15*12*(1+PARÁMETROS!$B$10)^($B$11+A54) -> 41545.661 | F54: =PARÁMETROS!$B$17*14*(1+PARÁMETROS!$B$10)^($B$11+A54) -> 36707.433 | G54: =INMUEBLES!$D$11*(1+PARÁMETROS!$B$10)^($B$11+A54) -> 0 | H54: =MAX(0,E54-F54-G54) -> 4838.2284 | I54: =MAX(0,D54*(1+PARÁMETROS!$B$20)-H54) -> 557723.48 | J54: =N53 -> 549345.72 | K54: =(PARÁMETROS!$B$15-DECISIONES!$B$7)*12*(1+PARÁMETROS!$B$10)^($B$11+A54)-IF(($B$11+A54)>DECISIONES!$B$14,DECISIONES!$B$19*12*(1+PARÁMETROS!$B$10)^($B$11+A54),0) -> 20150.472 | L54: =IF(AND(($B$11+A54)>=DECISIONES!$B$14,($B$11+A54)<DECISIONES!$B$14+DECISIONES!$B$18),DECISIONES!$B$17*12,0) -> 0 | M54: =MAX(0,K54+L54-F54-G54) -> 0 | N54: =MAX(0,J54*(1+PARÁMETROS!$B$20)-M54) -> 565826.09
A55: 5 | B55: =PARÁMETROS!$B$5+A55 -> 72 | C55: =PARÁMETROS!$B$6+($B$11+A55) -> 2057 | D55: =I54 -> 557723.48 | E55: =PARÁMETROS!$B$15*12*(1+PARÁMETROS!$B$10)^($B$11+A55) -> 42584.303 | F55: =PARÁMETROS!$B$17*14*(1+PARÁMETROS!$B$10)^($B$11+A55) -> 37625.118 | G55: =INMUEBLES!$D$11*(1+PARÁMETROS!$B$10)^($B$11+A55) -> 0 | H55: =MAX(0,E55-F55-G55) -> 4959.1841 | I55: =MAX(0,D55*(1+PARÁMETROS!$B$20)-H55) -> 569496 | J55: =N54 -> 565826.09 | K55: =(PARÁMETROS!$B$15-DECISIONES!$B$7)*12*(1+PARÁMETROS!$B$10)^($B$11+A55)-IF(($B$11+A55)>DECISIONES!$B$14,DECISIONES!$B$19*12*(1+PARÁMETROS!$B$10)^($B$11+A55),0) -> 20654.234 | L55: =IF(AND(($B$11+A55)>=DECISIONES!$B$14,($B$11+A55)<DECISIONES!$B$14+DECISIONES!$B$18),DECISIONES!$B$17*12,0) -> 0 | M55: =MAX(0,K55+L55-F55-G55) -> 0 | N55: =MAX(0,J55*(1+PARÁMETROS!$B$20)-M55) -> 582800.87
A56: 6 | B56: =PARÁMETROS!$B$5+A56 -> 73 | C56: =PARÁMETROS!$B$6+($B$11+A56) -> 2058 | D56: =I55 -> 569496 | E56: =PARÁMETROS!$B$15*12*(1+PARÁMETROS!$B$10)^($B$11+A56) -> 43648.91 | F56: =PARÁMETROS!$B$17*14*(1+PARÁMETROS!$B$10)^($B$11+A56) -> 38565.746 | G56: =INMUEBLES!$D$11*(1+PARÁMETROS!$B$10)^($B$11+A56) -> 0 | H56: =MAX(0,E56-F56-G56) -> 5083.1637 | I56: =MAX(0,D56*(1+PARÁMETROS!$B$20)-H56) -> 581497.72 | J56: =N55 -> 582800.87 | K56: =(PARÁMETROS!$B$15-DECISIONES!$B$7)*12*(1+PARÁMETROS!$B$10)^($B$11+A56)-IF(($B$11+A56)>DECISIONES!$B$14,DECISIONES!$B$19*12*(1+PARÁMETROS!$B$10)^($B$11+A56),0) -> 21170.589 | L56: =IF(AND(($B$11+A56)>=DECISIONES!$B$14,($B$11+A56)<DECISIONES!$B$14+DECISIONES!$B$18),DECISIONES!$B$17*12,0) -> 0 | M56: =MAX(0,K56+L56-F56-G56) -> 0 | N56: =MAX(0,J56*(1+PARÁMETROS!$B$20)-M56) -> 600284.9
A57: 7 | B57: =PARÁMETROS!$B$5+A57 -> 74 | C57: =PARÁMETROS!$B$6+($B$11+A57) -> 2059 | D57: =I56 -> 581497.72 | E57: =PARÁMETROS!$B$15*12*(1+PARÁMETROS!$B$10)^($B$11+A57) -> 44740.133 | F57: =PARÁMETROS!$B$17*14*(1+PARÁMETROS!$B$10)^($B$11+A57) -> 39529.89 | G57: =INMUEBLES!$D$11*(1+PARÁMETROS!$B$10)^($B$11+A57) -> 0 | H57: =MAX(0,E57-F57-G57) -> 5210.2428 | I57: =MAX(0,D57*(1+PARÁMETROS!$B$20)-H57) -> 593732.41 | J57: =N56 -> 600284.9 | K57: =(PARÁMETROS!$B$15-DECISIONES!$B$7)*12*(1+PARÁMETROS!$B$10)^($B$11+A57)-IF(($B$11+A57)>DECISIONES!$B$14,DECISIONES!$B$19*12*(1+PARÁMETROS!$B$10)^($B$11+A57),0) -> 21699.854 | L57: =IF(AND(($B$11+A57)>=DECISIONES!$B$14,($B$11+A57)<DECISIONES!$B$14+DECISIONES!$B$18),DECISIONES!$B$17*12,0) -> 0 | M57: =MAX(0,K57+L57-F57-G57) -> 0 | N57: =MAX(0,J57*(1+PARÁMETROS!$B$20)-M57) -> 618293.45
A58: 8 | B58: =PARÁMETROS!$B$5+A58 -> 75 | C58: =PARÁMETROS!$B$6+($B$11+A58) -> 2060 | D58: =I57 -> 593732.41 | E58: =PARÁMETROS!$B$15*12*(1+PARÁMETROS!$B$10)^($B$11+A58) -> 45858.636 | F58: =PARÁMETROS!$B$17*14*(1+PARÁMETROS!$B$10)^($B$11+A58) -> 40518.137 | G58: =INMUEBLES!$D$11*(1+PARÁMETROS!$B$10)^($B$11+A58) -> 0 | H58: =MAX(0,E58-F58-G58) -> 5340.4989 | I58: =MAX(0,D58*(1+PARÁMETROS!$B$20)-H58) -> 606203.88 | J58: =N57 -> 618293.45 | K58: =(PARÁMETROS!$B$15-DECISIONES!$B$7)*12*(1+PARÁMETROS!$B$10)^($B$11+A58)-IF(($B$11+A58)>DECISIONES!$B$14,DECISIONES!$B$19*12*(1+PARÁMETROS!$B$10)^($B$11+A58),0) -> 22242.35 | L58: =IF(AND(($B$11+A58)>=DECISIONES!$B$14,($B$11+A58)<DECISIONES!$B$14+DECISIONES!$B$18),DECISIONES!$B$17*12,0) -> 0 | M58: =MAX(0,K58+L58-F58-G58) -> 0 | N58: =MAX(0,J58*(1+PARÁMETROS!$B$20)-M58) -> 636842.25
A59: 9 | B59: =PARÁMETROS!$B$5+A59 -> 76 | C59: =PARÁMETROS!$B$6+($B$11+A59) -> 2061 | D59: =I58 -> 606203.88 | E59: =PARÁMETROS!$B$15*12*(1+PARÁMETROS!$B$10)^($B$11+A59) -> 47005.102 | F59: =PARÁMETROS!$B$17*14*(1+PARÁMETROS!$B$10)^($B$11+A59) -> 41531.091 | G59: =INMUEBLES!$D$11*(1+PARÁMETROS!$B$10)^($B$11+A59) -> 0 | H59: =MAX(0,E59-F59-G59) -> 5474.0114 | I59: =MAX(0,D59*(1+PARÁMETROS!$B$20)-H59) -> 618915.98 | J59: =N58 -> 636842.25 | K59: =(PARÁMETROS!$B$15-DECISIONES!$B$7)*12*(1+PARÁMETROS!$B$10)^($B$11+A59)-IF(($B$11+A59)>DECISIONES!$B$14,DECISIONES!$B$19*12*(1+PARÁMETROS!$B$10)^($B$11+A59),0) -> 22798.409 | L59: =IF(AND(($B$11+A59)>=DECISIONES!$B$14,($B$11+A59)<DECISIONES!$B$14+DECISIONES!$B$18),DECISIONES!$B$17*12,0) -> 0 | M59: =MAX(0,K59+L59-F59-G59) -> 0 | N59: =MAX(0,J59*(1+PARÁMETROS!$B$20)-M59) -> 655947.52
A60: 10 | B60: =PARÁMETROS!$B$5+A60 -> 77 | C60: =PARÁMETROS!$B$6+($B$11+A60) -> 2062 | D60: =I59 -> 618915.98 | E60: =PARÁMETROS!$B$15*12*(1+PARÁMETROS!$B$10)^($B$11+A60) -> 48180.23 | F60: =PARÁMETROS!$B$17*14*(1+PARÁMETROS!$B$10)^($B$11+A60) -> 42569.368 | G60: =INMUEBLES!$D$11*(1+PARÁMETROS!$B$10)^($B$11+A60) -> 0 | H60: =MAX(0,E60-F60-G60) -> 5610.8616 | I60: =MAX(0,D60*(1+PARÁMETROS!$B$20)-H60) -> 631872.6 | J60: =N59 -> 655947.52 | K60: =(PARÁMETROS!$B$15-DECISIONES!$B$7)*12*(1+PARÁMETROS!$B$10)^($B$11+A60)-IF(($B$11+A60)>DECISIONES!$B$14,DECISIONES!$B$19*12*(1+PARÁMETROS!$B$10)^($B$11+A60),0) -> 23368.369 | L60: =IF(AND(($B$11+A60)>=DECISIONES!$B$14,($B$11+A60)<DECISIONES!$B$14+DECISIONES!$B$18),DECISIONES!$B$17*12,0) -> 0 | M60: =MAX(0,K60+L60-F60-G60) -> 0 | N60: =MAX(0,J60*(1+PARÁMETROS!$B$20)-M60) -> 675625.94
A61: 11 | B61: =PARÁMETROS!$B$5+A61 -> 78 | C61: =PARÁMETROS!$B$6+($B$11+A61) -> 2063 | D61: =I60 -> 631872.6 | E61: =PARÁMETROS!$B$15*12*(1+PARÁMETROS!$B$10)^($B$11+A61) -> 49384.735 | F61: =PARÁMETROS!$B$17*14*(1+PARÁMETROS!$B$10)^($B$11+A61) -> 43633.602 | G61: =INMUEBLES!$D$11*(1+PARÁMETROS!$B$10)^($B$11+A61) -> 0 | H61: =MAX(0,E61-F61-G61) -> 5751.1332 | I61: =MAX(0,D61*(1+PARÁMETROS!$B$20)-H61) -> 645077.65 | J61: =N60 -> 675625.94 | K61: =(PARÁMETROS!$B$15-DECISIONES!$B$7)*12*(1+PARÁMETROS!$B$10)^($B$11+A61)-IF(($B$11+A61)>DECISIONES!$B$14,DECISIONES!$B$19*12*(1+PARÁMETROS!$B$10)^($B$11+A61),0) -> 23952.579 | L61: =IF(AND(($B$11+A61)>=DECISIONES!$B$14,($B$11+A61)<DECISIONES!$B$14+DECISIONES!$B$18),DECISIONES!$B$17*12,0) -> 0 | M61: =MAX(0,K61+L61-F61-G61) -> 0 | N61: =MAX(0,J61*(1+PARÁMETROS!$B$20)-M61) -> 695894.72
A62: 12 | B62: =PARÁMETROS!$B$5+A62 -> 79 | C62: =PARÁMETROS!$B$6+($B$11+A62) -> 2064 | D62: =I61 -> 645077.65 | E62: =PARÁMETROS!$B$15*12*(1+PARÁMETROS!$B$10)^($B$11+A62) -> 50619.354 | F62: =PARÁMETROS!$B$17*14*(1+PARÁMETROS!$B$10)^($B$11+A62) -> 44724.442 | G62: =INMUEBLES!$D$11*(1+PARÁMETROS!$B$10)^($B$11+A62) -> 0 | H62: =MAX(0,E62-F62-G62) -> 5894.9115 | I62: =MAX(0,D62*(1+PARÁMETROS!$B$20)-H62) -> 658535.06 | J62: =N61 -> 695894.72 | K62: =(PARÁMETROS!$B$15-DECISIONES!$B$7)*12*(1+PARÁMETROS!$B$10)^($B$11+A62)-IF(($B$11+A62)>DECISIONES!$B$14,DECISIONES!$B$19*12*(1+PARÁMETROS!$B$10)^($B$11+A62),0) -> 24551.393 | L62: =IF(AND(($B$11+A62)>=DECISIONES!$B$14,($B$11+A62)<DECISIONES!$B$14+DECISIONES!$B$18),DECISIONES!$B$17*12,0) -> 0 | M62: =MAX(0,K62+L62-F62-G62) -> 0 | N62: =MAX(0,J62*(1+PARÁMETROS!$B$20)-M62) -> 716771.56
... A90: 40 | B90: =PARÁMETROS!$B$5+A90 -> 107 | C90: =PARÁMETROS!$B$6+($B$11+A90) -> 2092 | D90: =I89 -> 1132297.1 | E90: =PARÁMETROS!$B$15*12*(1+PARÁMETROS!$B$10)^($B$11+A90) -> 101061.29 | F90: =PARÁMETROS!$B$17*14*(1+PARÁMETROS!$B$10)^($B$11+A90) -> 89292.126 | G90: =INMUEBLES!$D$11*(1+PARÁMETROS!$B$10)^($B$11+A90) -> 0 | H90: =MAX(0,E90-F90-G90) -> 11769.161 | I90: =MAX(0,D90*(1+PARÁMETROS!$B$20)-H90) -> 1154496.8 | J90: =N89 -> 1592156.8 | K90: =(PARÁMETROS!$B$15-DECISIONES!$B$7)*12*(1+PARÁMETROS!$B$10)^($B$11+A90)-IF(($B$11+A90)>DECISIONES!$B$14,DECISIONES!$B$19*12*(1+PARÁMETROS!$B$10)^($B$11+A90),0) -> 49016.734 | L90: =IF(AND(($B$11+A90)>=DECISIONES!$B$14,($B$11+A90)<DECISIONES!$B$14+DECISIONES!$B$18),DECISIONES!$B$17*12,0) -> 0 | M90: =MAX(0,K90+L90-F90-G90) -> 0 | N90: =MAX(0,J90*(1+PARÁMETROS!$B$20)-M90) -> 1639921.5
A92: Te dura hasta los (sin decisiones) | B92: =PARÁMETROS!$B$5+COUNTIF($I$50:$I$90,">0") -> 108
A93: Te dura hasta los (con decisiones) | B93: =PARÁMETROS!$B$5+COUNTIF($N$50:$N$90,">0") -> 108

Sheet PANEL_DATOS
A1: Esta pestaña la lee el dashboard. No la toques: todo son fórmulas.
A3: ## KPI
A4: clave | B4: valor
A5: fecha_datos | B5: =PROYECCIÓN!$B$4 -> 46266
A6: patrimonio_liquido | B6: =PROYECCIÓN!$B$8 -> 67957.06
A7: inmuebles | B7: =PROYECCIÓN!$B$9 -> 0
A8: patrimonio_total | B8: =PROYECCIÓN!$B$10 -> 67957.06
A9: cuenta_1 | B9: =INDEX('MIS DATOS'!$B$6:$B$245,COUNT('MIS DATOS'!$A$6:$A$245)) -> 10501.16
A10: cuenta_2 | B10: =INDEX('MIS DATOS'!$C$6:$C$245,COUNT('MIS DATOS'!$A$6:$A$245)) -> 1449.9
A11: cuenta_3 | B11: =INDEX('MIS DATOS'!$D$6:$D$245,COUNT('MIS DATOS'!$A$6:$A$245)) -> 56006
A12: nombre_cuenta_1 | B12: CaixaBank
A13: nombre_cuenta_2 | B13: Openbank
A14: nombre_cuenta_3 | B14: ING
A15: libertad | B15: =PROYECCIÓN!$M$15 -> 0.13724131
A16: nivel | B16: ='MI FUTURO'!$A$5 -> 🛡️ Escudo
A17: siguiente_nivel | B17: ='MI FUTURO'!$A$7 -> Siguiente: 🧭 Brújula al 15%
A18: ingresos_medio | B18: =IFERROR(AVERAGEIFS('MIS DATOS'!$G$6:$G$245,'MIS DATOS'!$N$6:$N$245,1),0) -> 2627.4092
A19: gastos_medio | B19: =PARÁMETROS!$B$15 -> 1650.5492
A20: ahorro_medio | B20: =PARÁMETROS!$B$13 -> 976.86
A21: casa_media | B21: =CASA!$O$13 -> 969.39
A22: por_revisar | B22: =COUNTIFS(MOVIMIENTOS!$H$4:$H$20000,"Por revisar",MOVIMIENTOS!$B$4:$B$20000,">="&'MIS DATOS'!$A$6) -> 2
A23: edad | B23: =PARÁMETROS!$B$4 -> 41
A24: edad_jubilacion | B24: =PARÁMETROS!$B$5 -> 67
A25: pension_mes | B25: =PARÁMETROS!$B$17 -> 1250
A26: rentabilidad_efectivo | B26: =PARÁMETROS!$B$9 -> 0.0059743609
A27: patrimonio_jub | B27: =INDEX(PROYECCIÓN!$G$15:$G$45,PROYECCIÓN!$B$11+1) -> 502169.25
A28: patrimonio_jub_hoy | B28: =INDEX(PROYECCIÓN!$H$15:$H$45,PROYECCIÓN!$B$11+1) -> 264258.89
A29: ingreso_mes_jub | B29: ='MI FUTURO'!$I$11 -> 2339.1963
A30: dura_sin | B30: =PROYECCIÓN!$B$92 -> 108
A31: dura_con | B31: =PROYECCIÓN!$B$93 -> 108
A32: dura_max | B32: =PARÁMETROS!$B$5+40 -> 107
A33: patrimonio_jub_con | B33: =INDEX(PROYECCIÓN!$O$15:$O$45,PROYECCIÓN!$B$11+1) -> 488086.56
A34: libertad_jub | B34: =INDEX(PROYECCIÓN!$M$15:$M$45,PROYECCIÓN!$B$11+1) -> 0.53367873
A35: libertad_jub_con | B35: =INDEX(PROYECCIÓN!$Q$15:$Q$45,PROYECCIÓN!$B$11+1) -> 1.0694662
A36: viajes_aportacion | B36: =VIAJES!$B$4 -> 150
A37: viajes_anio | B37: =VIAJES!$B$7 -> 2026
A38: viajes_saldo_fin_anio | B38: =VIAJES!$B$10 -> 1900
A39: viajes_aviso | B39: =VIAJES!$B$12 -> ✅ Llega para todos los viajes apuntados
A40: decisiones_texto | B40: ='MI FUTURO'!$A$43 -> Decisiones: 0 € del efectivo a inversión, +0 €/mes a inversión, −0 €/mes de gastos, compra de la vivienda (Comprar ya). Comprar pasa dinero líquido a ladrillo: mira las dos filas.
A42: ## MESES
A43: mes | B43: cuenta_1 | C43: cuenta_2 | D43: cuenta_3 | E43: ingresos | F43: gastos | G43: ahorro | H43: completo | I43: g_Casa | J43: g_Comida | K43: g_Transporte | L43: g_Salud | M43: g_Seguros | N43: g_Personal | O43: g_Ocio | P43: g_Viajes | Q43: g_Efectivo | R43: g_Otros
A44: =IF('MIS DATOS'!A6="","",'MIS DATOS'!A6) -> 45931 | B44: =IF($A44="","",'MIS DATOS'!B6) -> 3446.26 | C44: =IF($A44="","",'MIS DATOS'!C6) -> 1080 | D44: =IF($A44="","",'MIS DATOS'!D6) -> 52332.69 | E44: =IF($A44="","",'MIS DATOS'!G6) -> 2182.69 | F44: =IF($A44="","",'MIS DATOS'!H6) -> 1569.48 | G44: =IF($A44="","",'MIS DATOS'!I6) -> 613.21 | H44: =IF($A44="","",'MIS DATOS'!N6) -> 1 | I44: =IF($A44="","",-SUMIFS(MOVIMIENTOS!$E$4:$E$20000,MOVIMIENTOS!$B$4:$B$20000,$A44,MOVIMIENTOS!$I$4:$I$20000,"Casa",MOVIMIENTOS!$H$4:$H$20000,"Gasto")) -> 963.8 | J44: =IF($A44="","",-SUMIFS(MOVIMIENTOS!$E$4:$E$20000,MOVIMIENTOS!$B$4:$B$20000,$A44,MOVIMIENTOS!$I$4:$I$20000,"Comida",MOVIMIENTOS!$H$4:$H$20000,"Gasto")+SUMIFS(FLEXIBLE!$B$4:$B$200,FLEXIBLE!$F$4:$F$200,$A44)) -> 293.52 | K44: =IF($A44="","",-SUMIFS(MOVIMIENTOS!$E$4:$E$20000,MOVIMIENTOS!$B$4:$B$20000,$A44,MOVIMIENTOS!$I$4:$I$20000,"Transporte",MOVIMIENTOS!$H$4:$H$20000,"Gasto")+SUMIFS(FLEXIBLE!$C$4:$C$200,FLEXIBLE!$F$4:$F$200,$A44)) -> 71.05 | L44: =IF($A44="","",-SUMIFS(MOVIMIENTOS!$E$4:$E$20000,MOVIMIENTOS!$B$4:$B$20000,$A44,MOVIMIENTOS!$I$4:$I$20000,"Salud",MOVIMIENTOS!$H$4:$H$20000,"Gasto")) -> 14.76 | M44: =IF($A44="","",-SUMIFS(MOVIMIENTOS!$E$4:$E$20000,MOVIMIENTOS!$B$4:$B$20000,$A44,MOVIMIENTOS!$I$4:$I$20000,"Seguros",MOVIMIENTOS!$H$4:$H$20000,"Gasto")) -> 0 | N44: =IF($A44="","",-SUMIFS(MOVIMIENTOS!$E$4:$E$20000,MOVIMIENTOS!$B$4:$B$20000,$A44,MOVIMIENTOS!$I$4:$I$20000,"Personal",MOVIMIENTOS!$H$4:$H$20000,"Gasto")) -> 60.1 | O44: =IF($A44="","",-SUMIFS(MOVIMIENTOS!$E$4:$E$20000,MOVIMIENTOS!$B$4:$B$20000,$A44,MOVIMIENTOS!$I$4:$I$20000,"Ocio",MOVIMIENTOS!$H$4:$H$20000,"Gasto")) -> 16.25 | P44: =IF($A44="","",-SUMIFS(MOVIMIENTOS!$E$4:$E$20000,MOVIMIENTOS!$B$4:$B$20000,$A44,MOVIMIENTOS!$I$4:$I$20000,"Viajes",MOVIMIENTOS!$H$4:$H$20000,"Gasto")) -> 150 | Q44: =IF($A44="","",-SUMIFS(MOVIMIENTOS!$E$4:$E$20000,MOVIMIENTOS!$B$4:$B$20000,$A44,MOVIMIENTOS!$I$4:$I$20000,"Efectivo",MOVIMIENTOS!$H$4:$H$20000,"Gasto")) -> 0 | R44: =IF($A44="","",-SUMIFS(MOVIMIENTOS!$E$4:$E$20000,MOVIMIENTOS!$B$4:$B$20000,$A44,MOVIMIENTOS!$I$4:$I$20000,"Otros",MOVIMIENTOS!$H$4:$H$20000,"Gasto")) -> 0
A45: =IF('MIS DATOS'!A7="","",'MIS DATOS'!A7) -> 45962 | B45: =IF($A45="","",'MIS DATOS'!B7) -> 3570.92 | C45: =IF($A45="","",'MIS DATOS'!C7) -> 1114.26 | D45: =IF($A45="","",'MIS DATOS'!D7) -> 52665.59 | E45: =IF($A45="","",'MIS DATOS'!G7) -> 2182.9 | F45: =IF($A45="","",'MIS DATOS'!H7) -> 1735.4 | G45: =IF($A45="","",'MIS DATOS'!I7) -> 447.5 | H45: =IF($A45="","",'MIS DATOS'!N7) -> 1 | I45: =IF($A45="","",-SUMIFS(MOVIMIENTOS!$E$4:$E$20000,MOVIMIENTOS!$B$4:$B$20000,$A45,MOVIMIENTOS!$I$4:$I$20000,"Casa",MOVIMIENTOS!$H$4:$H$20000,"Gasto")) -> 940.22 | J45: =IF($A45="","",-SUMIFS(MOVIMIENTOS!$E$4:$E$20000,MOVIMIENTOS!$B$4:$B$20000,$A45,MOVIMIENTOS!$I$4:$I$20000,"Comida",MOVIMIENTOS!$H$4:$H$20000,"Gasto")+SUMIFS(FLEXIBLE!$B$4:$B$200,FLEXIBLE!$F$4:$F$200,$A45)) -> 339.89 | K45: =IF($A45="","",-SUMIFS(MOVIMIENTOS!$E$4:$E$20000,MOVIMIENTOS!$B$4:$B$20000,$A45,MOVIMIENTOS!$I$4:$I$20000,"Transporte",MOVIMIENTOS!$H$4:$H$20000,"Gasto")+SUMIFS(FLEXIBLE!$C$4:$C$200,FLEXIBLE!$F$4:$F$200,$A45)) -> 64.06 | L45: =IF($A45="","",-SUMIFS(MOVIMIENTOS!$E$4:$E$20000,MOVIMIENTOS!$B$4:$B$20000,$A45,MOVIMIENTOS!$I$4:$I$20000,"Salud",MOVIMIENTOS!$H$4:$H$20000,"Gasto")) -> 22.02 | M45: =IF($A45="","",-SUMIFS(MOVIMIENTOS!$E$4:$E$20000,MOVIMIENTOS!$B$4:$B$20000,$A45,MOVIMIENTOS!$I$4:$I$20000,"Seguros",MOVIMIENTOS!$H$4:$H$20000,"Gasto")) -> 0 | N45: =IF($A45="","",-SUMIFS(MOVIMIENTOS!$E$4:$E$20000,MOVIMIENTOS!$B$4:$B$20000,$A45,MOVIMIENTOS!$I$4:$I$20000,"Personal",MOVIMIENTOS!$H$4:$H$20000,"Gasto")) -> 203.48 | O45: =IF($A45="","",-SUMIFS(MOVIMIENTOS!$E$4:$E$20000,MOVIMIENTOS!$B$4:$B$20000,$A45,MOVIMIENTOS!$I$4:$I$20000,"Ocio",MOVIMIENTOS!$H$4:$H$20000,"Gasto")) -> 15.73 | P45: =IF($A45="","",-SUMIFS(MOVIMIENTOS!$E$4:$E$20000,MOVIMIENTOS!$B$4:$B$20000,$A45,MOVIMIENTOS!$I$4:$I$20000,"Viajes",MOVIMIENTOS!$H$4:$H$20000,"Gasto")) -> 150 | Q45: =IF($A45="","",-SUMIFS(MOVIMIENTOS!$E$4:$E$20000,MOVIMIENTOS!$B$4:$B$20000,$A45,MOVIMIENTOS!$I$4:$I$20000,"Efectivo",MOVIMIENTOS!$H$4:$H$20000,"Gasto")) -> 0 | R45: =IF($A45="","",-SUMIFS(MOVIMIENTOS!$E$4:$E$20000,MOVIMIENTOS!$B$4:$B$20000,$A45,MOVIMIENTOS!$I$4:$I$20000,"Otros",MOVIMIENTOS!$H$4:$H$20000,"Gasto")) -> 0
A46: =IF('MIS DATOS'!A8="","",'MIS DATOS'!A8) -> 45992 | B46: =IF($A46="","",'MIS DATOS'!B8) -> 5931.77 | C46: =IF($A46="","",'MIS DATOS'!C8) -> 1104.2 | D46: =IF($A46="","",'MIS DATOS'!D8) -> 52998.69 | E46: =IF($A46="","",'MIS DATOS'!G8) -> 4333.1 | F46: =IF($A46="","",'MIS DATOS'!H8) -> 1599.67 | G46: =IF($A46="","",'MIS DATOS'!I8) -> 2733.43 | H46: =IF($A46="","",'MIS DATOS'!N8) -> 1 | I46: =IF($A46="","",-SUMIFS(MOVIMIENTOS!$E$4:$E$20000,MOVIMIENTOS!$B$4:$B$20000,$A46,MOVIMIENTOS!$I$4:$I$20000,"Casa",MOVIMIENTOS!$H$4:$H$20000,"Gasto")) -> 980.21 | J46: =IF($A46="","",-SUMIFS(MOVIMIENTOS!$E$4:$E$20000,MOVIMIENTOS!$B$4:$B$20000,$A46,MOVIMIENTOS!$I$4:$I$20000,"Comida",MOVIMIENTOS!$H$4:$H$20000,"Gasto")+SUMIFS(FLEXIBLE!$B$4:$B$200,FLEXIBLE!$F$4:$F$200,$A46)) -> 320.48 | K46: =IF($A46="","",-SUMIFS(MOVIMIENTOS!$E$4:$E$20000,MOVIMIENTOS!$B$4:$B$20000,$A46,MOVIMIENTOS!$I$4:$I$20000,"Transporte",MOVIMIENTOS!$H$4:$H$20000,"Gasto")+SUMIFS(FLEXIBLE!$C$4:$C$200,FLEXIBLE!$F$4:$F$200,$A46)) -> 61.07 | L46: =IF($A46="","",-SUMIFS(MOVIMIENTOS!$E$4:$E$20000,MOVIMIENTOS!$B$4:$B$20000,$A46,MOVIMIENTOS!$I$4:$I$20000,"Salud",MOVIMIENTOS!$H$4:$H$20000,"Gasto")) -> 26.87 | M46: =IF($A46="","",-SUMIFS(MOVIMIENTOS!$E$4:$E$20000,MOVIMIENTOS!$B$4:$B$20000,$A46,MOVIMIENTOS!$I$4:$I$20000,"Seguros",MOVIMIENTOS!$H$4:$H$20000,"Gasto")) -> 0 | N46: =IF($A46="","",-SUMIFS(MOVIMIENTOS!$E$4:$E$20000,MOVIMIENTOS!$B$4:$B$20000,$A46,MOVIMIENTOS!$I$4:$I$20000,"Personal",MOVIMIENTOS!$H$4:$H$20000,"Gasto")) -> 48.14 | O46: =IF($A46="","",-SUMIFS(MOVIMIENTOS!$E$4:$E$20000,MOVIMIENTOS!$B$4:$B$20000,$A46,MOVIMIENTOS!$I$4:$I$20000,"Ocio",MOVIMIENTOS!$H$4:$H$20000,"Gasto")) -> 12.9 | P46: =IF($A46="","",-SUMIFS(MOVIMIENTOS!$E$4:$E$20000,MOVIMIENTOS!$B$4:$B$20000,$A46,MOVIMIENTOS!$I$4:$I$20000,"Viajes",MOVIMIENTOS!$H$4:$H$20000,"Gasto")) -> 150 | Q46: =IF($A46="","",-SUMIFS(MOVIMIENTOS!$E$4:$E$20000,MOVIMIENTOS!$B$4:$B$20000,$A46,MOVIMIENTOS!$I$4:$I$20000,"Efectivo",MOVIMIENTOS!$H$4:$H$20000,"Gasto")) -> 0 | R46: =IF($A46="","",-SUMIFS(MOVIMIENTOS!$E$4:$E$20000,MOVIMIENTOS!$B$4:$B$20000,$A46,MOVIMIENTOS!$I$4:$I$20000,"Otros",MOVIMIENTOS!$H$4:$H$20000,"Gasto")) -> 0
A47: =IF('MIS DATOS'!A9="","",'MIS DATOS'!A9) -> 46023 | B47: =IF($A47="","",'MIS DATOS'!B9) -> 6101.39 | C47: =IF($A47="","",'MIS DATOS'!C9) -> 1143.68 | D47: =IF($A47="","",'MIS DATOS'!D9) -> 53332 | E47: =IF($A47="","",'MIS DATOS'!G9) -> 2183.31 | F47: =IF($A47="","",'MIS DATOS'!H9) -> 1714.98 | G47: =IF($A47="","",'MIS DATOS'!I9) -> 468.33 | H47: =IF($A47="","",'MIS DATOS'!N9) -> 1 | I47: =IF($A47="","",-SUMIFS(MOVIMIENTOS!$E$4:$E$20000,MOVIMIENTOS!$B$4:$B$20000,$A47,MOVIMIENTOS!$I$4:$I$20000,"Casa",MOVIMIENTOS!$H$4:$H$20000,"Gasto")) -> 953.44 | J47: =IF($A47="","",-SUMIFS(MOVIMIENTOS!$E$4:$E$20000,MOVIMIENTOS!$B$4:$B$20000,$A47,MOVIMIENTOS!$I$4:$I$20000,"Comida",MOVIMIENTOS!$H$4:$H$20000,"Gasto")+SUMIFS(FLEXIBLE!$B$4:$B$200,FLEXIBLE!$F$4:$F$200,$A47)) -> 431.23 | K47: =IF($A47="","",-SUMIFS(MOVIMIENTOS!$E$4:$E$20000,MOVIMIENTOS!$B$4:$B$20000,$A47,MOVIMIENTOS!$I$4:$I$20000,"Transporte",MOVIMIENTOS!$H$4:$H$20000,"Gasto")+SUMIFS(FLEXIBLE!$C$4:$C$200,FLEXIBLE!$F$4:$F$200,$A47)) -> 61.61 | L47: =IF($A47="","",-SUMIFS(MOVIMIENTOS!$E$4:$E$20000,MOVIMIENTOS!$B$4:$B$20000,$A47,MOVIMIENTOS!$I$4:$I$20000,"Salud",MOVIMIENTOS!$H$4:$H$20000,"Gasto")) -> 24.69 | M47: =IF($A47="","",-SUMIFS(MOVIMIENTOS!$E$4:$E$20000,MOVIMIENTOS!$B$4:$B$20000,$A47,MOVIMIENTOS!$I$4:$I$20000,"Seguros",MOVIMIENTOS!$H$4:$H$20000,"Gasto")) -> 0 | N47: =IF($A47="","",-SUMIFS(MOVIMIENTOS!$E$4:$E$20000,MOVIMIENTOS!$B$4:$B$20000,$A47,MOVIMIENTOS!$I$4:$I$20000,"Personal",MOVIMIENTOS!$H$4:$H$20000,"Gasto")) -> 78.83 | O47: =IF($A47="","",-SUMIFS(MOVIMIENTOS!$E$4:$E$20000,MOVIMIENTOS!$B$4:$B$20000,$A47,MOVIMIENTOS!$I$4:$I$20000,"Ocio",MOVIMIENTOS!$H$4:$H$20000,"Gasto")) -> 15.18 | P47: =IF($A47="","",-SUMIFS(MOVIMIENTOS!$E$4:$E$20000,MOVIMIENTOS!$B$4:$B$20000,$A47,MOVIMIENTOS!$I$4:$I$20000,"Viajes",MOVIMIENTOS!$H$4:$H$20000,"Gasto")) -> 150 | Q47: =IF($A47="","",-SUMIFS(MOVIMIENTOS!$E$4:$E$20000,MOVIMIENTOS!$B$4:$B$20000,$A47,MOVIMIENTOS!$I$4:$I$20000,"Efectivo",MOVIMIENTOS!$H$4:$H$20000,"Gasto")) -> 0 | R47: =IF($A47="","",-SUMIFS(MOVIMIENTOS!$E$4:$E$20000,MOVIMIENTOS!$B$4:$B$20000,$A47,MOVIMIENTOS!$I$4:$I$20000,"Otros",MOVIMIENTOS!$H$4:$H$20000,"Gasto")) -> 0
A48: =IF('MIS DATOS'!A10="","",'MIS DATOS'!A10) -> 46054 | B48: =IF($A48="","",'MIS DATOS'!B10) -> 6319.16 | C48: =IF($A48="","",'MIS DATOS'!C10) -> 1109.08 | D48: =IF($A48="","",'MIS DATOS'!D10) -> 53665.52 | E48: =IF($A48="","",'MIS DATOS'!G10) -> 2183.52 | F48: =IF($A48="","",'MIS DATOS'!H10) -> 1587.05 | G48: =IF($A48="","",'MIS DATOS'!I10) -> 596.47 | H48: =IF($A48="","",'MIS DATOS'!N10) -> 1 | I48: =IF($A48="","",-SUMIFS(MOVIMIENTOS!$E$4:$E$20000,MOVIMIENTOS!$B$4:$B$20000,$A48,MOVIMIENTOS!$I$4:$I$20000,"Casa",MOVIMIENTOS!$H$4:$H$20000,"Gasto")) -> 977.29 | J48: =IF($A48="","",-SUMIFS(MOVIMIENTOS!$E$4:$E$20000,MOVIMIENTOS!$B$4:$B$20000,$A48,MOVIMIENTOS!$I$4:$I$20000,"Comida",MOVIMIENTOS!$H$4:$H$20000,"Gasto")+SUMIFS(FLEXIBLE!$B$4:$B$200,FLEXIBLE!$F$4:$F$200,$A48)) -> 290.66 | K48: =IF($A48="","",-SUMIFS(MOVIMIENTOS!$E$4:$E$20000,MOVIMIENTOS!$B$4:$B$20000,$A48,MOVIMIENTOS!$I$4:$I$20000,"Transporte",MOVIMIENTOS!$H$4:$H$20000,"Gasto")+SUMIFS(FLEXIBLE!$C$4:$C$200,FLEXIBLE!$F$4:$F$200,$A48)) -> 74.58 | L48: =IF($A48="","",-SUMIFS(MOVIMIENTOS!$E$4:$E$20000,MOVIMIENTOS!$B$4:$B$20000,$A48,MOVIMIENTOS!$I$4:$I$20000,"Salud",MOVIMIENTOS!$H$4:$H$20000,"Gasto")) -> 24.95 | M48: =IF($A48="","",-SUMIFS(MOVIMIENTOS!$E$4:$E$20000,MOVIMIENTOS!$B$4:$B$20000,$A48,MOVIMIENTOS!$I$4:$I$20000,"Seguros",MOVIMIENTOS!$H$4:$H$20000,"Gasto")) -> 0 | N48: =IF($A48="","",-SUMIFS(MOVIMIENTOS!$E$4:$E$20000,MOVIMIENTOS!$B$4:$B$20000,$A48,MOVIMIENTOS!$I$4:$I$20000,"Personal",MOVIMIENTOS!$H$4:$H$20000,"Gasto")) -> 53.95 | O48: =IF($A48="","",-SUMIFS(MOVIMIENTOS!$E$4:$E$20000,MOVIMIENTOS!$B$4:$B$20000,$A48,MOVIMIENTOS!$I$4:$I$20000,"Ocio",MOVIMIENTOS!$H$4:$H$20000,"Gasto")) -> 15.62 | P48: =IF($A48="","",-SUMIFS(MOVIMIENTOS!$E$4:$E$20000,MOVIMIENTOS!$B$4:$B$20000,$A48,MOVIMIENTOS!$I$4:$I$20000,"Viajes",MOVIMIENTOS!$H$4:$H$20000,"Gasto")) -> 150 | Q48: =IF($A48="","",-SUMIFS(MOVIMIENTOS!$E$4:$E$20000,MOVIMIENTOS!$B$4:$B$20000,$A48,MOVIMIENTOS!$I$4:$I$20000,"Efectivo",MOVIMIENTOS!$H$4:$H$20000,"Gasto")) -> 0 | R48: =IF($A48="","",-SUMIFS(MOVIMIENTOS!$E$4:$E$20000,MOVIMIENTOS!$B$4:$B$20000,$A48,MOVIMIENTOS!$I$4:$I$20000,"Otros",MOVIMIENTOS!$H$4:$H$20000,"Gasto")) -> 0
A49: =IF('MIS DATOS'!A11="","",'MIS DATOS'!A11) -> 46082 | B49: =IF($A49="","",'MIS DATOS'!B11) -> 6481.69 | C49: =IF($A49="","",'MIS DATOS'!C11) -> 1154.26 | D49: =IF($A49="","",'MIS DATOS'!D11) -> 53999.25 | E49: =IF($A49="","",'MIS DATOS'!G11) -> 2183.73 | F49: =IF($A49="","",'MIS DATOS'!H11) -> 1605.51 | G49: =IF($A49="","",'MIS DATOS'!I11) -> 578.22 | H49: =IF($A49="","",'MIS DATOS'!N11) -> 1 | I49: =IF($A49="","",-SUMIFS(MOVIMIENTOS!$E$4:$E$20000,MOVIMIENTOS!$B$4:$B$20000,$A49,MOVIMIENTOS!$I$4:$I$20000,"Casa",MOVIMIENTOS!$H$4:$H$20000,"Gasto")) -> 1078.53 | J49: =IF($A49="","",-SUMIFS(MOVIMIENTOS!$E$4:$E$20000,MOVIMIENTOS!$B$4:$B$20000,$A49,MOVIMIENTOS!$I$4:$I$20000,"Comida",MOVIMIENTOS!$H$4:$H$20000,"Gasto")+SUMIFS(FLEXIBLE!$B$4:$B$200,FLEXIBLE!$F$4:$F$200,$A49)) -> 197.42 | K49: =IF($A49="","",-SUMIFS(MOVIMIENTOS!$E$4:$E$20000,MOVIMIENTOS!$B$4:$B$20000,$A49,MOVIMIENTOS!$I$4:$I$20000,"Transporte",MOVIMIENTOS!$H$4:$H$20000,"Gasto")+SUMIFS(FLEXIBLE!$C$4:$C$200,FLEXIBLE!$F$4:$F$200,$A49)) -> 74.23 | L49: =IF($A49="","",-SUMIFS(MOVIMIENTOS!$E$4:$E$20000,MOVIMIENTOS!$B$4:$B$20000,$A49,MOVIMIENTOS!$I$4:$I$20000,"Salud",MOVIMIENTOS!$H$4:$H$20000,"Gasto")) -> 13.5 | M49: =IF($A49="","",-SUMIFS(MOVIMIENTOS!$E$4:$E$20000,MOVIMIENTOS!$B$4:$B$20000,$A49,MOVIMIENTOS!$I$4:$I$20000,"Seguros",MOVIMIENTOS!$H$4:$H$20000,"Gasto")) -> 0 | N49: =IF($A49="","",-SUMIFS(MOVIMIENTOS!$E$4:$E$20000,MOVIMIENTOS!$B$4:$B$20000,$A49,MOVIMIENTOS!$I$4:$I$20000,"Personal",MOVIMIENTOS!$H$4:$H$20000,"Gasto")) -> 77.18 | O49: =IF($A49="","",-SUMIFS(MOVIMIENTOS!$E$4:$E$20000,MOVIMIENTOS!$B$4:$B$20000,$A49,MOVIMIENTOS!$I$4:$I$20000,"Ocio",MOVIMIENTOS!$H$4:$H$20000,"Gasto")) -> 14.65 | P49: =IF($A49="","",-SUMIFS(MOVIMIENTOS!$E$4:$E$20000,MOVIMIENTOS!$B$4:$B$20000,$A49,MOVIMIENTOS!$I$4:$I$20000,"Viajes",MOVIMIENTOS!$H$4:$H$20000,"Gasto")) -> 150 | Q49: =IF($A49="","",-SUMIFS(MOVIMIENTOS!$E$4:$E$20000,MOVIMIENTOS!$B$4:$B$20000,$A49,MOVIMIENTOS!$I$4:$I$20000,"Efectivo",MOVIMIENTOS!$H$4:$H$20000,"Gasto")) -> 0 | R49: =IF($A49="","",-SUMIFS(MOVIMIENTOS!$E$4:$E$20000,MOVIMIENTOS!$B$4:$B$20000,$A49,MOVIMIENTOS!$I$4:$I$20000,"Otros",MOVIMIENTOS!$H$4:$H$20000,"Gasto")) -> 0
A50: =IF('MIS DATOS'!A12="","",'MIS DATOS'!A12) -> 46113 | B50: =IF($A50="","",'MIS DATOS'!B12) -> 6640.62 | C50: =IF($A50="","",'MIS DATOS'!C12) -> 1236.22 | D50: =IF($A50="","",'MIS DATOS'!D12) -> 54333.19 | E50: =IF($A50="","",'MIS DATOS'!G12) -> 2183.94 | F50: =IF($A50="","",'MIS DATOS'!H12) -> 1640.04 | G50: =IF($A50="","",'MIS DATOS'!I12) -> 543.9 | H50: =IF($A50="","",'MIS DATOS'!N12) -> 1 | I50: =IF($A50="","",-SUMIFS(MOVIMIENTOS!$E$4:$E$20000,MOVIMIENTOS!$B$4:$B$20000,$A50,MOVIMIENTOS!$I$4:$I$20000,"Casa",MOVIMIENTOS!$H$4:$H$20000,"Gasto")) -> 960.07 | J50: =IF($A50="","",-SUMIFS(MOVIMIENTOS!$E$4:$E$20000,MOVIMIENTOS!$B$4:$B$20000,$A50,MOVIMIENTOS!$I$4:$I$20000,"Comida",MOVIMIENTOS!$H$4:$H$20000,"Gasto")+SUMIFS(FLEXIBLE!$B$4:$B$200,FLEXIBLE!$F$4:$F$200,$A50)) -> 299.25 | K50: =IF($A50="","",-SUMIFS(MOVIMIENTOS!$E$4:$E$20000,MOVIMIENTOS!$B$4:$B$20000,$A50,MOVIMIENTOS!$I$4:$I$20000,"Transporte",MOVIMIENTOS!$H$4:$H$20000,"Gasto")+SUMIFS(FLEXIBLE!$C$4:$C$200,FLEXIBLE!$F$4:$F$200,$A50)) -> 60.23 | L50: =IF($A50="","",-SUMIFS(MOVIMIENTOS!$E$4:$E$20000,MOVIMIENTOS!$B$4:$B$20000,$A50,MOVIMIENTOS!$I$4:$I$20000,"Salud",MOVIMIENTOS!$H$4:$H$20000,"Gasto")) -> 20.57 | M50: =IF($A50="","",-SUMIFS(MOVIMIENTOS!$E$4:$E$20000,MOVIMIENTOS!$B$4:$B$20000,$A50,MOVIMIENTOS!$I$4:$I$20000,"Seguros",MOVIMIENTOS!$H$4:$H$20000,"Gasto")) -> 0 | N50: =IF($A50="","",-SUMIFS(MOVIMIENTOS!$E$4:$E$20000,MOVIMIENTOS!$B$4:$B$20000,$A50,MOVIMIENTOS!$I$4:$I$20000,"Personal",MOVIMIENTOS!$H$4:$H$20000,"Gasto")) -> 132.17 | O50: =IF($A50="","",-SUMIFS(MOVIMIENTOS!$E$4:$E$20000,MOVIMIENTOS!$B$4:$B$20000,$A50,MOVIMIENTOS!$I$4:$I$20000,"Ocio",MOVIMIENTOS!$H$4:$H$20000,"Gasto")) -> 17.75 | P50: =IF($A50="","",-SUMIFS(MOVIMIENTOS!$E$4:$E$20000,MOVIMIENTOS!$B$4:$B$20000,$A50,MOVIMIENTOS!$I$4:$I$20000,"Viajes",MOVIMIENTOS!$H$4:$H$20000,"Gasto")) -> 150 | Q50: =IF($A50="","",-SUMIFS(MOVIMIENTOS!$E$4:$E$20000,MOVIMIENTOS!$B$4:$B$20000,$A50,MOVIMIENTOS!$I$4:$I$20000,"Efectivo",MOVIMIENTOS!$H$4:$H$20000,"Gasto")) -> 0 | R50: =IF($A50="","",-SUMIFS(MOVIMIENTOS!$E$4:$E$20000,MOVIMIENTOS!$B$4:$B$20000,$A50,MOVIMIENTOS!$I$4:$I$20000,"Otros",MOVIMIENTOS!$H$4:$H$20000,"Gasto")) -> 0
A51: =IF('MIS DATOS'!A13="","",'MIS DATOS'!A13) -> 46143 | B51: =IF($A51="","",'MIS DATOS'!B13) -> 6863.18 | C51: =IF($A51="","",'MIS DATOS'!C13) -> 1287.25 | D51: =IF($A51="","",'MIS DATOS'!D13) -> 54667.34 | E51: =IF($A51="","",'MIS DATOS'!G13) -> 2184.15 | F51: =IF($A51="","",'MIS DATOS'!H13) -> 1553.78 | G51: =IF($A51="","",'MIS DATOS'!I13) -> 630.37 | H51: =IF($A51="","",'MIS DATOS'!N13) -> 1 | I51: =IF($A51="","",-SUMIFS(MOVIMIENTOS!$E$4:$E$20000,MOVIMIENTOS!$B$4:$B$20000,$A51,MOVIMIENTOS!$I$4:$I$20000,"Casa",MOVIMIENTOS!$H$4:$H$20000,"Gasto")) -> 937.5 | J51: =IF($A51="","",-SUMIFS(MOVIMIENTOS!$E$4:$E$20000,MOVIMIENTOS!$B$4:$B$20000,$A51,MOVIMIENTOS!$I$4:$I$20000,"Comida",MOVIMIENTOS!$H$4:$H$20000,"Gasto")+SUMIFS(FLEXIBLE!$B$4:$B$200,FLEXIBLE!$F$4:$F$200,$A51)) -> 293.48 | K51: =IF($A51="","",-SUMIFS(MOVIMIENTOS!$E$4:$E$20000,MOVIMIENTOS!$B$4:$B$20000,$A51,MOVIMIENTOS!$I$4:$I$20000,"Transporte",MOVIMIENTOS!$H$4:$H$20000,"Gasto")+SUMIFS(FLEXIBLE!$C$4:$C$200,FLEXIBLE!$F$4:$F$200,$A51)) -> 65.13 | L51: =IF($A51="","",-SUMIFS(MOVIMIENTOS!$E$4:$E$20000,MOVIMIENTOS!$B$4:$B$20000,$A51,MOVIMIENTOS!$I$4:$I$20000,"Salud",MOVIMIENTOS!$H$4:$H$20000,"Gasto")) -> 20.46 | M51: =IF($A51="","",-SUMIFS(MOVIMIENTOS!$E$4:$E$20000,MOVIMIENTOS!$B$4:$B$20000,$A51,MOVIMIENTOS!$I$4:$I$20000,"Seguros",MOVIMIENTOS!$H$4:$H$20000,"Gasto")) -> 0 | N51: =IF($A51="","",-SUMIFS(MOVIMIENTOS!$E$4:$E$20000,MOVIMIENTOS!$B$4:$B$20000,$A51,MOVIMIENTOS!$I$4:$I$20000,"Personal",MOVIMIENTOS!$H$4:$H$20000,"Gasto")) -> 70.42 | O51: =IF($A51="","",-SUMIFS(MOVIMIENTOS!$E$4:$E$20000,MOVIMIENTOS!$B$4:$B$20000,$A51,MOVIMIENTOS!$I$4:$I$20000,"Ocio",MOVIMIENTOS!$H$4:$H$20000,"Gasto")) -> 16.79 | P51: =IF($A51="","",-SUMIFS(MOVIMIENTOS!$E$4:$E$20000,MOVIMIENTOS!$B$4:$B$20000,$A51,MOVIMIENTOS!$I$4:$I$20000,"Viajes",MOVIMIENTOS!$H$4:$H$20000,"Gasto")) -> 150 | Q51: =IF($A51="","",-SUMIFS(MOVIMIENTOS!$E$4:$E$20000,MOVIMIENTOS!$B$4:$B$20000,$A51,MOVIMIENTOS!$I$4:$I$20000,"Efectivo",MOVIMIENTOS!$H$4:$H$20000,"Gasto")) -> 0 | R51: =IF($A51="","",-SUMIFS(MOVIMIENTOS!$E$4:$E$20000,MOVIMIENTOS!$B$4:$B$20000,$A51,MOVIMIENTOS!$I$4:$I$20000,"Otros",MOVIMIENTOS!$H$4:$H$20000,"Gasto")) -> 0
A52: =IF('MIS DATOS'!A14="","",'MIS DATOS'!A14) -> 46174 | B52: =IF($A52="","",'MIS DATOS'!B14) -> 9281.91 | C52: =IF($A52="","",'MIS DATOS'!C14) -> 1360.91 | D52: =IF($A52="","",'MIS DATOS'!D14) -> 55001.69 | E52: =IF($A52="","",'MIS DATOS'!G14) -> 4492.75 | F52: =IF($A52="","",'MIS DATOS'!H14) -> 1703.73 | G52: =IF($A52="","",'MIS DATOS'!I14) -> 2789.02 | H52: =IF($A52="","",'MIS DATOS'!N14) -> 1 | I52: =IF($A52="","",-SUMIFS(MOVIMIENTOS!$E$4:$E$20000,MOVIMIENTOS!$B$4:$B$20000,$A52,MOVIMIENTOS!$I$4:$I$20000,"Casa",MOVIMIENTOS!$H$4:$H$20000,"Gasto")) -> 976.33 | J52: =IF($A52="","",-SUMIFS(MOVIMIENTOS!$E$4:$E$20000,MOVIMIENTOS!$B$4:$B$20000,$A52,MOVIMIENTOS!$I$4:$I$20000,"Comida",MOVIMIENTOS!$H$4:$H$20000,"Gasto")+SUMIFS(FLEXIBLE!$B$4:$B$200,FLEXIBLE!$F$4:$F$200,$A52)) -> 397.01 | K52: =IF($A52="","",-SUMIFS(MOVIMIENTOS!$E$4:$E$20000,MOVIMIENTOS!$B$4:$B$20000,$A52,MOVIMIENTOS!$I$4:$I$20000,"Transporte",MOVIMIENTOS!$H$4:$H$20000,"Gasto")+SUMIFS(FLEXIBLE!$C$4:$C$200,FLEXIBLE!$F$4:$F$200,$A52)) -> 107.23 | L52: =IF($A52="","",-SUMIFS(MOVIMIENTOS!$E$4:$E$20000,MOVIMIENTOS!$B$4:$B$20000,$A52,MOVIMIENTOS!$I$4:$I$20000,"Salud",MOVIMIENTOS!$H$4:$H$20000,"Gasto")) -> 16.47 | M52: =IF($A52="","",-SUMIFS(MOVIMIENTOS!$E$4:$E$20000,MOVIMIENTOS!$B$4:$B$20000,$A52,MOVIMIENTOS!$I$4:$I$20000,"Seguros",MOVIMIENTOS!$H$4:$H$20000,"Gasto")) -> 0 | N52: =IF($A52="","",-SUMIFS(MOVIMIENTOS!$E$4:$E$20000,MOVIMIENTOS!$B$4:$B$20000,$A52,MOVIMIENTOS!$I$4:$I$20000,"Personal",MOVIMIENTOS!$H$4:$H$20000,"Gasto")) -> 41.74 | O52: =IF($A52="","",-SUMIFS(MOVIMIENTOS!$E$4:$E$20000,MOVIMIENTOS!$B$4:$B$20000,$A52,MOVIMIENTOS!$I$4:$I$20000,"Ocio",MOVIMIENTOS!$H$4:$H$20000,"Gasto")) -> 14.95 | P52: =IF($A52="","",-SUMIFS(MOVIMIENTOS!$E$4:$E$20000,MOVIMIENTOS!$B$4:$B$20000,$A52,MOVIMIENTOS!$I$4:$I$20000,"Viajes",MOVIMIENTOS!$H$4:$H$20000,"Gasto")) -> 150 | Q52: =IF($A52="","",-SUMIFS(MOVIMIENTOS!$E$4:$E$20000,MOVIMIENTOS!$B$4:$B$20000,$A52,MOVIMIENTOS!$I$4:$I$20000,"Efectivo",MOVIMIENTOS!$H$4:$H$20000,"Gasto")) -> 0 | R52: =IF($A52="","",-SUMIFS(MOVIMIENTOS!$E$4:$E$20000,MOVIMIENTOS!$B$4:$B$20000,$A52,MOVIMIENTOS!$I$4:$I$20000,"Otros",MOVIMIENTOS!$H$4:$H$20000,"Gasto")) -> 0
A53: =IF('MIS DATOS'!A15="","",'MIS DATOS'!A15) -> 46204 | B53: =IF($A53="","",'MIS DATOS'!B15) -> 9973.79 | C53: =IF($A53="","",'MIS DATOS'!C15) -> 1396.85 | D53: =IF($A53="","",'MIS DATOS'!D15) -> 55336.25 | E53: =IF($A53="","",'MIS DATOS'!G15) -> 2768.17 | F53: =IF($A53="","",'MIS DATOS'!H15) -> 1750.81 | G53: =IF($A53="","",'MIS DATOS'!I15) -> 1017.36 | H53: =IF($A53="","",'MIS DATOS'!N15) -> 1 | I53: =IF($A53="","",-SUMIFS(MOVIMIENTOS!$E$4:$E$20000,MOVIMIENTOS!$B$4:$B$20000,$A53,MOVIMIENTOS!$I$4:$I$20000,"Casa",MOVIMIENTOS!$H$4:$H$20000,"Gasto")) -> 932.54 | J53: =IF($A53="","",-SUMIFS(MOVIMIENTOS!$E$4:$E$20000,MOVIMIENTOS!$B$4:$B$20000,$A53,MOVIMIENTOS!$I$4:$I$20000,"Comida",MOVIMIENTOS!$H$4:$H$20000,"Gasto")+SUMIFS(FLEXIBLE!$B$4:$B$200,FLEXIBLE!$F$4:$F$200,$A53)) -> 430.95 | K53: =IF($A53="","",-SUMIFS(MOVIMIENTOS!$E$4:$E$20000,MOVIMIENTOS!$B$4:$B$20000,$A53,MOVIMIENTOS!$I$4:$I$20000,"Transporte",MOVIMIENTOS!$H$4:$H$20000,"Gasto")+SUMIFS(FLEXIBLE!$C$4:$C$200,FLEXIBLE!$F$4:$F$200,$A53)) -> 103 | L53: =IF($A53="","",-SUMIFS(MOVIMIENTOS!$E$4:$E$20000,MOVIMIENTOS!$B$4:$B$20000,$A53,MOVIMIENTOS!$I$4:$I$20000,"Salud",MOVIMIENTOS!$H$4:$H$20000,"Gasto")) -> 23.93 | M53: =IF($A53="","",-SUMIFS(MOVIMIENTOS!$E$4:$E$20000,MOVIMIENTOS!$B$4:$B$20000,$A53,MOVIMIENTOS!$I$4:$I$20000,"Seguros",MOVIMIENTOS!$H$4:$H$20000,"Gasto")) -> 0 | N53: =IF($A53="","",-SUMIFS(MOVIMIENTOS!$E$4:$E$20000,MOVIMIENTOS!$B$4:$B$20000,$A53,MOVIMIENTOS!$I$4:$I$20000,"Personal",MOVIMIENTOS!$H$4:$H$20000,"Gasto")) -> 96.6 | O53: =IF($A53="","",-SUMIFS(MOVIMIENTOS!$E$4:$E$20000,MOVIMIENTOS!$B$4:$B$20000,$A53,MOVIMIENTOS!$I$4:$I$20000,"Ocio",MOVIMIENTOS!$H$4:$H$20000,"Gasto")) -> 13.79 | P53: =IF($A53="","",-SUMIFS(MOVIMIENTOS!$E$4:$E$20000,MOVIMIENTOS!$B$4:$B$20000,$A53,MOVIMIENTOS!$I$4:$I$20000,"Viajes",MOVIMIENTOS!$H$4:$H$20000,"Gasto")) -> 150 | Q53: =IF($A53="","",-SUMIFS(MOVIMIENTOS!$E$4:$E$20000,MOVIMIENTOS!$B$4:$B$20000,$A53,MOVIMIENTOS!$I$4:$I$20000,"Efectivo",MOVIMIENTOS!$H$4:$H$20000,"Gasto")) -> 0 | R53: =IF($A53="","",-SUMIFS(MOVIMIENTOS!$E$4:$E$20000,MOVIMIENTOS!$B$4:$B$20000,$A53,MOVIMIENTOS!$I$4:$I$20000,"Otros",MOVIMIENTOS!$H$4:$H$20000,"Gasto")) -> 0
A54: =IF('MIS DATOS'!A16="","",'MIS DATOS'!A16) -> 46235 | B54: =IF($A54="","",'MIS DATOS'!B16) -> 10211.08 | C54: =IF($A54="","",'MIS DATOS'!C16) -> 1387.77 | D54: =IF($A54="","",'MIS DATOS'!D16) -> 55671.02 | E54: =IF($A54="","",'MIS DATOS'!G16) -> 2300.87 | F54: =IF($A54="","",'MIS DATOS'!H16) -> 1666.68 | G54: =IF($A54="","",'MIS DATOS'!I16) -> 634.19 | H54: =IF($A54="","",'MIS DATOS'!N16) -> 1 | I54: =IF($A54="","",-SUMIFS(MOVIMIENTOS!$E$4:$E$20000,MOVIMIENTOS!$B$4:$B$20000,$A54,MOVIMIENTOS!$I$4:$I$20000,"Casa",MOVIMIENTOS!$H$4:$H$20000,"Gasto")) -> 1004.77 | J54: =IF($A54="","",-SUMIFS(MOVIMIENTOS!$E$4:$E$20000,MOVIMIENTOS!$B$4:$B$20000,$A54,MOVIMIENTOS!$I$4:$I$20000,"Comida",MOVIMIENTOS!$H$4:$H$20000,"Gasto")+SUMIFS(FLEXIBLE!$B$4:$B$200,FLEXIBLE!$F$4:$F$200,$A54)) -> 363.47 | K54: =IF($A54="","",-SUMIFS(MOVIMIENTOS!$E$4:$E$20000,MOVIMIENTOS!$B$4:$B$20000,$A54,MOVIMIENTOS!$I$4:$I$20000,"Transporte",MOVIMIENTOS!$H$4:$H$20000,"Gasto")+SUMIFS(FLEXIBLE!$C$4:$C$200,FLEXIBLE!$F$4:$F$200,$A54)) -> 80.99 | L54: =IF($A54="","",-SUMIFS(MOVIMIENTOS!$E$4:$E$20000,MOVIMIENTOS!$B$4:$B$20000,$A54,MOVIMIENTOS!$I$4:$I$20000,"Salud",MOVIMIENTOS!$H$4:$H$20000,"Gasto")) -> 11.89 | M54: =IF($A54="","",-SUMIFS(MOVIMIENTOS!$E$4:$E$20000,MOVIMIENTOS!$B$4:$B$20000,$A54,MOVIMIENTOS!$I$4:$I$20000,"Seguros",MOVIMIENTOS!$H$4:$H$20000,"Gasto")) -> 0 | N54: =IF($A54="","",-SUMIFS(MOVIMIENTOS!$E$4:$E$20000,MOVIMIENTOS!$B$4:$B$20000,$A54,MOVIMIENTOS!$I$4:$I$20000,"Personal",MOVIMIENTOS!$H$4:$H$20000,"Gasto")) -> 46.08 | O54: =IF($A54="","",-SUMIFS(MOVIMIENTOS!$E$4:$E$20000,MOVIMIENTOS!$B$4:$B$20000,$A54,MOVIMIENTOS!$I$4:$I$20000,"Ocio",MOVIMIENTOS!$H$4:$H$20000,"Gasto")) -> 9.48 | P54: =IF($A54="","",-SUMIFS(MOVIMIENTOS!$E$4:$E$20000,MOVIMIENTOS!$B$4:$B$20000,$A54,MOVIMIENTOS!$I$4:$I$20000,"Viajes",MOVIMIENTOS!$H$4:$H$20000,"Gasto")) -> 150 | Q54: =IF($A54="","",-SUMIFS(MOVIMIENTOS!$E$4:$E$20000,MOVIMIENTOS!$B$4:$B$20000,$A54,MOVIMIENTOS!$I$4:$I$20000,"Efectivo",MOVIMIENTOS!$H$4:$H$20000,"Gasto")) -> 0 | R54: =IF($A54="","",-SUMIFS(MOVIMIENTOS!$E$4:$E$20000,MOVIMIENTOS!$B$4:$B$20000,$A54,MOVIMIENTOS!$I$4:$I$20000,"Otros",MOVIMIENTOS!$H$4:$H$20000,"Gasto")) -> 0
